Workbook

Sheet Summary
B2: Tumble Wash Laundromat: underwriting summary
B3: 1147 Summit Ave, Jersey City NJ. BizBuySell #2564518. Model as of 2026-10-16. Change assumptions on the Inputs sheet.
B5: Deal
B6: Asking price | C6: =Price -> 450000
B7: Total cash at close (price + closing + working capital) | C7: =TotalInvest -> 480000
B8: Capex scenario selected (1 keep/repair, 2 washers now, 3 full retool, 4 bear) | C8: =CapexScenario -> 1
B9: Equipment capex over the lease (inflated) | C9: =-SUM(Projection!C53:T53) -> 655956.02
B11: Earnings: broker vs. underwritten (Year 1)
C12: Broker | D12: Underwritten | E12: Difference
B13: Revenue | C13: ='Seller Recast'!C9 -> 376200 | D13: ='Seller Recast'!D9 -> 370170 | E13: ='Seller Recast'!E9 -> -6030
B14: Operating expenses | C14: ='Seller Recast'!C28 -> 213780 | D14: ='Seller Recast'!D28 -> 262202.9 | E14: ='Seller Recast'!E28 -> 48422.9
B15: NOI, absentee | C15: ='Seller Recast'!C29 -> 162420 | D15: ='Seller Recast'!D29 -> 107967.1 | E15: ='Seller Recast'!E29 -> -54452.9
B16: Broker's stated NOI / SDE (as listed) | C16: ='Seller Recast'!C31 -> 177720
B17: SDE if Ryan works his hours | D17: =Projection!D49 -> 150191.1
B18: NOI after average equipment reserve | D18: ='Seller Recast'!D40 -> 69381.452
B19: Ask as a multiple of underwritten absentee NOI | D19: =Price/'Seller Recast'!D29 -> 4.1679363
B21: Returns
B22: Pre-tax unlevered IRR, 17 years (absentee) | C22: =Projection!C58 -> 0.17525465
B23: Year-1 cash-on-cash, pre-tax | C23: =Projection!C59 -> 0.22493146
B24: After tax, family level | C24: NPV | D24: IRR | E24: Total tax 1-17 | F24: Year-1 tax
B25: A Ryan owns (gift), single-member LLC | C25: =Structures!C101 -> 388418.1 | D25: =Structures!D101 -> 0.19149462 | E25: =Structures!E101 -> 935027.66 | F25: =Structures!F101 -> 17890.201
B26: B Parents own, passive, no passive income | C26: =Structures!C102 -> 353962.62 | D26: =Structures!D102 -> 0.18300719 | E26: =Structures!E102 -> 589953.97 | F26: =Structures!F102 -> 4437.1989
B27: C Parents own, passive, with passive income | C27: =Structures!C103 -> 371078.76 | D27: =Structures!D103 -> 0.19066626 | E27: =Structures!E103 -> 589953.97 | F27: =Structures!F103 -> 3335.7757
B28: D Ryan owns, AFR loan from parents, S-corp later | C28: =Structures!C104 -> 402532.12 | D28: =Structures!D104 -> 0.19196049 | E28: =Structures!E104 -> 784109.29 | F28: =Structures!F104 -> 9394.8585
B30: Value
B31: Fair value range, low | C31: =Valuation!C29 -> 323901.3
B32: Fair value range, high | C32: =Valuation!D29 -> 377884.85
B33: Max price at pre-tax target return | C33: =Valuation!C19 -> 536926.08
B34: Suggested opening offer | C34: =Valuation!C31 -> 320000
B35: Walk-away price | C35: =Valuation!C32 -> 380000
B37: Scenario snapshot (values pasted by build script; rerun build_model.py after changing inputs)
B38: Case | C38: Yr-1 NOI | D38: Pre-tax IRR | E38: A: NPV | F38: A: IRR | G38: B: NPV | H38: C: NPV | I38: D: NPV
B39: Base: ask $450,000, keep & repair machines | C39: 107967.1 | D39: 0.17525465 | E39: 388418.1 | F39: 0.19149462 | G39: 353962.62 | H39: 371078.76 | I39: 402532.12
B40: Offer $400,000 (90% of ask) | C40: 107967.1 | D40: 0.19350204 | E40: 429483.79 | F40: 0.21052159 | G40: 393738.09 | H40: 410132.2 | I40: 446056.2
B41: Offer $360,000 (80% of ask) | C41: 107967.1 | D41: 0.21094051 | E41: 462336.35 | F41: 0.22887458 | G41: 425645.85 | H41: 441535.16 | I41: 480875.47
B42: Replace washers at close (scenario 2) | C42: 125681.39 | D42: 0.15301022 | E42: 351994.02 | F42: 0.16214813 | G42: 325340.32 | H42: 349952.93 | I42: 378453.28
B43: Full retool at close (scenario 3) | C43: 137141.26 | D43: 0.14531154 | E43: 333913.45 | F43: 0.14938724 | G43: 313843.61 | H43: 345893.61 | I43: 377794.18
B44: Machines fail early (scenario 4) | C44: 107967.1 | D44: 0.15593412 | E44: 363555.84 | F44: 0.16787236 | G44: 340594.45 | H44: 368394.49 | I44: 391693.21
B45: Utilities +20% vs. the P&L | C45: 93711.1 | D45: 0.14628834 | E45: 299019.95 | F45: 0.1710263 | G45: 271285.47 | H45: 292063.53 | I45: 299868.17
B46: Revenue 10% below the P&L | C46: 75543.58 | D46: 0.10378068 | E46: 170160.15 | F46: 0.14140232 | G46: 149259.43 | H46: 177502.7 | I46: 150340.18
B47: Ryan works 0 hrs (fully absentee) | C47: 107967.1 | D47: 0.17525465 | E47: 363971.78 | F47: 0.18299963 | G47: 332791.05 | H47: 349907.19 | I47: 376307.57
B48: No lease renewal (exit value $0) | C48: 107967.1 | D48: 0.16855561 | E48: 347647.95 | F48: 0.18724607 | G48: 313192.47 | H48: 330308.61 | I48: 361761.97
B49: Ryan's plan (owner hours, day manager) | C49: 107967.1 | D49: 0.15448053 | E49: 123518 | F49: 0.13048147 | G49: 124098.95 | H49: 143750.04 | I49: 93959.449
B50: BEAR case (cases.py) | C50: 54956.08 | D50: -0.035523348 | E50: -434432.02 | F50: -0.0090700708 | G50: -466194.47 | H50: -321789.98 | I50: -546970.49
... B55: Broker's expense assumptions | C55: 161998.2 | D55: 0.28508272 | E55: 672383.71 | F55: 0.25616327 | G55: 647983.37 | H55: 657739.91 | I55: 727817.49
B56: Static values from snapshot.py; each case changes only the listed inputs from the base. NPV at the Inputs discount rate.

Sheet Inputs
B2: Inputs: Tumble Wash Laundromat, 1147 Summit Ave, Jersey City NJ
B3: Blue = hardcoded input. Yellow = key assumption / please confirm. Year 1 = first 12 months of ownership (assumed calendar 2027). Edit only column C.
B6: Deal
B7: Purchase price | C7: 450000 | D7: Listing ask (BizBuySell #2564518). Change to test offers.
B8: Closing costs (legal, accounting/QoE, inspection, bulk-sale filing) | C8: 20000 | D8: Estimate. Capitalized with goodwill (15-yr).
B9: Opening working capital (card float, supplies, cash reserve) | C9: 10000 | D9: Estimate. Recovered at exit.
B10: Form 8594 allocation: machines, card system, ATM, vending (Class V) | C10: 60000 | D10: Estimate: ~69 machines at 15 yrs old; support with a distributor appraisal. Seller will want this low (recapture).
B11: Form 8594 allocation: leasehold improvements (curbs, tile, plumbing troughs, venting) | C11: 25000 | D11: Estimate. Qualified improvement property (15-yr, bonus-eligible).
B12: Form 8594 allocation: seller non-compete | C12: 15000 | D12: Estimate. Sec. 197, 15-yr. Negotiate a 5-yr / 3-mile non-compete.
B14: Revenue (Year 1, annual, from the broker P&L unless noted)
B15: Self-serve washer/dryer revenue | C15: 216000 | D15: P&L $18,000/mo; listing $4,150/wk. Verify with 24 months of CCI card-system reports.
B16: Wash-dry-fold pounds per month | C16: 8000 | D16: P&L ~8,000 lb/mo (listing 1,846 lb/wk). Verify in Cents POS.
B17: Wash-dry-fold price per lb (Year 1) | C17: 1.25 | D17: P&L/listing. Local range $1.00-1.25; delivery $1.25-1.49 (research/opex.md).
B18: Wash-dry-fold price per lb after increase | C18: 1.5 | D18: Assumption: raise to $1.50 (CLA survey mode $1.50-1.99).
B19: Year the W&F price increase takes effect | C19: 2 | D19: Assumption.
B20: W&F volume lost when price rises | C20: 0.1 | D20: Assumption.
B21: Drop-off dry cleaning revenue | C21: 6000 | D21: P&L $500/mo.
B22: ATM revenue | C22: 6000 | D22: P&L $500/mo. Seller-owned ATM included. Verify.
B23: Soap vending revenue | C23: 15000 | D23: P&L $1,250/mo. NJ sales tax applies to detergent; confirm whether P&L figure is net of tax.
B24: Snack/soda vending revenue | C24: 7200 | D24: P&L $600/mo.
B25: Game (quarter pusher / arcade) revenue | C25: 6000 | D25: P&L $500/mo. Unverifiable cash; verify.
B26: Share of ancillary (non-laundry) revenue underwritten | C26: 0.85 | D26: Haircut on cash-heavy, unverifiable lines (dry cleaning, ATM, vending, games).
... B30: Self-serve revenue lift from a fully new washer/dryer fleet | C30: 0.05 | D30: Equipment thread base case (5%).
B32: Operating expenses (Year 1)
B33: Rent incl. NNN, CAM and any utilities the lease covers (annual) | C33: 33096 | D33: $2,758/mo per listing; +~3%/yr; ~17 yrs left. Confirm escalation date and that sewer is truly included (P&L says so).
B34: Rent escalation per year | C34: 0.03 | D34: Listing: approx. 3%/yr.
B35: Paid attendant hours per week (absentee model) | C35: 91 | D35: P&L: 91 hrs/wk (store open 112, 21 unattended).
B36: Attendant wage per hour (Year 1) | C36: 17.5 | D36: NJ minimum wage $16.48 from 1/1/2027; local attendants ~$16.50-18 (research/opex.md). P&L uses $16.50.
B37: Wage growth per year | C37: 0.035 | D37: NJ minimum wage is CPI-indexed.
B38: Employer payroll burden (FICA, FUTA, state UI/DI, local payroll tax, workers' comp, sick leave) | C38: 0.16 | D38: research/opex.md: ~16% all-in. P&L shows N/A for payroll tax and WC.
B39: Water and sewer (annual) | C39: 32400 | D39: P&L $2,700/mo. JCMUA rates rise ~5%/yr (2026 $17.82 per 1,000 gal combined).
B40: Gas + electric (annual) | C40: 32400 | D40: P&L $2,700/mo on the 'Gas' line, electric marked 'Inc'. Our read: one combined PSE&G bill. If electric is extra, add it in the next row.
B41: Additional electric not in the broker P&L (annual) | C41: 0 | D41: Set to ~$10-15k if 12 months of PSE&G bills show electric is billed separately.
B42: Utility contingency (unverified bills) | C42: 0.1 | D42: Assumption until 12-24 months of bills are reviewed.
B43: Utility cost inflation per year | C43: 0.04 | D43: PSE&G/JCMUA trend (research/opex.md).
B44: Utility saving with a fully new fleet | C44: 0.2 | D44: Equipment thread: new washers ~25% less water/energy; blended ~20%.
... B61: General expense inflation | C61: 0.03 | D61: Assumption.
B63: Owner time (Ryan)
B64: Hours per week Ryan works in the store (replacing paid attendants) | C64: 40 | D64: Assumption. 500+ hrs/yr (~10/wk) is the material-participation test. Broker: plan 10-15 hrs/wk even 'absentee'.
B66: Owner hand-off and delivery/commercial growth (defaults = off; see Summary scenario table)
B67: Year Ryan steps back to a management role | C67: 2 | D67: Ryan: full-time in Year 1, then train staff to take over.
B68: Ryan's hours per week in the store after the hand-off | C68: 40 | D68: Default 40 = no hand-off. Ryan's plan: ~10 (management, books, marketing, contracts).
B69: Day-manager hours per week (lead attendant who covers Ryan's shifts) from hand-off | C69: 0 | D69: Default 0 = off. Plan: 40.
B70: Day-manager pay premium over attendant wage, per hour | C70: 4.5 | D70: ~$22/hr vs $17.50 attendant (research/opex.md range).
B71: First year of the pickup/delivery + commercial program | C71: 2 | D71: Assumption.
B72: Delivery/commercial pounds per month, first year | C72: 0 | D72: Default 0 = off. Plan: 2,000 lb/mo.
B73: Delivery/commercial pounds per month, later years | C73: 0 | D73: Default 0 = off. Plan: 5,000 lb/mo (e.g. ~60 residential customers + 2-4 Airbnb/gym/restaurant accounts).
B74: Delivery/commercial price per lb | C74: 1.95 | D74: Jersey City delivery $1.25-1.49 at local stores, app services ~$2.65 (research/opex.md); commercial linens taxable 6.625% (passed through).
B75: Pounds processed (wash, dry, fold) per labor hour | C75: 30 | D75: Industry rule of thumb 25-35 lb/hr.
B76: Share of processing labor that is new paid hours (rest absorbed by idle attendant time) | C76: 0.6 | D76: Attendants already on shift have slack during slow hours.
B77: Utilities per lb processed | C77: 0.1 | D77: Estimate: water, gas, electric for wash + dry.
B78: Driver hours per week once the program runs | C78: 20 | D78: Part-time driver; routes 2x/day, 5 days.
... B80: Van lease, fuel, commercial auto insurance per year | C80: 12000 | D80: Assumption ~$1,000/mo. Alternative: per-stop courier.
B82: Equipment capital plan
B83: Capex scenario (1 = keep & repair; 2 = washers now; 3 = full retool at close; 4 = bear: machines fail early). See Depreciation sheet. | C83: 1 | D83: Equipment thread (revised): washers ~15 yrs old vs 12-15 yr CLA average, so replace in yrs 1-4; base yr 4 (/mnt/project-files/equipment/README.md s.2).
B84: Equipment price inflation per year (capex schedule is in today's dollars) | C84: 0.03 | D84: Assumption.
B85: Federal/state MACRS recovery period for machines (5 or 7) | C85: 5 | D85: Asset class 57.0 = 5-yr (research/tax.md). Confirm with CPA.
B86: Federal bonus depreciation % | C86: 1 | D86: OBBBA: 100% permanent for property acquired after 1/19/2025; used property from unrelated seller qualifies.
B87: State Section 179 limit per year (NJ: $25k, no bonus) | C87: 25000 | D87: NJ decoupled: $25k cap, no bonus (GIT-DEP).
B89: Tax rates and limits
B90: Ryan: federal marginal income tax rate | C90: 0.22 | D90: Placeholder. Depends on Ryan's other income. Please confirm.
B91: Ryan: state marginal rate | C91: 0.0637 | D91: NJ GIT bracket $75k-$500k (single).
B92: Ryan: other income available to absorb business losses (federal) | C92: 50000 | D92: Structure memo: ~$50k role at the parents' practice. Losses above this become an NOL carryforward.
B93: Excess business loss limit, single | C93: 256000 | D93: Rev. Proc. 2025-32.
B94: Social Security wage base | C94: 184500 | D94: SSA. Grown with wages in the model.
B95: QBI deduction rate (Sec. 199A) | C95: 0.2 | D95: Permanent under OBBBA.
B96: Parents: federal marginal rate | C96: 0.37 | D96: Assumed top bracket (physicians). Confirm.
B97: Net investment income tax on passive income | C97: 0.038 | D97: Sec. 1411; applies to passive owners.
B98: Parents: state marginal rate | C98: 0.0897 | D98: NJ GIT $500k-$1M bracket; 10.75% above $1M.
B99: Parents: other net passive income each year (structure C only) | C99: 250000 | D99: Placeholder, e.g. rental K-1s from their investment LLCs. Structure B assumes $0.
B100: Parents: other state partnership/business income for netting (structure C only) | C100: 250000 | D100: Placeholder: practice/investment partnership K-1s (NJ-BUS-2 netting).
B101: Blended tax rate on exit proceeds | C101: 0.3 | D101: Mix of Sec. 1245 recapture (ordinary) and capital gain.
B103: Family capital (structure D loan terms; structure E uses the same amount as parents' capital)
B104: Parents' funding (D: AFR loan to Ryan's LLC; E: capital into OpCo) | C104: 500000 | D104: Structure memo: ~$500k AFR note, interest-only.
B105: Loan interest rate (AFR) | C105: 0.0461 | D105: Oct 2026 mid-term AFR 4.61% (Rev. Rul. 2026-19); long-term 5.22%.
B106: Principal forgiven each year (annual-exclusion gifts) | C106: 38000 | D106: $19k x 2 parents (2026 exclusion).
B107: First year taxed as an S-corp | C107: 2 | D107: Structure memo: elect from Year 2.
B108: Ryan's reasonable salary from the S-corp (Year of election) | C108: 60000 | D108: Assumption; grows with wages. Must be defensible for ~40 hrs/wk management + attendant work.
B109: Payroll taxes on Ryan's salary (FICA both halves + state UI/DI + local payroll tax) | C109: 0.183 | D109: 15.3% + ~3.0% (research/opex.md); JC 1% does not apply if Ryan lives in Jersey City.
B111: Valuation
B112: Discount rate (after-tax, all-cash equity) | C112: 0.1 | D112: Small-business equity; parents' cash alternative ~4-5% in Treasuries.
B113: Target pre-tax unlevered return for max-price test | C113: 0.15 | D113: Assumption.
B114: Exit value at end of Year 17, multiple of Year-17 EBITDA | C114: 1.5 | D114: Lease ends in Year 17; value depends on a renewal. 0 = walk away.
B116: Derived (formulas)
B117: Goodwill + going concern (Class VII) incl. closing costs | C117: =Price+ClosingCosts-AllocEquip-AllocLHI-AllocNoncompete -> 370000
B118: Total cash at close (price + closing + working capital) | C118: =Price+ClosingCosts+WorkingCap -> 480000
B119: Ancillary revenue underwritten (Year 1) | C119: =(DryClean+ATM+SoapVend+SnackVend+GameVend)*AncRealize -> 34170

Sheet Seller Recast
B2: Broker P&L vs. underwritten Year 1 (annual)
B3: Broker column = proforma P&L dated 10-4-26 x 12 (photo IMG_1029), annualized. Underwritten = Projection Year 1.
B5: Line | C5: Broker P&L | D5: Underwritten Yr 1 | E5: Difference | F5: Why
B6: Self-serve | C6: 216000 | D6: =Projection!D11 -> 216000 | E6: =D6-C6 -> 0 | F6: Same; verify with CCI reports.
B7: Wash-dry-fold | C7: 120000 | D7: =Projection!D14 -> 120000 | E7: =D7-C7 -> 0 | F7: Same in Year 1; price increase starts Year 2.
B8: Ancillary (dry cleaning, ATM, vending, games) | C8: 40200 | D8: =Projection!D15 -> 34170 | E8: =D8-C8 -> -6030 | F8: Haircut on unverifiable cash lines.
B9: TOTAL REVENUE | C9: =SUM(C6:C8) -> 376200 | D9: =Projection!D18 -> 370170 | E9: =D9-C9 -> -6030 | F9: Listing says $372k; P&L sums to $376k.
B10: Rent incl. NNN/CAM | C10: 33096 | D10: =Projection!D21 -> 33096 | E10: =D10-C10 -> 0 | F10: From the lease.
B11: Payroll wages | C11: 78084 | D11: =Projection!D22 -> 82810 | E11: =D11-C11 -> 4726 | F11: P&L: 91 hrs x $16.50. 2027 NJ minimum wage is $16.48, so $17.50 to keep staff.
B12: Payroll taxes, workers' comp, sick leave | C12: 0 | D12: =Projection!D23 -> 13249.6 | E12: =D12-C12 -> 13249.6 | F12: P&L shows N/A. Legally required.
B13: Water and sewer | C13: 32400 | D13: =Projection!D24 -> 35640 | E13: =D13-C13 -> 3240 | F13: Plus 10% contingency until bills are seen.
B14: Gas + electric | C14: 32400 | D14: =Projection!D25 -> 35640 | E14: =D14-C14 -> 3240 | F14: Electric marked 'Inc'; confirm with bills.
B15: Repairs & maintenance | C15: 5400 | D15: =Projection!D26 -> 12000 | E15: =D15-C15 -> 6600 | F15: 15-yr fleet; seller likely does own repairs unpaid.
B16: Insurance | C16: 2880 | D16: =Projection!D27 -> 7500 | E16: =D16-C16 -> 4620 | F16: $240/mo is too low for property + GL + equipment breakdown.
B17: Card processing | C17: 4800 | D17: =Projection!D28 -> 4804.8 | E17: =D17-C17 -> 4.8
B18: POS system & cards | C18: 6600 | D18: =Projection!D29 -> 6600 | E18: =D18-C18 -> 0
B19: W&F supplies | C19: 3600 | D19: =Projection!D30 -> 3600 | E19: =D19-C19 -> 0
B20: Vending COGS + dry cleaning cost | C20: 10500 | D20: =Projection!D31 -> 8965.8 | E20: =D20-C20 -> -1534.2
B21: Phone, alarm, trash | C21: 2220 | D21: =Projection!D32 -> 2595 | E21: =D21-C21 -> 375 | F21: Underwritten adds the $375/yr fire alarm noted on the P&L.
B22: Misc. supplies | C22: 1800 | D22: =Projection!D33 -> 1800 | E22: =D22-C22 -> 0
B23: Accounting, tax & legal | C23: 0 | D23: =Projection!D34 -> 5000 | E23: =D23-C23 -> 5000 | F23: Not in P&L.
B24: Licenses & fees | C24: 0 | D24: =Projection!D35 -> 1000 | E24: =D24-C24 -> 1000 | F24: Not in P&L.
B25: Payroll service | C25: 0 | D25: =Projection!D36 -> 1200 | E25: =D25-C25 -> 1200 | F25: Not in P&L.
B26: Marketing | C26: 0 | D26: =Projection!D37 -> 3000 | E26: =D26-C26 -> 3000 | F26: Not in P&L.
B27: Contingency | C27: 0 | D27: =Projection!D42 -> 3701.7 | E27: =D27-C27 -> 3701.7 | F27: 1% of revenue.
B28: TOTAL EXPENSES | C28: =SUM(C10:C27) -> 213780 | D28: =Projection!D43 -> 262202.9 | E28: =D28-C28 -> 48422.9 | F28: Broker's lines add to $17,815/mo; the P&L's TOTAL says $16,540.
B29: NET OPERATING INCOME (absentee) | C29: =C9-C28 -> 162420 | D29: =Projection!D45 -> 107967.1 | E29: =D29-C29 -> -54452.9 | F29: Broker's lines, added correctly: $162,420, not $177,720.
B31: Broker's stated NOI / SDE (as listed) | C31: 177720 | F31: P&L TOTAL omits vending COGS, dry cleaning cost and card fees ($1,275/mo). Lines added correctly give $162,420.
B32: Note: underwritten Year 1 uses the selected capex scenario; under scenarios 2/3 new machines lift revenue and cut utilities/repairs.
B34: Implied price multiples
B35: Ask / broker's stated NOI | D35: =Price/C31 -> 2.5320729
B36: Ask / underwritten NOI (absentee) | D36: =Price/D29 -> 4.1679363
B37: Ask / underwritten SDE (Ryan works his hours) | D37: =Price/Projection!D49 -> 2.9961829
B38: Ask / underwritten revenue | D38: =Price/D9 -> 1.2156577
B40: Underwritten NOI after equipment reserve (avg. annual capex) | D40: =D29-Projection!C60 -> 69381.452

Sheet Valuation
B2: Valuation: what is this store worth?
B3: Three approaches. Market multiples come from the Comps sheet and research/comps.md.
B5: Earnings bases (Year 1, underwritten)
B6: NOI, absentee (all hours paid) | C6: ='Seller Recast'!D29 -> 107967.1
B7: SDE, Ryan works his hours | C7: =Projection!D49 -> 150191.1
B8: NOI after equipment reserve | C8: ='Seller Recast'!D40 -> 69381.452
B9: Broker's stated NOI | C9: ='Seller Recast'!C31 -> 177720
B11: 1. Market approach: earnings x comparable multiples
B12: Multiple | C12: x | D12: x NOI | E12: x SDE | F12: x NOI after reserve
B13: Low (old fleet, NYC metro sold median less) | C13: 2.5 | D13: =$C13*$C$6 -> 269917.75 | E13: =$C13*$C$7 -> 375477.75 | F13: =$C13*$C$8 -> 173453.63 | G13: Sources: underwriting/research/comps.md (BizBuySell Insight 855 deals; 28 NYC-metro listings; Laundromat Resource rules of thumb)
B14: Sold-listing median, NYC metro | C14: 3.3 | D14: =$C14*$C$6 -> 356291.43 | E14: =$C14*$C$7 -> 495630.63 | F14: =$C14*$C$8 -> 228958.79
B15: National closed-deal median (BizBuySell 2021-25) | C15: 3.5 | D15: =$C15*$C$6 -> 377884.85 | E15: =$C15*$C$7 -> 525668.85 | F15: =$C15*$C$8 -> 242835.08
B16: Rule of thumb, 15+ yr lease, low rent | C16: 4 | D16: =$C16*$C$6 -> 431868.4 | E16: =$C16*$C$7 -> 600764.4 | F16: =$C16*$C$8 -> 277525.81
B18: 2. Income approach: price that still earns the target return
B19: Max price at pre-tax target return (absentee cash flows, selected capex) | C19: =(NPV(PreTaxTarget,Projection!D55:T55)+Projection!C53-ClosingCosts-WorkingCap) -> 536926.08 | G19: PV of Years 1-17 at the target, less Year-0 capex, closing costs and working capital.
B20: Max price at after-tax discount rate: structure A | C20: =Price+Structures!C101 -> 838418.1 | G20: Ask + NPV (approx.; taxes held at the current price's allocation).
B21: Max price at after-tax discount rate: structure B | C21: =Price+Structures!C102 -> 803962.62 | G21: Ask + NPV (approx.; taxes held at the current price's allocation).
B22: Max price at after-tax discount rate: structure C | C22: =Price+Structures!C103 -> 821078.76 | G22: Ask + NPV (approx.; taxes held at the current price's allocation).
B23: Max price at after-tax discount rate: structure D | C23: =Price+Structures!C104 -> 852532.12 | G23: Ask + NPV (approx.; taxes held at the current price's allocation).
B25: 3. Asset-light floor
B26: Used-equipment value + improvements (liquidation-ish floor) | C26: =AllocEquip+AllocLHI -> 85000
B28: Conclusion
B29: Fair value range: 3.0x (low) to 3.5x (high) underwritten absentee NOI | C29: =3*C6 -> 323901.3 | D29: =3.5*C6 -> 377884.85
B30: Asking price | C30: =Price -> 450000
B31: Suggested opening offer (3.0x absentee NOI, rounded) | C31: =ROUND(3*C6,-4) -> 320000
B32: Walk-away price (3.5x absentee NOI, rounded) | C32: =ROUND(3.5*C6,-4) -> 380000

Sheet Projection
B2: 17-year projection (pre-tax, absentee basis: every staffed hour is paid)
B3: Year 0 = closing. Taxes by ownership structure are on the Structures sheet.
B5: Year | C5: 0 | D5: 1 | E5: 2 | F5: 3 | G5: 4 | H5: 5 | I5: 6 | J5: 7 | K5: 8 | L5: 9 | M5: 10 | N5: 11 | O5: 12 | P5: 13 | Q5: 14 | R5: 15 | S5: 16 | T5: 17 | U5: Total 1-17
B6: Calendar year (assumed) | C6: 2026 | D6: 2027 | E6: 2028 | F6: 2029 | G6: 2030 | H6: 2031 | I6: 2032 | J6: 2033 | K6: 2034 | L6: 2035 | M6: 2036 | N6: 2037 | O6: 2038 | P6: 2039 | Q6: 2040 | R6: 2041 | S6: 2042 | T6: 2043
B7: Share of fleet new | C7: =Depreciation!C13 -> 0 | D7: =Depreciation!D13 -> 0 | E7: =Depreciation!E13 -> 0 | F7: =Depreciation!F13 -> 0 | G7: =Depreciation!G13 -> 0 | H7: =Depreciation!H13 -> 0.63914655 | I7: =Depreciation!I13 -> 0.63914655 | J7: =Depreciation!J13 -> 0.63914655 | ... T7: =Depreciation!T13 -> 1
B8: Years of growth (y-1) | D8: =D5-1 -> 0 | E8: =E5-1 -> 1 | F8: =F5-1 -> 2 | G8: =G5-1 -> 3 | H8: =H5-1 -> 4 | I8: =I5-1 -> 5 | J8: =J5-1 -> 6 | K8: =K5-1 -> 7 | ... T8: =T5-1 -> 16
B10: Revenue
B11: Self-serve wash & dry | D11: =SelfServe*(1+SSGrowth)^D$8*(1+RetoolLift*D$7) -> 216000 | E11: =SelfServe*(1+SSGrowth)^E$8*(1+RetoolLift*E$7) -> 222480 | F11: =SelfServe*(1+SSGrowth)^F$8*(1+RetoolLift*F$7) -> 229154.4 | G11: =SelfServe*(1+SSGrowth)^G$8*(1+RetoolLift*G$7) -> 236029.03 | H11: =SelfServe*(1+SSGrowth)^H$8*(1+RetoolLift*H$7) -> 250879.05 | I11: =SelfServe*(1+SSGrowth)^I$8*(1+RetoolLift*I$7) -> 258405.42 | J11: =SelfServe*(1+SSGrowth)^J$8*(1+RetoolLift*J$7) -> 266157.58 | K11: =SelfServe*(1+SSGrowth)^K$8*(1+RetoolLift*K$7) -> 274142.31 | ... T11: =SelfServe*(1+SSGrowth)^T$8*(1+RetoolLift*T$7) -> 363947.42 | U11: =SUM(D11:T11) -> 4856734.7
B12: W&F pounds | D12: =WFLbsMonth*12*IF(D$5>=WFPriceYear,1-WFVolLoss,1) -> 96000 | E12: =WFLbsMonth*12*IF(E$5>=WFPriceYear,1-WFVolLoss,1) -> 86400 | F12: =WFLbsMonth*12*IF(F$5>=WFPriceYear,1-WFVolLoss,1) -> 86400 | G12: =WFLbsMonth*12*IF(G$5>=WFPriceYear,1-WFVolLoss,1) -> 86400 | H12: =WFLbsMonth*12*IF(H$5>=WFPriceYear,1-WFVolLoss,1) -> 86400 | I12: =WFLbsMonth*12*IF(I$5>=WFPriceYear,1-WFVolLoss,1) -> 86400 | J12: =WFLbsMonth*12*IF(J$5>=WFPriceYear,1-WFVolLoss,1) -> 86400 | K12: =WFLbsMonth*12*IF(K$5>=WFPriceYear,1-WFVolLoss,1) -> 86400 | ... T12: =WFLbsMonth*12*IF(T$5>=WFPriceYear,1-WFVolLoss,1) -> 86400 | U12: =SUM(D12:T12) -> 1478400
B13: W&F price per lb | D13: =IF(D$5>=WFPriceYear,WFPriceNew,WFPrice)*(1+WFGrowth)^MAX(0,D$5-WFPriceYear) -> 1.25 | E13: =IF(E$5>=WFPriceYear,WFPriceNew,WFPrice)*(1+WFGrowth)^MAX(0,E$5-WFPriceYear) -> 1.5 | F13: =IF(F$5>=WFPriceYear,WFPriceNew,WFPrice)*(1+WFGrowth)^MAX(0,F$5-WFPriceYear) -> 1.545 | G13: =IF(G$5>=WFPriceYear,WFPriceNew,WFPrice)*(1+WFGrowth)^MAX(0,G$5-WFPriceYear) -> 1.59135 | H13: =IF(H$5>=WFPriceYear,WFPriceNew,WFPrice)*(1+WFGrowth)^MAX(0,H$5-WFPriceYear) -> 1.6390905 | I13: =IF(I$5>=WFPriceYear,WFPriceNew,WFPrice)*(1+WFGrowth)^MAX(0,I$5-WFPriceYear) -> 1.6882632 | J13: =IF(J$5>=WFPriceYear,WFPriceNew,WFPrice)*(1+WFGrowth)^MAX(0,J$5-WFPriceYear) -> 1.7389111 | K13: =IF(K$5>=WFPriceYear,WFPriceNew,WFPrice)*(1+WFGrowth)^MAX(0,K$5-WFPriceYear) -> 1.7910784 | ... T13: =IF(T$5>=WFPriceYear,WFPriceNew,WFPrice)*(1+WFGrowth)^MAX(0,T$5-WFPriceYear) -> 2.3369511
B14: Wash-dry-fold (incl. pickup & delivery) | D14: =D12*D13 -> 120000 | E14: =E12*E13 -> 129600 | F14: =F12*F13 -> 133488 | G14: =G12*G13 -> 137492.64 | H14: =H12*H13 -> 141617.42 | I14: =I12*I13 -> 145865.94 | J14: =J12*J13 -> 150241.92 | K14: =K12*K13 -> 154749.18 | ... T14: =T12*T13 -> 201912.58 | U14: =SUM(D14:T14) -> 2732331.8
B15: Ancillary (dry cleaning, ATM, vending, games), after haircut | D15: =AncYr1*(1+AncGrowth)^D$8 -> 34170 | E15: =AncYr1*(1+AncGrowth)^E$8 -> 34853.4 | F15: =AncYr1*(1+AncGrowth)^F$8 -> 35550.468 | G15: =AncYr1*(1+AncGrowth)^G$8 -> 36261.477 | H15: =AncYr1*(1+AncGrowth)^H$8 -> 36986.707 | I15: =AncYr1*(1+AncGrowth)^I$8 -> 37726.441 | J15: =AncYr1*(1+AncGrowth)^J$8 -> 38480.97 | K15: =AncYr1*(1+AncGrowth)^K$8 -> 39250.589 | ... T15: =AncYr1*(1+AncGrowth)^T$8 -> 46908.088 | U15: =SUM(D15:T15) -> 683812.46
B16: Delivery/commercial pounds | D16: =IF(D$5<DelivStart,0,IF(D$5=DelivStart,DelivLbsRamp,DelivLbsFull))*12 -> 0 | E16: =IF(E$5<DelivStart,0,IF(E$5=DelivStart,DelivLbsRamp,DelivLbsFull))*12 -> 0 | F16: =IF(F$5<DelivStart,0,IF(F$5=DelivStart,DelivLbsRamp,DelivLbsFull))*12 -> 0 | G16: =IF(G$5<DelivStart,0,IF(G$5=DelivStart,DelivLbsRamp,DelivLbsFull))*12 -> 0 | H16: =IF(H$5<DelivStart,0,IF(H$5=DelivStart,DelivLbsRamp,DelivLbsFull))*12 -> 0 | I16: =IF(I$5<DelivStart,0,IF(I$5=DelivStart,DelivLbsRamp,DelivLbsFull))*12 -> 0 | J16: =IF(J$5<DelivStart,0,IF(J$5=DelivStart,DelivLbsRamp,DelivLbsFull))*12 -> 0 | K16: =IF(K$5<DelivStart,0,IF(K$5=DelivStart,DelivLbsRamp,DelivLbsFull))*12 -> 0 | ... T16: =IF(T$5<DelivStart,0,IF(T$5=DelivStart,DelivLbsRamp,DelivLbsFull))*12 -> 0 | U16: =SUM(D16:T16) -> 0
B17: Pickup/delivery + commercial wash-dry-fold | D17: =D16*DelivPrice*(1+WFGrowth)^MAX(0,D$5-DelivStart) -> 0 | E17: =E16*DelivPrice*(1+WFGrowth)^MAX(0,E$5-DelivStart) -> 0 | F17: =F16*DelivPrice*(1+WFGrowth)^MAX(0,F$5-DelivStart) -> 0 | G17: =G16*DelivPrice*(1+WFGrowth)^MAX(0,G$5-DelivStart) -> 0 | H17: =H16*DelivPrice*(1+WFGrowth)^MAX(0,H$5-DelivStart) -> 0 | I17: =I16*DelivPrice*(1+WFGrowth)^MAX(0,I$5-DelivStart) -> 0 | J17: =J16*DelivPrice*(1+WFGrowth)^MAX(0,J$5-DelivStart) -> 0 | K17: =K16*DelivPrice*(1+WFGrowth)^MAX(0,K$5-DelivStart) -> 0 | ... T17: =T16*DelivPrice*(1+WFGrowth)^MAX(0,T$5-DelivStart) -> 0 | U17: =SUM(D17:T17) -> 0
B18: Total revenue | D18: =D11+D14+D15+D17 -> 370170 | E18: =E11+E14+E15+E17 -> 386933.4 | F18: =F11+F14+F15+F17 -> 398192.87 | G18: =G11+G14+G15+G17 -> 409783.15 | H18: =H11+H14+H15+H17 -> 429483.17 | I18: =I11+I14+I15+I17 -> 441997.8 | J18: =J11+J14+J15+J17 -> 454880.47 | K18: =K11+K14+K15+K17 -> 468142.07 | ... T18: =T11+T14+T15+T17 -> 612768.09 | U18: =SUM(D18:T18) -> 8272879
B20: Operating expenses
B21: Rent (incl. NNN, CAM, sewer) | D21: =RentYr1*(1+RentEsc)^D$8 -> 33096 | E21: =RentYr1*(1+RentEsc)^E$8 -> 34088.88 | F21: =RentYr1*(1+RentEsc)^F$8 -> 35111.546 | G21: =RentYr1*(1+RentEsc)^G$8 -> 36164.893 | H21: =RentYr1*(1+RentEsc)^H$8 -> 37249.84 | I21: =RentYr1*(1+RentEsc)^I$8 -> 38367.335 | J21: =RentYr1*(1+RentEsc)^J$8 -> 39518.355 | K21: =RentYr1*(1+RentEsc)^K$8 -> 40703.905 | ... T21: =RentYr1*(1+RentEsc)^T$8 -> 53109.364 | U21: =SUM(D21:T21) -> 720221.51
B22: Attendant wages | D22: =PaidHours*52*Wage*(1+WageGrowth)^D$8 -> 82810 | E22: =PaidHours*52*Wage*(1+WageGrowth)^E$8 -> 85708.35 | F22: =PaidHours*52*Wage*(1+WageGrowth)^F$8 -> 88708.142 | G22: =PaidHours*52*Wage*(1+WageGrowth)^G$8 -> 91812.927 | H22: =PaidHours*52*Wage*(1+WageGrowth)^H$8 -> 95026.38 | I22: =PaidHours*52*Wage*(1+WageGrowth)^I$8 -> 98352.303 | J22: =PaidHours*52*Wage*(1+WageGrowth)^J$8 -> 101794.63 | K22: =PaidHours*52*Wage*(1+WageGrowth)^K$8 -> 105357.45 | ... T22: =PaidHours*52*Wage*(1+WageGrowth)^T$8 -> 143591.38 | U22: =SUM(D22:T22) -> 1880202.4
B23: Employer payroll taxes, workers' comp, sick leave | D23: =D22*Burden -> 13249.6 | E23: =E22*Burden -> 13713.336 | F23: =F22*Burden -> 14193.303 | G23: =G22*Burden -> 14690.068 | H23: =H22*Burden -> 15204.221 | I23: =I22*Burden -> 15736.368 | J23: =J22*Burden -> 16287.141 | K23: =K22*Burden -> 16857.191 | ... T23: =T22*Burden -> 22974.621 | U23: =SUM(D23:T23) -> 300832.38
B24: Water | D24: =WaterYr1*(1+UtilCont)*(1+UtilInfl)^D$8*(1-UtilSave*D$7) -> 35640 | E24: =WaterYr1*(1+UtilCont)*(1+UtilInfl)^E$8*(1-UtilSave*E$7) -> 37065.6 | F24: =WaterYr1*(1+UtilCont)*(1+UtilInfl)^F$8*(1-UtilSave*F$7) -> 38548.224 | G24: =WaterYr1*(1+UtilCont)*(1+UtilInfl)^G$8*(1-UtilSave*G$7) -> 40090.153 | H24: =WaterYr1*(1+UtilCont)*(1+UtilInfl)^H$8*(1-UtilSave*H$7) -> 36364.075 | I24: =WaterYr1*(1+UtilCont)*(1+UtilInfl)^I$8*(1-UtilSave*I$7) -> 37818.638 | J24: =WaterYr1*(1+UtilCont)*(1+UtilInfl)^J$8*(1-UtilSave*J$7) -> 39331.383 | K24: =WaterYr1*(1+UtilCont)*(1+UtilInfl)^K$8*(1-UtilSave*K$7) -> 40904.638 | ... T24: =WaterYr1*(1+UtilCont)*(1+UtilInfl)^T$8*(1-UtilSave*T$7) -> 53402.441 | U24: =SUM(D24:T24) -> 729698.77
B25: Gas + electric | D25: =(GasElecYr1+ElecExtra)*(1+UtilCont)*(1+UtilInfl)^D$8*(1-UtilSave*D$7) -> 35640 | E25: =(GasElecYr1+ElecExtra)*(1+UtilCont)*(1+UtilInfl)^E$8*(1-UtilSave*E$7) -> 37065.6 | F25: =(GasElecYr1+ElecExtra)*(1+UtilCont)*(1+UtilInfl)^F$8*(1-UtilSave*F$7) -> 38548.224 | G25: =(GasElecYr1+ElecExtra)*(1+UtilCont)*(1+UtilInfl)^G$8*(1-UtilSave*G$7) -> 40090.153 | H25: =(GasElecYr1+ElecExtra)*(1+UtilCont)*(1+UtilInfl)^H$8*(1-UtilSave*H$7) -> 36364.075 | I25: =(GasElecYr1+ElecExtra)*(1+UtilCont)*(1+UtilInfl)^I$8*(1-UtilSave*I$7) -> 37818.638 | J25: =(GasElecYr1+ElecExtra)*(1+UtilCont)*(1+UtilInfl)^J$8*(1-UtilSave*J$7) -> 39331.383 | K25: =(GasElecYr1+ElecExtra)*(1+UtilCont)*(1+UtilInfl)^K$8*(1-UtilSave*K$7) -> 40904.638 | ... T25: =(GasElecYr1+ElecExtra)*(1+UtilCont)*(1+UtilInfl)^T$8*(1-UtilSave*T$7) -> 53402.441 | U25: =SUM(D25:T25) -> 729698.77
B26: Repairs & maintenance | D26: =RepairsYr1*(1+RepairsAging)^D$8*(1-D$7)+D18*RepairsNewPct*D$7 -> 12000 | E26: =RepairsYr1*(1+RepairsAging)^E$8*(1-E$7)+E18*RepairsNewPct*E$7 -> 12960 | F26: =RepairsYr1*(1+RepairsAging)^F$8*(1-F$7)+F18*RepairsNewPct*F$7 -> 13996.8 | G26: =RepairsYr1*(1+RepairsAging)^G$8*(1-G$7)+G18*RepairsNewPct*G$7 -> 15116.544 | H26: =RepairsYr1*(1+RepairsAging)^H$8*(1-H$7)+H18*RepairsNewPct*H$7 -> 11381.299 | I26: =RepairsYr1*(1+RepairsAging)^I$8*(1-I$7)+I18*RepairsNewPct*I$7 -> 12012.573 | J26: =RepairsYr1*(1+RepairsAging)^J$8*(1-J$7)+J18*RepairsNewPct*J$7 -> 12686.255 | K26: =RepairsYr1*(1+RepairsAging)^K$8*(1-K$7)+K18*RepairsNewPct*K$7 -> 13405.501 | ... T26: =RepairsYr1*(1+RepairsAging)^T$8*(1-T$7)+T18*RepairsNewPct*T$7 -> 12255.362 | U26: =SUM(D26:T26) -> 217106.03
B27: Insurance | D27: =Insurance*(1+ExpInfl)^D$8 -> 7500 | E27: =Insurance*(1+ExpInfl)^E$8 -> 7725 | F27: =Insurance*(1+ExpInfl)^F$8 -> 7956.75 | G27: =Insurance*(1+ExpInfl)^G$8 -> 8195.4525 | H27: =Insurance*(1+ExpInfl)^H$8 -> 8441.3161 | I27: =Insurance*(1+ExpInfl)^I$8 -> 8694.5556 | J27: =Insurance*(1+ExpInfl)^J$8 -> 8955.3922 | K27: =Insurance*(1+ExpInfl)^K$8 -> 9224.054 | ... T27: =Insurance*(1+ExpInfl)^T$8 -> 12035.298 | U27: =SUM(D27:T27) -> 163211.91
B28: Card processing | D28: =(D11+D14)*CardFeePct -> 4804.8 | E28: =(E11+E14)*CardFeePct -> 5034.744 | F28: =(F11+F14)*CardFeePct -> 5185.7863 | G28: =(G11+G14)*CardFeePct -> 5341.3599 | H28: =(H11+H14)*CardFeePct -> 5612.6994 | I28: =(I11+I14)*CardFeePct -> 5781.0804 | J28: =(J11+J14)*CardFeePct -> 5954.5128 | K28: =(K11+K14)*CardFeePct -> 6133.1482 | ... T28: =(T11+T14)*CardFeePct -> 8091.798 | U28: =SUM(D28:T28) -> 108523.65
B29: POS system & cards | D29: =POS*(1+ExpInfl)^D$8 -> 6600 | E29: =POS*(1+ExpInfl)^E$8 -> 6798 | F29: =POS*(1+ExpInfl)^F$8 -> 7001.94 | G29: =POS*(1+ExpInfl)^G$8 -> 7211.9982 | H29: =POS*(1+ExpInfl)^H$8 -> 7428.3581 | I29: =POS*(1+ExpInfl)^I$8 -> 7651.2089 | J29: =POS*(1+ExpInfl)^J$8 -> 7880.7452 | K29: =POS*(1+ExpInfl)^K$8 -> 8117.1675 | ... T29: =POS*(1+ExpInfl)^T$8 -> 10591.062 | U29: =SUM(D29:T29) -> 143626.48
B30: W&F supplies | D30: =D12*WFSupplyLb*(1+ExpInfl)^D$8 -> 3600 | E30: =E12*WFSupplyLb*(1+ExpInfl)^E$8 -> 3337.2 | F30: =F12*WFSupplyLb*(1+ExpInfl)^F$8 -> 3437.316 | G30: =G12*WFSupplyLb*(1+ExpInfl)^G$8 -> 3540.4355 | H30: =H12*WFSupplyLb*(1+ExpInfl)^H$8 -> 3646.6485 | I30: =I12*WFSupplyLb*(1+ExpInfl)^I$8 -> 3756.048 | J30: =J12*WFSupplyLb*(1+ExpInfl)^J$8 -> 3868.7294 | K30: =K12*WFSupplyLb*(1+ExpInfl)^K$8 -> 3984.7913 | ... T30: =T12*WFSupplyLb*(1+ExpInfl)^T$8 -> 5199.2489 | U30: =SUM(D30:T30) -> 70867.544
B31: Vending COGS + dry cleaning cost | D31: =D15*((SoapVend+SnackVend)*VendCOGS+DryClean*DCCost)/(DryClean+ATM+SoapVend+SnackVend+GameVend) -> 8965.8 | E31: =E15*((SoapVend+SnackVend)*VendCOGS+DryClean*DCCost)/(DryClean+ATM+SoapVend+SnackVend+GameVend) -> 9145.116 | F31: =F15*((SoapVend+SnackVend)*VendCOGS+DryClean*DCCost)/(DryClean+ATM+SoapVend+SnackVend+GameVend) -> 9328.0183 | G31: =G15*((SoapVend+SnackVend)*VendCOGS+DryClean*DCCost)/(DryClean+ATM+SoapVend+SnackVend+GameVend) -> 9514.5787 | H31: =H15*((SoapVend+SnackVend)*VendCOGS+DryClean*DCCost)/(DryClean+ATM+SoapVend+SnackVend+GameVend) -> 9704.8703 | I31: =I15*((SoapVend+SnackVend)*VendCOGS+DryClean*DCCost)/(DryClean+ATM+SoapVend+SnackVend+GameVend) -> 9898.9677 | J31: =J15*((SoapVend+SnackVend)*VendCOGS+DryClean*DCCost)/(DryClean+ATM+SoapVend+SnackVend+GameVend) -> 10096.947 | K31: =K15*((SoapVend+SnackVend)*VendCOGS+DryClean*DCCost)/(DryClean+ATM+SoapVend+SnackVend+GameVend) -> 10298.886 | ... T31: =T15*((SoapVend+SnackVend)*VendCOGS+DryClean*DCCost)/(DryClean+ATM+SoapVend+SnackVend+GameVend) -> 12308.122 | U31: =SUM(D31:T31) -> 179424.23
B32: Phone, alarm, trash | D32: =TeleAlarmTrash*(1+ExpInfl)^D$8 -> 2595 | E32: =TeleAlarmTrash*(1+ExpInfl)^E$8 -> 2672.85 | F32: =TeleAlarmTrash*(1+ExpInfl)^F$8 -> 2753.0355 | G32: =TeleAlarmTrash*(1+ExpInfl)^G$8 -> 2835.6266 | H32: =TeleAlarmTrash*(1+ExpInfl)^H$8 -> 2920.6954 | I32: =TeleAlarmTrash*(1+ExpInfl)^I$8 -> 3008.3162 | J32: =TeleAlarmTrash*(1+ExpInfl)^J$8 -> 3098.5657 | K32: =TeleAlarmTrash*(1+ExpInfl)^K$8 -> 3191.5227 | ... T32: =TeleAlarmTrash*(1+ExpInfl)^T$8 -> 4164.2132 | U32: =SUM(D32:T32) -> 56471.32
B33: Misc. supplies | D33: =MiscSupplies*(1+ExpInfl)^D$8 -> 1800 | E33: =MiscSupplies*(1+ExpInfl)^E$8 -> 1854 | F33: =MiscSupplies*(1+ExpInfl)^F$8 -> 1909.62 | G33: =MiscSupplies*(1+ExpInfl)^G$8 -> 1966.9086 | H33: =MiscSupplies*(1+ExpInfl)^H$8 -> 2025.9159 | I33: =MiscSupplies*(1+ExpInfl)^I$8 -> 2086.6933 | J33: =MiscSupplies*(1+ExpInfl)^J$8 -> 2149.2941 | K33: =MiscSupplies*(1+ExpInfl)^K$8 -> 2213.773 | ... T33: =MiscSupplies*(1+ExpInfl)^T$8 -> 2888.4716 | U33: =SUM(D33:T33) -> 39170.858
B34: Accounting, tax & legal | D34: =ProFees*(1+ExpInfl)^D$8 -> 5000 | E34: =ProFees*(1+ExpInfl)^E$8 -> 5150 | F34: =ProFees*(1+ExpInfl)^F$8 -> 5304.5 | G34: =ProFees*(1+ExpInfl)^G$8 -> 5463.635 | H34: =ProFees*(1+ExpInfl)^H$8 -> 5627.5441 | I34: =ProFees*(1+ExpInfl)^I$8 -> 5796.3704 | J34: =ProFees*(1+ExpInfl)^J$8 -> 5970.2615 | K34: =ProFees*(1+ExpInfl)^K$8 -> 6149.3693 | ... T34: =ProFees*(1+ExpInfl)^T$8 -> 8023.5322 | U34: =SUM(D34:T34) -> 108807.94
B35: Licenses & fees | D35: =Licenses*(1+ExpInfl)^D$8 -> 1000 | E35: =Licenses*(1+ExpInfl)^E$8 -> 1030 | F35: =Licenses*(1+ExpInfl)^F$8 -> 1060.9 | G35: =Licenses*(1+ExpInfl)^G$8 -> 1092.727 | H35: =Licenses*(1+ExpInfl)^H$8 -> 1125.5088 | I35: =Licenses*(1+ExpInfl)^I$8 -> 1159.2741 | J35: =Licenses*(1+ExpInfl)^J$8 -> 1194.0523 | K35: =Licenses*(1+ExpInfl)^K$8 -> 1229.8739 | ... T35: =Licenses*(1+ExpInfl)^T$8 -> 1604.7064 | U35: =SUM(D35:T35) -> 21761.588
B36: Payroll service | D36: =PayrollSvc*(1+ExpInfl)^D$8 -> 1200 | E36: =PayrollSvc*(1+ExpInfl)^E$8 -> 1236 | F36: =PayrollSvc*(1+ExpInfl)^F$8 -> 1273.08 | G36: =PayrollSvc*(1+ExpInfl)^G$8 -> 1311.2724 | H36: =PayrollSvc*(1+ExpInfl)^H$8 -> 1350.6106 | I36: =PayrollSvc*(1+ExpInfl)^I$8 -> 1391.1289 | J36: =PayrollSvc*(1+ExpInfl)^J$8 -> 1432.8628 | K36: =PayrollSvc*(1+ExpInfl)^K$8 -> 1475.8486 | ... T36: =PayrollSvc*(1+ExpInfl)^T$8 -> 1925.6477 | U36: =SUM(D36:T36) -> 26113.905
B37: Marketing | D37: =Marketing*(1+ExpInfl)^D$8 -> 3000 | E37: =Marketing*(1+ExpInfl)^E$8 -> 3090 | F37: =Marketing*(1+ExpInfl)^F$8 -> 3182.7 | G37: =Marketing*(1+ExpInfl)^G$8 -> 3278.181 | H37: =Marketing*(1+ExpInfl)^H$8 -> 3376.5264 | I37: =Marketing*(1+ExpInfl)^I$8 -> 3477.8222 | J37: =Marketing*(1+ExpInfl)^J$8 -> 3582.1569 | K37: =Marketing*(1+ExpInfl)^K$8 -> 3689.6216 | ... T37: =Marketing*(1+ExpInfl)^T$8 -> 4814.1193 | U37: =SUM(D37:T37) -> 65284.763
B38: Day-manager pay premium (after hand-off) | D38: =IF(D$5>=HandoffYear,MgrHours*52*MgrPremium*(1+WageGrowth)^D$8*(1+Burden),0) -> 0 | E38: =IF(E$5>=HandoffYear,MgrHours*52*MgrPremium*(1+WageGrowth)^E$8*(1+Burden),0) -> 0 | F38: =IF(F$5>=HandoffYear,MgrHours*52*MgrPremium*(1+WageGrowth)^F$8*(1+Burden),0) -> 0 | G38: =IF(G$5>=HandoffYear,MgrHours*52*MgrPremium*(1+WageGrowth)^G$8*(1+Burden),0) -> 0 | H38: =IF(H$5>=HandoffYear,MgrHours*52*MgrPremium*(1+WageGrowth)^H$8*(1+Burden),0) -> 0 | I38: =IF(I$5>=HandoffYear,MgrHours*52*MgrPremium*(1+WageGrowth)^I$8*(1+Burden),0) -> 0 | J38: =IF(J$5>=HandoffYear,MgrHours*52*MgrPremium*(1+WageGrowth)^J$8*(1+Burden),0) -> 0 | K38: =IF(K$5>=HandoffYear,MgrHours*52*MgrPremium*(1+WageGrowth)^K$8*(1+Burden),0) -> 0 | ... T38: =IF(T$5>=HandoffYear,MgrHours*52*MgrPremium*(1+WageGrowth)^T$8*(1+Burden),0) -> 0 | U38: =SUM(D38:T38) -> 0
B39: Delivery program: processing labor | D39: =D16/LbsPerHour*DelivLaborShare*Wage*(1+WageGrowth)^D$8*(1+Burden) -> 0 | E39: =E16/LbsPerHour*DelivLaborShare*Wage*(1+WageGrowth)^E$8*(1+Burden) -> 0 | F39: =F16/LbsPerHour*DelivLaborShare*Wage*(1+WageGrowth)^F$8*(1+Burden) -> 0 | G39: =G16/LbsPerHour*DelivLaborShare*Wage*(1+WageGrowth)^G$8*(1+Burden) -> 0 | H39: =H16/LbsPerHour*DelivLaborShare*Wage*(1+WageGrowth)^H$8*(1+Burden) -> 0 | I39: =I16/LbsPerHour*DelivLaborShare*Wage*(1+WageGrowth)^I$8*(1+Burden) -> 0 | J39: =J16/LbsPerHour*DelivLaborShare*Wage*(1+WageGrowth)^J$8*(1+Burden) -> 0 | K39: =K16/LbsPerHour*DelivLaborShare*Wage*(1+WageGrowth)^K$8*(1+Burden) -> 0 | ... T39: =T16/LbsPerHour*DelivLaborShare*Wage*(1+WageGrowth)^T$8*(1+Burden) -> 0 | U39: =SUM(D39:T39) -> 0
B40: Delivery program: supplies + utilities | D40: =D16*(WFSupplyLb+DelivUtilLb)*(1+ExpInfl)^D$8 -> 0 | E40: =E16*(WFSupplyLb+DelivUtilLb)*(1+ExpInfl)^E$8 -> 0 | F40: =F16*(WFSupplyLb+DelivUtilLb)*(1+ExpInfl)^F$8 -> 0 | G40: =G16*(WFSupplyLb+DelivUtilLb)*(1+ExpInfl)^G$8 -> 0 | H40: =H16*(WFSupplyLb+DelivUtilLb)*(1+ExpInfl)^H$8 -> 0 | I40: =I16*(WFSupplyLb+DelivUtilLb)*(1+ExpInfl)^I$8 -> 0 | J40: =J16*(WFSupplyLb+DelivUtilLb)*(1+ExpInfl)^J$8 -> 0 | K40: =K16*(WFSupplyLb+DelivUtilLb)*(1+ExpInfl)^K$8 -> 0 | ... T40: =T16*(WFSupplyLb+DelivUtilLb)*(1+ExpInfl)^T$8 -> 0 | U40: =SUM(D40:T40) -> 0
B41: Delivery program: driver + vehicle | D41: =IF(D16>0,DriverHours*52*DriverWage*(1+WageGrowth)^D$8*(1+Burden)+VehicleCost*(1+ExpInfl)^D$8,0) -> 0 | E41: =IF(E16>0,DriverHours*52*DriverWage*(1+WageGrowth)^E$8*(1+Burden)+VehicleCost*(1+ExpInfl)^E$8,0) -> 0 | F41: =IF(F16>0,DriverHours*52*DriverWage*(1+WageGrowth)^F$8*(1+Burden)+VehicleCost*(1+ExpInfl)^F$8,0) -> 0 | G41: =IF(G16>0,DriverHours*52*DriverWage*(1+WageGrowth)^G$8*(1+Burden)+VehicleCost*(1+ExpInfl)^G$8,0) -> 0 | H41: =IF(H16>0,DriverHours*52*DriverWage*(1+WageGrowth)^H$8*(1+Burden)+VehicleCost*(1+ExpInfl)^H$8,0) -> 0 | I41: =IF(I16>0,DriverHours*52*DriverWage*(1+WageGrowth)^I$8*(1+Burden)+VehicleCost*(1+ExpInfl)^I$8,0) -> 0 | J41: =IF(J16>0,DriverHours*52*DriverWage*(1+WageGrowth)^J$8*(1+Burden)+VehicleCost*(1+ExpInfl)^J$8,0) -> 0 | K41: =IF(K16>0,DriverHours*52*DriverWage*(1+WageGrowth)^K$8*(1+Burden)+VehicleCost*(1+ExpInfl)^K$8,0) -> 0 | ... T41: =IF(T16>0,DriverHours*52*DriverWage*(1+WageGrowth)^T$8*(1+Burden)+VehicleCost*(1+ExpInfl)^T$8,0) -> 0 | U41: =SUM(D41:T41) -> 0
B42: Contingency | D42: =D18*ContPct -> 3701.7 | E42: =E18*ContPct -> 3869.334 | F42: =F18*ContPct -> 3981.9287 | G42: =G18*ContPct -> 4097.8315 | H42: =H18*ContPct -> 4294.8317 | I42: =I18*ContPct -> 4419.978 | J42: =J18*ContPct -> 4548.8047 | K42: =K18*ContPct -> 4681.4207 | ... T42: =T18*ContPct -> 6127.6809 | U42: =SUM(D42:T42) -> 82728.79
B43: Total operating expenses | D43: =SUM(D21:D42) -> 262202.9 | E43: =SUM(E21:E42) -> 271544.01 | F43: =SUM(F21:F42) -> 281481.81 | G43: =SUM(G21:G42) -> 291814.75 | H43: =SUM(H21:H42) -> 287145.41 | I43: =SUM(I21:I42) -> 297227.3 | J43: =SUM(J21:J42) -> 307681.48 | K43: =SUM(K21:K42) -> 318522.8 | ... T43: =SUM(T21:T42) -> 416509.51 | U43: =SUM(D43:T43) -> 5643752.8
B45: EBITDA / net operating income (absentee) | D45: =D18-D43 -> 107967.1 | E45: =E18-E43 -> 115389.39 | F45: =F18-F43 -> 116711.05 | G45: =G18-G43 -> 117968.4 | H45: =H18-H43 -> 142337.76 | I45: =I18-I43 -> 144770.5 | J45: =J18-J43 -> 147198.99 | K45: =K18-K43 -> 149619.28 | ... T45: =T18-T43 -> 196258.57 | U45: =SUM(D45:T45) -> 2629126.2
B46: EBITDA margin | D46: =IF(D18=0,0,D45/D18) -> 0.29166896 | E46: =IF(E18=0,0,E45/E18) -> 0.29821512 | F46: =IF(F18=0,0,F45/F18) -> 0.29310182 | G46: =IF(G18=0,0,G45/G18) -> 0.28788008 | H46: =IF(H18=0,0,H45/H18) -> 0.33141638 | I46: =IF(I18=0,0,I45/I18) -> 0.3275367 | J46: =IF(J18=0,0,J45/J18) -> 0.32359928 | K46: =IF(K18=0,0,K45/K18) -> 0.31960229 | ... T46: =IF(T18=0,0,T45/T18) -> 0.32028197
B47: Ryan's hours per week in the store | D47: =IF(D$5<HandoffYear,OwnerHours,OwnerHoursLater) -> 40 | E47: =IF(E$5<HandoffYear,OwnerHours,OwnerHoursLater) -> 40 | F47: =IF(F$5<HandoffYear,OwnerHours,OwnerHoursLater) -> 40 | G47: =IF(G$5<HandoffYear,OwnerHours,OwnerHoursLater) -> 40 | H47: =IF(H$5<HandoffYear,OwnerHours,OwnerHoursLater) -> 40 | I47: =IF(I$5<HandoffYear,OwnerHours,OwnerHoursLater) -> 40 | J47: =IF(J$5<HandoffYear,OwnerHours,OwnerHoursLater) -> 40 | K47: =IF(K$5<HandoffYear,OwnerHours,OwnerHoursLater) -> 40 | ... T47: =IF(T$5<HandoffYear,OwnerHours,OwnerHoursLater) -> 40
B48: Value of Ryan's hours (wages + burden he replaces) | D48: =MIN(D47,PaidHours)*52*Wage*(1+WageGrowth)^D$8*(1+Burden) -> 42224 | E48: =MIN(E47,PaidHours)*52*Wage*(1+WageGrowth)^E$8*(1+Burden) -> 43701.84 | F48: =MIN(F47,PaidHours)*52*Wage*(1+WageGrowth)^F$8*(1+Burden) -> 45231.404 | G48: =MIN(G47,PaidHours)*52*Wage*(1+WageGrowth)^G$8*(1+Burden) -> 46814.504 | H48: =MIN(H47,PaidHours)*52*Wage*(1+WageGrowth)^H$8*(1+Burden) -> 48453.011 | I48: =MIN(I47,PaidHours)*52*Wage*(1+WageGrowth)^I$8*(1+Burden) -> 50148.867 | J48: =MIN(J47,PaidHours)*52*Wage*(1+WageGrowth)^J$8*(1+Burden) -> 51904.077 | K48: =MIN(K47,PaidHours)*52*Wage*(1+WageGrowth)^K$8*(1+Burden) -> 53720.72 | ... T48: =MIN(T47,PaidHours)*52*Wage*(1+WageGrowth)^T$8*(1+Burden) -> 73215.827 | U48: =SUM(D48:T48) -> 958696.58
B49: Owner-operator cash flow (SDE) = EBITDA + Ryan's hours | D49: =D45+D48 -> 150191.1 | E49: =E45+E48 -> 159091.23 | F49: =F45+F48 -> 161942.46 | G49: =G45+G48 -> 164782.91 | H49: =H45+H48 -> 190790.77 | I49: =I45+I48 -> 194919.37 | J49: =J45+J48 -> 199103.07 | K49: =K45+K48 -> 203340 | ... T49: =T45+T48 -> 269474.4 | U49: =SUM(D49:T49) -> 3587822.8
B51: Capital and cash flow (pre-tax, unlevered)
B52: Purchase price + closing costs + working capital | C52: =-TotalInvest -> -480000 | D52: =0 -> 0 | E52: =0 -> 0 | F52: =0 -> 0 | G52: =0 -> 0 | H52: =0 -> 0 | I52: =0 -> 0 | J52: =0 -> 0 | K52: =0 -> 0 | ... T52: =0 -> 0 | U52: =SUM(D52:T52) -> 0
B53: Equipment capex (selected scenario) | C53: =-Depreciation!C12 -> 0 | D53: =-Depreciation!D12 -> 0 | E53: =-Depreciation!E12 -> 0 | F53: =-Depreciation!F12 -> 0 | G53: =-Depreciation!G12 -> -419252.03 | H53: =-Depreciation!H12 -> 0 | I53: =-Depreciation!I12 -> 0 | J53: =-Depreciation!J12 -> 0 | ... T53: =-Depreciation!T12 -> 0 | U53: =SUM(D53:T53) -> -655956.02
B54: Exit value (Year 17) + working capital returned | D54: =IF(D$5=17,ExitMult*D45+WorkingCap,0) -> 0 | E54: =IF(E$5=17,ExitMult*E45+WorkingCap,0) -> 0 | F54: =IF(F$5=17,ExitMult*F45+WorkingCap,0) -> 0 | G54: =IF(G$5=17,ExitMult*G45+WorkingCap,0) -> 0 | H54: =IF(H$5=17,ExitMult*H45+WorkingCap,0) -> 0 | I54: =IF(I$5=17,ExitMult*I45+WorkingCap,0) -> 0 | J54: =IF(J$5=17,ExitMult*J45+WorkingCap,0) -> 0 | K54: =IF(K$5=17,ExitMult*K45+WorkingCap,0) -> 0 | ... T54: =IF(T$5=17,ExitMult*T45+WorkingCap,0) -> 304387.86 | U54: =SUM(D54:T54) -> 304387.86
B55: Pre-tax cash flow (absentee) | C55: =C52+C53 -> -480000 | D55: =D45+D52+D53+D54 -> 107967.1 | E55: =E45+E52+E53+E54 -> 115389.39 | F55: =F45+F52+F53+F54 -> 116711.05 | G55: =G45+G52+G53+G54 -> -301283.63 | H55: =H45+H52+H53+H54 -> 142337.76 | I55: =I45+I52+I53+I54 -> 144770.5 | J55: =J45+J52+J53+J54 -> 147198.99 | K55: =K45+K52+K53+K54 -> 149619.28 | ... T55: =T45+T52+T53+T54 -> 500646.43 | U55: =SUM(D55:T55) -> 2277558
B56: Cumulative pre-tax cash flow | C56: =C55 -> -480000 | D56: =C56+D55 -> -372032.9 | E56: =D56+E55 -> -256643.51 | F56: =E56+F55 -> -139932.46 | G56: =F56+G55 -> -441216.08 | H56: =G56+H55 -> -298878.33 | I56: =H56+I55 -> -154107.82 | J56: =I56+J55 -> -6908.8288 | K56: =J56+K55 -> 142710.45 | ... T56: =S56+T55 -> 1797558
B58: Pre-tax unlevered IRR (absentee) | C58: =IRR(C55:T55) -> 0.17525465
B59: Year-1 cash-on-cash (EBITDA less Year-1 capex / total cash at close) | C59: =(D45+D53)/(TotalInvest-C53) -> 0.22493146
B60: Average annual capex over 17 years (reserve equivalent) | C60: =-SUM(C53:T53)/17 -> 38585.648

Sheet Structures
B2: After-tax cash flow by ownership structure (family level)
B3: A: Ryan owns (parents gift the cash), works 40 hrs/wk unpaid. D: Ryan owns, funded by an AFR loan, S-corp from Year 2. B: parents' LLC owns, parents passive, no other passive income; Ryan paid W-2 for his hours. C: same as B but parents have passive income and NJ partnership income to absorb losses. Structure advice is in the ownership thread.
B5: Year | C5: 0 | D5: 1 | E5: 2 | F5: 3 | G5: 4 | H5: 5 | I5: 6 | J5: 7 | K5: 8 | L5: 9 | M5: 10 | N5: 11 | O5: 12 | P5: 13 | Q5: 14 | R5: 15 | S5: 16 | T5: 17 | U5: Total 1-17
B6: Common lines (from Projection and Depreciation)
B7: EBITDA (absentee) | D7: =Projection!D45 -> 107967.1 | E7: =Projection!E45 -> 115389.39 | F7: =Projection!F45 -> 116711.05 | G7: =Projection!G45 -> 117968.4 | H7: =Projection!H45 -> 142337.76 | I7: =Projection!I45 -> 144770.5 | J7: =Projection!J45 -> 147198.99 | K7: =Projection!K45 -> 149619.28 | ... T7: =Projection!T45 -> 196258.57 | U7: =SUM(D7:T7) -> 2629126.2
B8: Value of Ryan's hours | D8: =Projection!D48 -> 42224 | E8: =Projection!E48 -> 43701.84 | F8: =Projection!F48 -> 45231.404 | G8: =Projection!G48 -> 46814.504 | H8: =Projection!H48 -> 48453.011 | I8: =Projection!I48 -> 50148.867 | J8: =Projection!J48 -> 51904.077 | K8: =Projection!K48 -> 53720.72 | ... T8: =Projection!T48 -> 73215.827 | U8: =SUM(D8:T8) -> 958696.58
B9: W-2 wages paid (all attendant hours) | D9: =Projection!D22 -> 82810 | E9: =Projection!E22 -> 85708.35 | F9: =Projection!F22 -> 88708.142 | G9: =Projection!G22 -> 91812.927 | H9: =Projection!H22 -> 95026.38 | I9: =Projection!I22 -> 98352.303 | J9: =Projection!J22 -> 101794.63 | K9: =Projection!K22 -> 105357.45 | ... T9: =Projection!T22 -> 143591.38 | U9: =SUM(D9:T9) -> 1880202.4
B10: Federal depreciation & amortization | D10: =Depreciation!D69 -> 110666.67 | E10: =Depreciation!E69 -> 25666.667 | F10: =Depreciation!F69 -> 25666.667 | G10: =Depreciation!G69 -> 444918.7 | H10: =Depreciation!H69 -> 25666.667 | I10: =Depreciation!I69 -> 25666.667 | J10: =Depreciation!J69 -> 25666.667 | K10: =Depreciation!K69 -> 25666.667 | ... T10: =Depreciation!T69 -> 0 | U10: =SUM(D10:T10) -> 1125956
B11: NJ depreciation & amortization | D11: =Depreciation!D70 -> 58500 | E11: =Depreciation!E70 -> 38533.333 | F11: =Depreciation!F70 -> 34053.333 | G11: =Depreciation!G70 -> 135215.74 | H11: =Depreciation!H70 -> 157525.98 | I11: =Depreciation!I70 -> 105045.72 | J11: =Depreciation!J70 -> 72751.167 | K11: =Depreciation!K70 -> 72751.167 | ... T11: =Depreciation!T70 -> 0 | U11: =SUM(D11:T11) -> 1125956
B12: UBIA proxy | D12: =Depreciation!D71 -> 85000 | E12: =Depreciation!E71 -> 85000 | F12: =Depreciation!F71 -> 85000 | G12: =Depreciation!G71 -> 504252.03 | H12: =Depreciation!H71 -> 504252.03 | I12: =Depreciation!I71 -> 504252.03 | J12: =Depreciation!J71 -> 504252.03 | K12: =Depreciation!K71 -> 504252.03 | ... T12: =Depreciation!T71 -> 740956.02
B13: Pre-tax cash flow (absentee) | C13: =Projection!C55 -> -480000 | D13: =Projection!D55 -> 107967.1 | E13: =Projection!E55 -> 115389.39 | F13: =Projection!F55 -> 116711.05 | G13: =Projection!G55 -> -301283.63 | H13: =Projection!H55 -> 142337.76 | I13: =Projection!I55 -> 144770.5 | J13: =Projection!J55 -> 147198.99 | ... T13: =Projection!T55 -> 500646.43 | U13: =SUM(D13:T13) -> 2277558
B14: Exit value in cash flow | D14: =Projection!D54-IF(D$5=17,WorkingCap,0) -> 0 | E14: =Projection!E54-IF(E$5=17,WorkingCap,0) -> 0 | F14: =Projection!F54-IF(F$5=17,WorkingCap,0) -> 0 | G14: =Projection!G54-IF(G$5=17,WorkingCap,0) -> 0 | H14: =Projection!H54-IF(H$5=17,WorkingCap,0) -> 0 | I14: =Projection!I54-IF(I$5=17,WorkingCap,0) -> 0 | J14: =Projection!J54-IF(J$5=17,WorkingCap,0) -> 0 | K14: =Projection!K54-IF(K$5=17,WorkingCap,0) -> 0 | ... T14: =Projection!T54-IF(T$5=17,WorkingCap,0) -> 294387.86 | U14: =SUM(D14:T14) -> 294387.86
B16: A. Ryan owns 100% (single-member LLC, materially participates)
B17: Net business income (EBITDA + Ryan's unpaid hours - federal depreciation) | D17: =D7+D8-D10 -> 39524.433 | E17: =E7+E8-E10 -> 133424.56 | F17: =F7+F8-F10 -> 136275.79 | G17: =G7+G8-G10 -> -280135.79 | H17: =H7+H8-H10 -> 165124.1 | I17: =I7+I8-I10 -> 169252.7 | J17: =J7+J8-J10 -> 173436.4 | K17: =K7+K8-K10 -> 177673.33 | ... T17: =T7+T8-T10 -> 269474.4 | U17: =SUM(D17:T17) -> 2461866.7
B18: Self-employment tax | D18: =IF(D17>0,MIN(D17*0.9235,SSBase*(1+WageGrowth)^(D$5-1))*0.124+D17*0.9235*0.029,0) -> 5584.6246 | E18: =IF(E17>0,MIN(E17*0.9235,SSBase*(1+WageGrowth)^(E$5-1))*0.124+E17*0.9235*0.029,0) -> 18852.29 | F18: =IF(F17>0,MIN(F17*0.9235,SSBase*(1+WageGrowth)^(F$5-1))*0.124+F17*0.9235*0.029,0) -> 19255.156 | G18: =IF(G17>0,MIN(G17*0.9235,SSBase*(1+WageGrowth)^(G$5-1))*0.124+G17*0.9235*0.029,0) -> 0 | H18: =IF(H17>0,MIN(H17*0.9235,SSBase*(1+WageGrowth)^(H$5-1))*0.124+H17*0.9235*0.029,0) -> 23331.293 | I18: =IF(I17>0,MIN(I17*0.9235,SSBase*(1+WageGrowth)^(I$5-1))*0.124+I17*0.9235*0.029,0) -> 23914.645 | J18: =IF(J17>0,MIN(J17*0.9235,SSBase*(1+WageGrowth)^(J$5-1))*0.124+J17*0.9235*0.029,0) -> 24505.784 | K18: =IF(K17>0,MIN(K17*0.9235,SSBase*(1+WageGrowth)^(K$5-1))*0.124+K17*0.9235*0.029,0) -> 25104.442 | ... T18: =IF(T17>0,MIN(T17*0.9235,SSBase*(1+WageGrowth)^(T$5-1))*0.124+T17*0.9235*0.029,0) -> 38075.52 | U18: =SUM(D18:T18) -> 393935.53
B19: QBI deduction (below threshold: 20%) | D19: =MAX(0,D17-D18/2)*QBIRate -> 7346.4242 | E19: =MAX(0,E17-E18/2)*QBIRate -> 24799.684 | F19: =MAX(0,F17-F18/2)*QBIRate -> 25329.643 | G19: =MAX(0,G17-G18/2)*QBIRate -> 0 | H19: =MAX(0,H17-H18/2)*QBIRate -> 30691.691 | I19: =MAX(0,I17-I18/2)*QBIRate -> 31459.076 | J19: =MAX(0,J17-J18/2)*QBIRate -> 32236.703 | K19: =MAX(0,K17-K18/2)*QBIRate -> 33024.222 | ... T19: =MAX(0,T17-T18/2)*QBIRate -> 50087.327 | U19: =SUM(D19:T19) -> 518211.66
B20: Federal taxable income from the business | D20: =D17-D18/2-D19 -> 29385.697 | E20: =E17-E18/2-E19 -> 99198.735 | F20: =F17-F18/2-F19 -> 101318.57 | G20: =G17-G18/2-G19 -> -280135.79 | H20: =H17-H18/2-H19 -> 122766.77 | I20: =I17-I18/2-I19 -> 125836.3 | J20: =J17-J18/2-J19 -> 128946.81 | K20: =K17-K18/2-K19 -> 132096.89 | ... T20: =T17-T18/2-T19 -> 200349.31 | U20: =SUM(D20:T20) -> 1746687.3
B21: Fed loss carryforward, start of year | D21: =0 -> 0 | E21: =D24 -> 0 | F21: =E24 -> 0 | G21: =F24 -> 0 | H21: =G24 -> 230135.79 | I21: =H24 -> 107369.03 | J21: =I24 -> 0 | K21: =J24 -> 0 | L21: =K24 -> 0 | ... T21: =S24 -> 0
B22: Fed carryforward used | D22: =MIN(D21,MAX(0,D20)) -> 0 | E22: =MIN(E21,MAX(0,E20)) -> 0 | F22: =MIN(F21,MAX(0,F20)) -> 0 | G22: =MIN(G21,MAX(0,G20)) -> 0 | H22: =MIN(H21,MAX(0,H20)) -> 122766.77 | I22: =MIN(I21,MAX(0,I20)) -> 107369.03 | J22: =MIN(J21,MAX(0,J20)) -> 0 | K22: =MIN(K21,MAX(0,K20)) -> 0 | ... T22: =MIN(T21,MAX(0,T20)) -> 0 | U22: =SUM(D22:T22) -> 230135.79
B23: Fed loss used against other income | D23: =IF(D20<0,MIN(-D20,MIN(RyanOtherInc,EBLSingle)),0) -> 0 | E23: =IF(E20<0,MIN(-E20,MIN(RyanOtherInc,EBLSingle)),0) -> 0 | F23: =IF(F20<0,MIN(-F20,MIN(RyanOtherInc,EBLSingle)),0) -> 0 | G23: =IF(G20<0,MIN(-G20,MIN(RyanOtherInc,EBLSingle)),0) -> 50000 | H23: =IF(H20<0,MIN(-H20,MIN(RyanOtherInc,EBLSingle)),0) -> 0 | I23: =IF(I20<0,MIN(-I20,MIN(RyanOtherInc,EBLSingle)),0) -> 0 | J23: =IF(J20<0,MIN(-J20,MIN(RyanOtherInc,EBLSingle)),0) -> 0 | K23: =IF(K20<0,MIN(-K20,MIN(RyanOtherInc,EBLSingle)),0) -> 0 | ... T23: =IF(T20<0,MIN(-T20,MIN(RyanOtherInc,EBLSingle)),0) -> 0 | U23: =SUM(D23:T23) -> 96023.521
B24: Fed loss carryforward, end of year | D24: =D21-D22+MAX(0,-D20)-D23 -> 0 | E24: =E21-E22+MAX(0,-E20)-E23 -> 0 | F24: =F21-F22+MAX(0,-F20)-F23 -> 0 | G24: =G21-G22+MAX(0,-G20)-G23 -> 230135.79 | H24: =H21-H22+MAX(0,-H20)-H23 -> 107369.03 | I24: =I21-I22+MAX(0,-I20)-I23 -> 0 | J24: =J21-J22+MAX(0,-J20)-J23 -> 0 | K24: =K21-K22+MAX(0,-K20)-K23 -> 0 | ... T24: =T21-T22+MAX(0,-T20)-T23 -> 0
B25: Fed tax (negative = tax saved on other income) | D25: =(MAX(0,D20)-D22-D23)*RyanFed -> 6464.8533 | E25: =(MAX(0,E20)-E22-E23)*RyanFed -> 21823.722 | F25: =(MAX(0,F20)-F22-F23)*RyanFed -> 22290.086 | G25: =(MAX(0,G20)-G22-G23)*RyanFed -> -11000 | H25: =(MAX(0,H20)-H22-H23)*RyanFed -> 0 | I25: =(MAX(0,I20)-I22-I23)*RyanFed -> 4062.8012 | J25: =(MAX(0,J20)-J22-J23)*RyanFed -> 28368.298 | K25: =(MAX(0,K20)-K22-K23)*RyanFed -> 29061.315 | ... T25: =(MAX(0,T20)-T22-T23)*RyanFed -> 44076.848 | U25: =SUM(D25:T25) -> 384271.21
B26: NJ taxable income (EBITDA + Ryan's hours - NJ depreciation) | D26: =D7+D8-D11 -> 91691.1 | E26: =E7+E8-E11 -> 120557.9 | F26: =F7+F8-F11 -> 127889.12 | G26: =G7+G8-G11 -> 29567.168 | H26: =H7+H8-H11 -> 33264.786 | I26: =I7+I8-I11 -> 89873.645 | J26: =J7+J8-J11 -> 126351.9 | K26: =K7+K8-K11 -> 130588.83 | ... T26: =T7+T8-T11 -> 269474.4 | U26: =SUM(D26:T26) -> 2461866.7
B27: NJ loss carryforward, start of year | D27: =0 -> 0 | E27: =D30 -> 0 | F27: =E30 -> 0 | G27: =F30 -> 0 | H27: =G30 -> 0 | I27: =H30 -> 0 | J27: =I30 -> 0 | K27: =J30 -> 0 | L27: =K30 -> 0 | ... T27: =S30 -> 0
B28: NJ carryforward used | D28: =MIN(D27,MAX(0,D26)) -> 0 | E28: =MIN(E27,MAX(0,E26)) -> 0 | F28: =MIN(F27,MAX(0,F26)) -> 0 | G28: =MIN(G27,MAX(0,G26)) -> 0 | H28: =MIN(H27,MAX(0,H26)) -> 0 | I28: =MIN(I27,MAX(0,I26)) -> 0 | J28: =MIN(J27,MAX(0,J26)) -> 0 | K28: =MIN(K27,MAX(0,K26)) -> 0 | ... T28: =MIN(T27,MAX(0,T26)) -> 0 | U28: =SUM(D28:T28) -> 0
B29: NJ loss used against other income | D29: =IF(D26<0,MIN(-D26,0),0) -> 0 | E29: =IF(E26<0,MIN(-E26,0),0) -> 0 | F29: =IF(F26<0,MIN(-F26,0),0) -> 0 | G29: =IF(G26<0,MIN(-G26,0),0) -> 0 | H29: =IF(H26<0,MIN(-H26,0),0) -> 0 | I29: =IF(I26<0,MIN(-I26,0),0) -> 0 | J29: =IF(J26<0,MIN(-J26,0),0) -> 0 | K29: =IF(K26<0,MIN(-K26,0),0) -> 0 | ... T29: =IF(T26<0,MIN(-T26,0),0) -> 0 | U29: =SUM(D29:T29) -> 0
B30: NJ loss carryforward, end of year | D30: =D27-D28+MAX(0,-D26)-D29 -> 0 | E30: =E27-E28+MAX(0,-E26)-E29 -> 0 | F30: =F27-F28+MAX(0,-F26)-F29 -> 0 | G30: =G27-G28+MAX(0,-G26)-G29 -> 0 | H30: =H27-H28+MAX(0,-H26)-H29 -> 0 | I30: =I27-I28+MAX(0,-I26)-I29 -> 0 | J30: =J27-J28+MAX(0,-J26)-J29 -> 0 | K30: =K27-K28+MAX(0,-K26)-K29 -> 0 | ... T30: =T27-T28+MAX(0,-T26)-T29 -> 0
B31: NJ tax (negative = tax saved on other income) | D31: =(MAX(0,D26)-D28-D29)*RyanNJ -> 5840.7231 | E31: =(MAX(0,E26)-E28-E29)*RyanNJ -> 7679.538 | F31: =(MAX(0,F26)-F28-F29)*RyanNJ -> 8146.5373 | G31: =(MAX(0,G26)-G28-G29)*RyanNJ -> 1883.4286 | H31: =(MAX(0,H26)-H28-H29)*RyanNJ -> 2118.9669 | I31: =(MAX(0,I26)-I28-I29)*RyanNJ -> 5724.9512 | J31: =(MAX(0,J26)-J28-J29)*RyanNJ -> 8048.6163 | K31: =(MAX(0,K26)-K28-K29)*RyanNJ -> 8318.5084 | ... T31: =(MAX(0,T26)-T28-T29)*RyanNJ -> 17165.519 | U31: =SUM(D31:T31) -> 156820.91
B32: Total tax (federal + SE + NJ) | D32: =D25+D18+D31 -> 17890.201 | E32: =E25+E18+E31 -> 48355.55 | F32: =F25+F18+F31 -> 49691.779 | G32: =G25+G18+G31 -> -9116.5714 | H32: =H25+H18+H31 -> 25450.259 | I32: =I25+I18+I31 -> 33702.398 | J32: =J25+J18+J31 -> 60922.698 | K32: =K25+K18+K31 -> 62484.266 | ... T32: =T25+T18+T31 -> 99317.887 | U32: =SUM(D32:T32) -> 935027.66
B33: Family after-tax cash flow | C33: =C13 -> -480000 | D33: =D13+D8-D32-D14*ExitTax -> 132300.9 | E33: =E13+E8-E32-E14*ExitTax -> 110735.68 | F33: =F13+F8-F32-F14*ExitTax -> 112250.68 | G33: =G13+G8-G32-G14*ExitTax -> -245352.55 | H33: =H13+H8-H32-H14*ExitTax -> 165340.51 | I33: =I13+I8-I32-I14*ExitTax -> 161216.97 | J33: =J13+J8-J32-J14*ExitTax -> 138180.37 | K33: =K13+K8-K32-K14*ExitTax -> 140855.73 | ... T33: =T13+T8-T32-T14*ExitTax -> 386228.01 | U33: =SUM(D33:T33) -> 2212910.6
B35: B. Parents' LLC owns 100%; parents passive with no other passive income; Ryan is a paid W-2 manager
B36: Net business income (EBITDA - federal depreciation) | D36: =D7-D10 -> -2699.5667 | E36: =E7-E10 -> 89722.723 | F36: =F7-F10 -> 91044.387 | G36: =G7-G10 -> -326950.29 | H36: =H7-H10 -> 116671.09 | I36: =I7-I10 -> 119103.84 | J36: =J7-J10 -> 121532.33 | K36: =K7-K10 -> 123952.61 | ... T36: =T7-T10 -> 196258.57 | U36: =SUM(D36:T36) -> 1503170.2
B37: QBI deduction (above threshold: limited by W-2 wages / property) | D37: =MIN(MAX(0,D36)*QBIRate,MAX(0.5*D9,0.25*D9+0.025*D12)) -> 0 | E37: =MIN(MAX(0,E36)*QBIRate,MAX(0.5*E9,0.25*E9+0.025*E12)) -> 17944.545 | F37: =MIN(MAX(0,F36)*QBIRate,MAX(0.5*F9,0.25*F9+0.025*F12)) -> 18208.877 | G37: =MIN(MAX(0,G36)*QBIRate,MAX(0.5*G9,0.25*G9+0.025*G12)) -> 0 | H37: =MIN(MAX(0,H36)*QBIRate,MAX(0.5*H9,0.25*H9+0.025*H12)) -> 23334.218 | I37: =MIN(MAX(0,I36)*QBIRate,MAX(0.5*I9,0.25*I9+0.025*I12)) -> 23820.767 | J37: =MIN(MAX(0,J36)*QBIRate,MAX(0.5*J9,0.25*J9+0.025*J12)) -> 24306.466 | K37: =MIN(MAX(0,K36)*QBIRate,MAX(0.5*K9,0.25*K9+0.025*K12)) -> 24790.522 | ... T37: =MIN(MAX(0,T36)*QBIRate,MAX(0.5*T9,0.25*T9+0.025*T12)) -> 39251.714 | U37: =SUM(D37:T37) -> 387680.93
B38: Federal taxable income from the business | D38: =D36-D37 -> -2699.5667 | E38: =E36-E37 -> 71778.179 | F38: =F36-F37 -> 72835.51 | G38: =G36-G37 -> -326950.29 | H38: =H36-H37 -> 93336.873 | I38: =I36-I37 -> 95283.069 | J38: =J36-J37 -> 97225.862 | K38: =K36-K37 -> 99162.088 | ... T38: =T36-T37 -> 157006.86 | U38: =SUM(D38:T38) -> 1115489.2
B39: Fed (passive) loss carryforward, start of year | D39: =0 -> 0 | E39: =D42 -> 2699.5667 | F39: =E42 -> 0 | G39: =F42 -> 0 | H39: =G42 -> 326950.29 | I39: =H42 -> 233613.42 | J39: =I42 -> 138330.35 | K39: =J42 -> 41104.49 | L39: =K42 -> 0 | ... T39: =S42 -> 0
B40: Fed (passive) carryforward used | D40: =MIN(D39,MAX(0,D38)) -> 0 | E40: =MIN(E39,MAX(0,E38)) -> 2699.5667 | F40: =MIN(F39,MAX(0,F38)) -> 0 | G40: =MIN(G39,MAX(0,G38)) -> 0 | H40: =MIN(H39,MAX(0,H38)) -> 93336.873 | I40: =MIN(I39,MAX(0,I38)) -> 95283.069 | J40: =MIN(J39,MAX(0,J38)) -> 97225.862 | K40: =MIN(K39,MAX(0,K38)) -> 41104.49 | ... T40: =MIN(T39,MAX(0,T38)) -> 0 | U40: =SUM(D40:T40) -> 435234.5
B41: Fed (passive) loss used against other income | D41: =IF(D38<0,MIN(-D38,0),0) -> 0 | E41: =IF(E38<0,MIN(-E38,0),0) -> 0 | F41: =IF(F38<0,MIN(-F38,0),0) -> 0 | G41: =IF(G38<0,MIN(-G38,0),0) -> 0 | H41: =IF(H38<0,MIN(-H38,0),0) -> 0 | I41: =IF(I38<0,MIN(-I38,0),0) -> 0 | J41: =IF(J38<0,MIN(-J38,0),0) -> 0 | K41: =IF(K38<0,MIN(-K38,0),0) -> 0 | ... T41: =IF(T38<0,MIN(-T38,0),0) -> 0 | U41: =SUM(D41:T41) -> 0
B42: Fed (passive) loss carryforward, end of year | D42: =D39-D40+MAX(0,-D38)-D41 -> 2699.5667 | E42: =E39-E40+MAX(0,-E38)-E41 -> 0 | F42: =F39-F40+MAX(0,-F38)-F41 -> 0 | G42: =G39-G40+MAX(0,-G38)-G41 -> 326950.29 | H42: =H39-H40+MAX(0,-H38)-H41 -> 233613.42 | I42: =I39-I40+MAX(0,-I38)-I41 -> 138330.35 | J42: =J39-J40+MAX(0,-J38)-J41 -> 41104.49 | K42: =K39-K40+MAX(0,-K38)-K41 -> 0 | ... T42: =T39-T40+MAX(0,-T38)-T41 -> 0
B43: Fed (passive) tax (negative = tax saved on other income) | D43: =(MAX(0,D38)-D40-D41)*(ParentFed+NIIT) -> 0 | E43: =(MAX(0,E38)-E40-E41)*(ParentFed+NIIT) -> 28184.074 | F43: =(MAX(0,F38)-F40-F41)*(ParentFed+NIIT) -> 29716.888 | G43: =(MAX(0,G38)-G40-G41)*(ParentFed+NIIT) -> 0 | H43: =(MAX(0,H38)-H40-H41)*(ParentFed+NIIT) -> 0 | I43: =(MAX(0,I38)-I40-I41)*(ParentFed+NIIT) -> 0 | J43: =(MAX(0,J38)-J40-J41)*(ParentFed+NIIT) -> 0 | K43: =(MAX(0,K38)-K40-K41)*(ParentFed+NIIT) -> 23687.5 | ... T43: =(MAX(0,T38)-T40-T41)*(ParentFed+NIIT) -> 64058.797 | U43: =SUM(D43:T43) -> 455119.6
B44: NJ taxable income (EBITDA - NJ depreciation) | D44: =D7-D11 -> 49467.1 | E44: =E7-E11 -> 76856.057 | F44: =F7-F11 -> 82657.72 | G44: =G7-G11 -> -17247.335 | H44: =H7-H11 -> -15188.225 | I44: =I7-I11 -> 39724.779 | J44: =J7-J11 -> 74447.827 | K44: =K7-K11 -> 76868.11 | ... T44: =T7-T11 -> 196258.57 | U44: =SUM(D44:T44) -> 1503170.2
B45: NJ loss carryforward, start of year | D45: =0 -> 0 | E45: =D48 -> 0 | F45: =E48 -> 0 | G45: =F48 -> 0 | H45: =G48 -> 17247.335 | I45: =H48 -> 32435.561 | J45: =I48 -> 0 | K45: =J48 -> 0 | L45: =K48 -> 0 | ... T45: =S48 -> 0
B46: NJ carryforward used | D46: =MIN(D45,MAX(0,D44)) -> 0 | E46: =MIN(E45,MAX(0,E44)) -> 0 | F46: =MIN(F45,MAX(0,F44)) -> 0 | G46: =MIN(G45,MAX(0,G44)) -> 0 | H46: =MIN(H45,MAX(0,H44)) -> 0 | I46: =MIN(I45,MAX(0,I44)) -> 32435.561 | J46: =MIN(J45,MAX(0,J44)) -> 0 | K46: =MIN(K45,MAX(0,K44)) -> 0 | ... T46: =MIN(T45,MAX(0,T44)) -> 0 | U46: =SUM(D46:T46) -> 32435.561
B47: NJ loss used against other income | D47: =IF(D44<0,MIN(-D44,0),0) -> 0 | E47: =IF(E44<0,MIN(-E44,0),0) -> 0 | F47: =IF(F44<0,MIN(-F44,0),0) -> 0 | G47: =IF(G44<0,MIN(-G44,0),0) -> 0 | H47: =IF(H44<0,MIN(-H44,0),0) -> 0 | I47: =IF(I44<0,MIN(-I44,0),0) -> 0 | J47: =IF(J44<0,MIN(-J44,0),0) -> 0 | K47: =IF(K44<0,MIN(-K44,0),0) -> 0 | ... T47: =IF(T44<0,MIN(-T44,0),0) -> 0 | U47: =SUM(D47:T47) -> 0
B48: NJ loss carryforward, end of year | D48: =D45-D46+MAX(0,-D44)-D47 -> 0 | E48: =E45-E46+MAX(0,-E44)-E47 -> 0 | F48: =F45-F46+MAX(0,-F44)-F47 -> 0 | G48: =G45-G46+MAX(0,-G44)-G47 -> 17247.335 | H48: =H45-H46+MAX(0,-H44)-H47 -> 32435.561 | I48: =I45-I46+MAX(0,-I44)-I47 -> 0 | J48: =J45-J46+MAX(0,-J44)-J47 -> 0 | K48: =K45-K46+MAX(0,-K44)-K47 -> 0 | ... T48: =T45-T46+MAX(0,-T44)-T47 -> 0
B49: NJ tax (negative = tax saved on other income) | D49: =(MAX(0,D44)-D46-D47)*ParentNJ -> 4437.1989 | E49: =(MAX(0,E44)-E46-E47)*ParentNJ -> 6893.9883 | F49: =(MAX(0,F44)-F46-F47)*ParentNJ -> 7414.3975 | G49: =(MAX(0,G44)-G46-G47)*ParentNJ -> 0 | H49: =(MAX(0,H44)-H46-H47)*ParentNJ -> 0 | I49: =(MAX(0,I44)-I46-I47)*ParentNJ -> 653.84286 | J49: =(MAX(0,J44)-J46-J47)*ParentNJ -> 6677.9701 | K49: =(MAX(0,K44)-K46-K47)*ParentNJ -> 6895.0695 | ... T49: =(MAX(0,T44)-T46-T47)*ParentNJ -> 17604.394 | U49: =SUM(D49:T49) -> 134834.36
B50: Total tax (parents) | D50: =D43+D49 -> 4437.1989 | E50: =E43+E49 -> 35078.062 | F50: =F43+F49 -> 37131.285 | G50: =G43+G49 -> 0 | H50: =H43+H49 -> 0 | I50: =I43+I49 -> 653.84286 | J50: =J43+J49 -> 6677.9701 | K50: =K43+K49 -> 30582.57 | ... T50: =T43+T49 -> 81663.191 | U50: =SUM(D50:T50) -> 589953.97
B51: Ryan's after-tax wages for his hours (stays in the family) | D51: =D8/(1+Burden)*(1-RyanFed-RyanNJ-0.0765) -> 23288.72 | E51: =E8/(1+Burden)*(1-RyanFed-RyanNJ-0.0765) -> 24103.825 | F51: =F8/(1+Burden)*(1-RyanFed-RyanNJ-0.0765) -> 24947.459 | G51: =G8/(1+Burden)*(1-RyanFed-RyanNJ-0.0765) -> 25820.62 | H51: =H8/(1+Burden)*(1-RyanFed-RyanNJ-0.0765) -> 26724.342 | I51: =I8/(1+Burden)*(1-RyanFed-RyanNJ-0.0765) -> 27659.694 | J51: =J8/(1+Burden)*(1-RyanFed-RyanNJ-0.0765) -> 28627.783 | K51: =K8/(1+Burden)*(1-RyanFed-RyanNJ-0.0765) -> 29629.756 | ... T51: =T8/(1+Burden)*(1-RyanFed-RyanNJ-0.0765) -> 40382.315 | U51: =SUM(D51:T51) -> 528770.75
B52: Family after-tax cash flow | C52: =C13 -> -480000 | D52: =D13-D50+D51-D14*ExitTax -> 126818.62 | E52: =E13-E50+E51-E14*ExitTax -> 104415.15 | F52: =F13-F50+F51-F14*ExitTax -> 104527.23 | G52: =G13-G50+G51-G14*ExitTax -> -275463.01 | H52: =H13-H50+H51-H14*ExitTax -> 169062.1 | I52: =I13-I50+I51-I14*ExitTax -> 171776.35 | J52: =J13-J50+J51-J14*ExitTax -> 169148.81 | K52: =K13-K50+K51-K14*ExitTax -> 148666.46 | ... T52: =T13-T50+T51-T14*ExitTax -> 371049.19 | U52: =SUM(D52:T52) -> 2128058.4
B54: C. Parents' LLC owns 100%; parents passive but have passive + NJ partnership income to absorb losses
B55: Net business income (EBITDA - federal depreciation) | D55: =D7-D10 -> -2699.5667 | E55: =E7-E10 -> 89722.723 | F55: =F7-F10 -> 91044.387 | G55: =G7-G10 -> -326950.29 | H55: =H7-H10 -> 116671.09 | I55: =I7-I10 -> 119103.84 | J55: =J7-J10 -> 121532.33 | K55: =K7-K10 -> 123952.61 | ... T55: =T7-T10 -> 196258.57 | U55: =SUM(D55:T55) -> 1503170.2
B56: QBI deduction (above threshold: limited by W-2 wages / property) | D56: =MIN(MAX(0,D55)*QBIRate,MAX(0.5*D9,0.25*D9+0.025*D12)) -> 0 | E56: =MIN(MAX(0,E55)*QBIRate,MAX(0.5*E9,0.25*E9+0.025*E12)) -> 17944.545 | F56: =MIN(MAX(0,F55)*QBIRate,MAX(0.5*F9,0.25*F9+0.025*F12)) -> 18208.877 | G56: =MIN(MAX(0,G55)*QBIRate,MAX(0.5*G9,0.25*G9+0.025*G12)) -> 0 | H56: =MIN(MAX(0,H55)*QBIRate,MAX(0.5*H9,0.25*H9+0.025*H12)) -> 23334.218 | I56: =MIN(MAX(0,I55)*QBIRate,MAX(0.5*I9,0.25*I9+0.025*I12)) -> 23820.767 | J56: =MIN(MAX(0,J55)*QBIRate,MAX(0.5*J9,0.25*J9+0.025*J12)) -> 24306.466 | K56: =MIN(MAX(0,K55)*QBIRate,MAX(0.5*K9,0.25*K9+0.025*K12)) -> 24790.522 | ... T56: =MIN(MAX(0,T55)*QBIRate,MAX(0.5*T9,0.25*T9+0.025*T12)) -> 39251.714 | U56: =SUM(D56:T56) -> 387680.93
B57: Federal taxable income from the business | D57: =D55-D56 -> -2699.5667 | E57: =E55-E56 -> 71778.179 | F57: =F55-F56 -> 72835.51 | G57: =G55-G56 -> -326950.29 | H57: =H55-H56 -> 93336.873 | I57: =I55-I56 -> 95283.069 | J57: =J55-J56 -> 97225.862 | K57: =K55-K56 -> 99162.088 | ... T57: =T55-T56 -> 157006.86 | U57: =SUM(D57:T57) -> 1115489.2
B58: Fed (passive) loss carryforward, start of year | D58: =0 -> 0 | E58: =D61 -> 0 | F58: =E61 -> 0 | G58: =F61 -> 0 | H58: =G61 -> 76950.294 | I58: =H61 -> 0 | J58: =I61 -> 0 | K58: =J61 -> 0 | L58: =K61 -> 0 | ... T58: =S61 -> 0
B59: Fed (passive) carryforward used | D59: =MIN(D58,MAX(0,D57)) -> 0 | E59: =MIN(E58,MAX(0,E57)) -> 0 | F59: =MIN(F58,MAX(0,F57)) -> 0 | G59: =MIN(G58,MAX(0,G57)) -> 0 | H59: =MIN(H58,MAX(0,H57)) -> 76950.294 | I59: =MIN(I58,MAX(0,I57)) -> 0 | J59: =MIN(J58,MAX(0,J57)) -> 0 | K59: =MIN(K58,MAX(0,K57)) -> 0 | ... T59: =MIN(T58,MAX(0,T57)) -> 0 | U59: =SUM(D59:T59) -> 76950.294
B60: Fed (passive) loss used against other income | D60: =IF(D57<0,MIN(-D57,ParentPassive),0) -> 2699.5667 | E60: =IF(E57<0,MIN(-E57,ParentPassive),0) -> 0 | F60: =IF(F57<0,MIN(-F57,ParentPassive),0) -> 0 | G60: =IF(G57<0,MIN(-G57,ParentPassive),0) -> 250000 | H60: =IF(H57<0,MIN(-H57,ParentPassive),0) -> 0 | I60: =IF(I57<0,MIN(-I57,ParentPassive),0) -> 0 | J60: =IF(J57<0,MIN(-J57,ParentPassive),0) -> 0 | K60: =IF(K57<0,MIN(-K57,ParentPassive),0) -> 0 | ... T60: =IF(T57<0,MIN(-T57,ParentPassive),0) -> 0 | U60: =SUM(D60:T60) -> 358284.21
B61: Fed (passive) loss carryforward, end of year | D61: =D58-D59+MAX(0,-D57)-D60 -> 0 | E61: =E58-E59+MAX(0,-E57)-E60 -> 0 | F61: =F58-F59+MAX(0,-F57)-F60 -> 0 | G61: =G58-G59+MAX(0,-G57)-G60 -> 76950.294 | H61: =H58-H59+MAX(0,-H57)-H60 -> 0 | I61: =I58-I59+MAX(0,-I57)-I60 -> 0 | J61: =J58-J59+MAX(0,-J57)-J60 -> 0 | K61: =K58-K59+MAX(0,-K57)-K60 -> 0 | ... T61: =T58-T59+MAX(0,-T57)-T60 -> 0
B62: Fed (passive) tax (negative = tax saved on other income) | D62: =(MAX(0,D57)-D59-D60)*(ParentFed+NIIT) -> -1101.4232 | E62: =(MAX(0,E57)-E59-E60)*(ParentFed+NIIT) -> 29285.497 | F62: =(MAX(0,F57)-F59-F60)*(ParentFed+NIIT) -> 29716.888 | G62: =(MAX(0,G57)-G59-G60)*(ParentFed+NIIT) -> -102000 | H62: =(MAX(0,H57)-H59-H60)*(ParentFed+NIIT) -> 6685.7242 | I62: =(MAX(0,I57)-I59-I60)*(ParentFed+NIIT) -> 38875.492 | J62: =(MAX(0,J57)-J59-J60)*(ParentFed+NIIT) -> 39668.152 | K62: =(MAX(0,K57)-K59-K60)*(ParentFed+NIIT) -> 40458.132 | ... T62: =(MAX(0,T57)-T59-T60)*(ParentFed+NIIT) -> 64058.797 | U62: =SUM(D62:T62) -> 455119.6
B63: NJ taxable income (EBITDA - NJ depreciation) | D63: =D7-D11 -> 49467.1 | E63: =E7-E11 -> 76856.057 | F63: =F7-F11 -> 82657.72 | G63: =G7-G11 -> -17247.335 | H63: =H7-H11 -> -15188.225 | I63: =I7-I11 -> 39724.779 | J63: =J7-J11 -> 74447.827 | K63: =K7-K11 -> 76868.11 | ... T63: =T7-T11 -> 196258.57 | U63: =SUM(D63:T63) -> 1503170.2
B64: NJ loss carryforward, start of year | D64: =0 -> 0 | E64: =D67 -> 0 | F64: =E67 -> 0 | G64: =F67 -> 0 | H64: =G67 -> 0 | I64: =H67 -> 0 | J64: =I67 -> 0 | K64: =J67 -> 0 | L64: =K67 -> 0 | ... T64: =S67 -> 0
B65: NJ carryforward used | D65: =MIN(D64,MAX(0,D63)) -> 0 | E65: =MIN(E64,MAX(0,E63)) -> 0 | F65: =MIN(F64,MAX(0,F63)) -> 0 | G65: =MIN(G64,MAX(0,G63)) -> 0 | H65: =MIN(H64,MAX(0,H63)) -> 0 | I65: =MIN(I64,MAX(0,I63)) -> 0 | J65: =MIN(J64,MAX(0,J63)) -> 0 | K65: =MIN(K64,MAX(0,K63)) -> 0 | ... T65: =MIN(T64,MAX(0,T63)) -> 0 | U65: =SUM(D65:T65) -> 0
B66: NJ loss used against other income | D66: =IF(D63<0,MIN(-D63,ParentNJBiz),0) -> 0 | E66: =IF(E63<0,MIN(-E63,ParentNJBiz),0) -> 0 | F66: =IF(F63<0,MIN(-F63,ParentNJBiz),0) -> 0 | G66: =IF(G63<0,MIN(-G63,ParentNJBiz),0) -> 17247.335 | H66: =IF(H63<0,MIN(-H63,ParentNJBiz),0) -> 15188.225 | I66: =IF(I63<0,MIN(-I63,ParentNJBiz),0) -> 0 | J66: =IF(J63<0,MIN(-J63,ParentNJBiz),0) -> 0 | K66: =IF(K63<0,MIN(-K63,ParentNJBiz),0) -> 0 | ... T66: =IF(T63<0,MIN(-T63,ParentNJBiz),0) -> 0 | U66: =SUM(D66:T66) -> 32435.561
B67: NJ loss carryforward, end of year | D67: =D64-D65+MAX(0,-D63)-D66 -> 0 | E67: =E64-E65+MAX(0,-E63)-E66 -> 0 | F67: =F64-F65+MAX(0,-F63)-F66 -> 0 | G67: =G64-G65+MAX(0,-G63)-G66 -> 0 | H67: =H64-H65+MAX(0,-H63)-H66 -> 0 | I67: =I64-I65+MAX(0,-I63)-I66 -> 0 | J67: =J64-J65+MAX(0,-J63)-J66 -> 0 | K67: =K64-K65+MAX(0,-K63)-K66 -> 0 | ... T67: =T64-T65+MAX(0,-T63)-T66 -> 0
B68: NJ tax (negative = tax saved on other income) | D68: =(MAX(0,D63)-D65-D66)*ParentNJ -> 4437.1989 | E68: =(MAX(0,E63)-E65-E66)*ParentNJ -> 6893.9883 | F68: =(MAX(0,F63)-F65-F66)*ParentNJ -> 7414.3975 | G68: =(MAX(0,G63)-G65-G66)*ParentNJ -> -1547.086 | H68: =(MAX(0,H63)-H65-H66)*ParentNJ -> -1362.3838 | I68: =(MAX(0,I63)-I65-I66)*ParentNJ -> 3563.3127 | J68: =(MAX(0,J63)-J65-J66)*ParentNJ -> 6677.9701 | K68: =(MAX(0,K63)-K65-K66)*ParentNJ -> 6895.0695 | ... T68: =(MAX(0,T63)-T65-T66)*ParentNJ -> 17604.394 | U68: =SUM(D68:T68) -> 134834.36
B69: Total tax (parents) | D69: =D62+D68 -> 3335.7757 | E69: =E62+E68 -> 36179.485 | F69: =F62+F68 -> 37131.285 | G69: =G62+G68 -> -103547.09 | H69: =H62+H68 -> 5323.3404 | I69: =I62+I68 -> 42438.805 | J69: =J62+J68 -> 46346.122 | K69: =K62+K68 -> 47353.202 | ... T69: =T62+T68 -> 81663.191 | U69: =SUM(D69:T69) -> 589953.97
B70: Ryan's after-tax wages for his hours (stays in the family) | D70: =D8/(1+Burden)*(1-RyanFed-RyanNJ-0.0765) -> 23288.72 | E70: =E8/(1+Burden)*(1-RyanFed-RyanNJ-0.0765) -> 24103.825 | F70: =F8/(1+Burden)*(1-RyanFed-RyanNJ-0.0765) -> 24947.459 | G70: =G8/(1+Burden)*(1-RyanFed-RyanNJ-0.0765) -> 25820.62 | H70: =H8/(1+Burden)*(1-RyanFed-RyanNJ-0.0765) -> 26724.342 | I70: =I8/(1+Burden)*(1-RyanFed-RyanNJ-0.0765) -> 27659.694 | J70: =J8/(1+Burden)*(1-RyanFed-RyanNJ-0.0765) -> 28627.783 | K70: =K8/(1+Burden)*(1-RyanFed-RyanNJ-0.0765) -> 29629.756 | ... T70: =T8/(1+Burden)*(1-RyanFed-RyanNJ-0.0765) -> 40382.315 | U70: =SUM(D70:T70) -> 528770.75
B71: Family after-tax cash flow | C71: =C13 -> -480000 | D71: =D13-D69+D70-D14*ExitTax -> 127920.04 | E71: =E13-E69+E70-E14*ExitTax -> 103313.73 | F71: =F13-F69+F70-F14*ExitTax -> 104527.23 | G71: =G13-G69+G70-G14*ExitTax -> -171915.92 | H71: =H13-H69+H70-H14*ExitTax -> 163738.76 | I71: =I13-I69+I70-I14*ExitTax -> 129991.39 | J71: =J13-J69+J70-J14*ExitTax -> 129480.66 | K71: =K13-K69+K70-K14*ExitTax -> 131895.83 | ... T71: =T13-T69+T70-T14*ExitTax -> 371049.19 | U71: =SUM(D71:T71) -> 2128058.4
B73: D. Ryan's LLC owns 100%, funded by an AFR loan from parents; S-corp from SCorpYear (runner-up; structure E is in structure_e.py)
B74: Loan balance, start of year | D74: =LoanAmt -> 500000 | E74: =MAX(0,D74-LoanForgive) -> 462000 | F74: =MAX(0,E74-LoanForgive) -> 424000 | G74: =MAX(0,F74-LoanForgive) -> 386000 | H74: =MAX(0,G74-LoanForgive) -> 348000 | I74: =MAX(0,H74-LoanForgive) -> 310000 | J74: =MAX(0,I74-LoanForgive) -> 272000 | K74: =MAX(0,J74-LoanForgive) -> 234000 | L74: =MAX(0,K74-LoanForgive) -> 196000 | ... T74: =MAX(0,S74-LoanForgive) -> 0
B75: Interest paid to parents | D75: =D74*LoanRate -> 23050 | E75: =E74*LoanRate -> 21298.2 | F75: =F74*LoanRate -> 19546.4 | G75: =G74*LoanRate -> 17794.6 | H75: =H74*LoanRate -> 16042.8 | I75: =I74*LoanRate -> 14291 | J75: =J74*LoanRate -> 12539.2 | K75: =K74*LoanRate -> 10787.4 | ... T75: =T74*LoanRate -> 0 | U75: =SUM(D75:T75) -> 163286.2
B76: S-corp year? (1 = yes) | D76: =IF(D$5>=SCorpYear,1,0) -> 0 | E76: =IF(E$5>=SCorpYear,1,0) -> 1 | F76: =IF(F$5>=SCorpYear,1,0) -> 1 | G76: =IF(G$5>=SCorpYear,1,0) -> 1 | H76: =IF(H$5>=SCorpYear,1,0) -> 1 | I76: =IF(I$5>=SCorpYear,1,0) -> 1 | J76: =IF(J$5>=SCorpYear,1,0) -> 1 | K76: =IF(K$5>=SCorpYear,1,0) -> 1 | ... T76: =IF(T$5>=SCorpYear,1,0) -> 1
B77: Ryan's S-corp salary | D77: =D76*RyanSalary*(1+WageGrowth)^MAX(0,D$5-SCorpYear) -> 0 | E77: =E76*RyanSalary*(1+WageGrowth)^MAX(0,E$5-SCorpYear) -> 60000 | F77: =F76*RyanSalary*(1+WageGrowth)^MAX(0,F$5-SCorpYear) -> 62100 | G77: =G76*RyanSalary*(1+WageGrowth)^MAX(0,G$5-SCorpYear) -> 64273.5 | H77: =H76*RyanSalary*(1+WageGrowth)^MAX(0,H$5-SCorpYear) -> 66523.072 | I77: =I76*RyanSalary*(1+WageGrowth)^MAX(0,I$5-SCorpYear) -> 68851.38 | J77: =J76*RyanSalary*(1+WageGrowth)^MAX(0,J$5-SCorpYear) -> 71261.178 | K77: =K76*RyanSalary*(1+WageGrowth)^MAX(0,K$5-SCorpYear) -> 73755.32 | ... T77: =T76*RyanSalary*(1+WageGrowth)^MAX(0,T$5-SCorpYear) -> 100520.93 | U77: =SUM(D77:T77) -> 1258261.8
B78: Business income before owner pay (EBITDA + Ryan's hours - fed depreciation - interest) | D78: =D7+D8-D10-D75 -> 16474.433 | E78: =E7+E8-E10-E75 -> 112126.36 | F78: =F7+F8-F10-F75 -> 116729.39 | G78: =G7+G8-G10-G75 -> -297930.39 | H78: =H7+H8-H10-H75 -> 149081.3 | I78: =I7+I8-I10-I75 -> 154961.7 | J78: =J7+J8-J10-J75 -> 160897.2 | K78: =K7+K8-K10-K75 -> 166885.93 | ... T78: =T7+T8-T10-T75 -> 269474.4 | U78: =SUM(D78:T78) -> 2298580.5
B79: Employer share of payroll tax on salary (deductible) | D79: =D77*(SCorpPayroll-0.0765) -> 0 | E79: =E77*(SCorpPayroll-0.0765) -> 6390 | F79: =F77*(SCorpPayroll-0.0765) -> 6613.65 | G79: =G77*(SCorpPayroll-0.0765) -> 6845.1277 | H79: =H77*(SCorpPayroll-0.0765) -> 7084.7072 | I79: =I77*(SCorpPayroll-0.0765) -> 7332.672 | J79: =J77*(SCorpPayroll-0.0765) -> 7589.3155 | K79: =K77*(SCorpPayroll-0.0765) -> 7854.9415 | ... T79: =T77*(SCorpPayroll-0.0765) -> 10705.479 | U79: =SUM(D79:T79) -> 134004.88
B80: SE tax (LLC year) or payroll tax on salary (S-corp years) | D80: =IF(D76=1,D77*SCorpPayroll,IF(D78>0,MIN(D78*0.9235,SSBase*(1+WageGrowth)^(D$5-1))*0.124+D78*0.9235*0.029,0)) -> 2327.7633 | E80: =IF(E76=1,E77*SCorpPayroll,IF(E78>0,MIN(E78*0.9235,SSBase*(1+WageGrowth)^(E$5-1))*0.124+E78*0.9235*0.029,0)) -> 10980 | F80: =IF(F76=1,F77*SCorpPayroll,IF(F78>0,MIN(F78*0.9235,SSBase*(1+WageGrowth)^(F$5-1))*0.124+F78*0.9235*0.029,0)) -> 11364.3 | G80: =IF(G76=1,G77*SCorpPayroll,IF(G78>0,MIN(G78*0.9235,SSBase*(1+WageGrowth)^(G$5-1))*0.124+G78*0.9235*0.029,0)) -> 11762.05 | H80: =IF(H76=1,H77*SCorpPayroll,IF(H78>0,MIN(H78*0.9235,SSBase*(1+WageGrowth)^(H$5-1))*0.124+H78*0.9235*0.029,0)) -> 12173.722 | I80: =IF(I76=1,I77*SCorpPayroll,IF(I78>0,MIN(I78*0.9235,SSBase*(1+WageGrowth)^(I$5-1))*0.124+I78*0.9235*0.029,0)) -> 12599.803 | J80: =IF(J76=1,J77*SCorpPayroll,IF(J78>0,MIN(J78*0.9235,SSBase*(1+WageGrowth)^(J$5-1))*0.124+J78*0.9235*0.029,0)) -> 13040.796 | K80: =IF(K76=1,K77*SCorpPayroll,IF(K78>0,MIN(K78*0.9235,SSBase*(1+WageGrowth)^(K$5-1))*0.124+K78*0.9235*0.029,0)) -> 13497.223 | ... T80: =IF(T76=1,T77*SCorpPayroll,IF(T78>0,MIN(T78*0.9235,SSBase*(1+WageGrowth)^(T$5-1))*0.124+T78*0.9235*0.029,0)) -> 18395.33 | U80: =SUM(D80:T80) -> 232589.67
B81: QBI deduction (on profit after salary) | D81: =MAX(0,D78-IF(D76=1,D77+D79,D80/2))*QBIRate -> 3062.1103 | E81: =MAX(0,E78-IF(E76=1,E77+E79,E80/2))*QBIRate -> 9147.2727 | F81: =MAX(0,F78-IF(F76=1,F77+F79,F80/2))*QBIRate -> 9603.1483 | G81: =MAX(0,G78-IF(G76=1,G77+G79,G80/2))*QBIRate -> 0 | H81: =MAX(0,H78-IF(H76=1,H77+H79,H80/2))*QBIRate -> 15094.705 | I81: =MAX(0,I78-IF(I76=1,I77+I79,I80/2))*QBIRate -> 15755.53 | J81: =MAX(0,J78-IF(J76=1,J77+J79,J80/2))*QBIRate -> 16409.342 | K81: =MAX(0,K78-IF(K76=1,K77+K79,K80/2))*QBIRate -> 17055.134 | ... T81: =MAX(0,T78-IF(T76=1,T77+T79,T80/2))*QBIRate -> 31649.598 | U81: =SUM(D81:T81) -> 283247.46
B82: Federal taxable income (salary + K-1) | D82: =D78-IF(D76=1,D79,D80/2)-D81 -> 12248.441 | E82: =E78-IF(E76=1,E79,E80/2)-E81 -> 96589.091 | F82: =F78-IF(F76=1,F79,F80/2)-F81 -> 100512.59 | G82: =G78-IF(G76=1,G79,G80/2)-G81 -> -304775.52 | H82: =H78-IF(H76=1,H79,H80/2)-H81 -> 126901.89 | I82: =I78-IF(I76=1,I79,I80/2)-I81 -> 131873.5 | J82: =J78-IF(J76=1,J79,J80/2)-J81 -> 136898.55 | K82: =K78-IF(K76=1,K79,K80/2)-K81 -> 141975.85 | ... T82: =T78-IF(T76=1,T79,T80/2)-T81 -> 227119.32 | U82: =SUM(D82:T82) -> 1880164.3
B83: Fed loss carryforward, start of year | D83: =0 -> 0 | E83: =D86 -> 0 | F83: =E86 -> 0 | G83: =F86 -> 0 | H83: =G86 -> 254775.52 | I83: =H86 -> 127873.63 | J83: =I86 -> 0 | K83: =J86 -> 0 | L83: =K86 -> 0 | ... T83: =S86 -> 0
B84: Fed carryforward used | D84: =MIN(D83,MAX(0,D82)) -> 0 | E84: =MIN(E83,MAX(0,E82)) -> 0 | F84: =MIN(F83,MAX(0,F82)) -> 0 | G84: =MIN(G83,MAX(0,G82)) -> 0 | H84: =MIN(H83,MAX(0,H82)) -> 126901.89 | I84: =MIN(I83,MAX(0,I82)) -> 127873.63 | J84: =MIN(J83,MAX(0,J82)) -> 0 | K84: =MIN(K83,MAX(0,K82)) -> 0 | ... T84: =MIN(T83,MAX(0,T82)) -> 0 | U84: =SUM(D84:T84) -> 265039.95
B85: Fed loss used against other income | D85: =IF(D82<0,MIN(-D82,MIN(RyanOtherInc,EBLSingle)),0) -> 0 | E85: =IF(E82<0,MIN(-E82,MIN(RyanOtherInc,EBLSingle)),0) -> 0 | F85: =IF(F82<0,MIN(-F82,MIN(RyanOtherInc,EBLSingle)),0) -> 0 | G85: =IF(G82<0,MIN(-G82,MIN(RyanOtherInc,EBLSingle)),0) -> 50000 | H85: =IF(H82<0,MIN(-H82,MIN(RyanOtherInc,EBLSingle)),0) -> 0 | I85: =IF(I82<0,MIN(-I82,MIN(RyanOtherInc,EBLSingle)),0) -> 0 | J85: =IF(J82<0,MIN(-J82,MIN(RyanOtherInc,EBLSingle)),0) -> 0 | K85: =IF(K82<0,MIN(-K82,MIN(RyanOtherInc,EBLSingle)),0) -> 0 | ... T85: =IF(T82<0,MIN(-T82,MIN(RyanOtherInc,EBLSingle)),0) -> 0 | U85: =SUM(D85:T85) -> 100000
B86: Fed loss carryforward, end of year | D86: =D83-D84+MAX(0,-D82)-D85 -> 0 | E86: =E83-E84+MAX(0,-E82)-E85 -> 0 | F86: =F83-F84+MAX(0,-F82)-F85 -> 0 | G86: =G83-G84+MAX(0,-G82)-G85 -> 254775.52 | H86: =H83-H84+MAX(0,-H82)-H85 -> 127873.63 | I86: =I83-I84+MAX(0,-I82)-I85 -> 0 | J86: =J83-J84+MAX(0,-J82)-J85 -> 0 | K86: =K83-K84+MAX(0,-K82)-K85 -> 0 | ... T86: =T83-T84+MAX(0,-T82)-T85 -> 0
B87: Fed tax (negative = tax saved on other income) | D87: =(MAX(0,D82)-D84-D85)*RyanFed -> 2694.6571 | E87: =(MAX(0,E82)-E84-E85)*RyanFed -> 21249.6 | F87: =(MAX(0,F82)-F84-F85)*RyanFed -> 22112.771 | G87: =(MAX(0,G82)-G84-G85)*RyanFed -> -11000 | H87: =(MAX(0,H82)-H84-H85)*RyanFed -> 0 | I87: =(MAX(0,I82)-I84-I85)*RyanFed -> 879.97199 | J87: =(MAX(0,J82)-J84-J85)*RyanFed -> 30117.68 | K87: =(MAX(0,K82)-K84-K85)*RyanFed -> 31234.688 | ... T87: =(MAX(0,T82)-T84-T85)*RyanFed -> 49966.25 | U87: =SUM(D87:T87) -> 413636.15
B88: NJ taxable income | D88: =D7+D8-D11-D75-D79 -> 68641.1 | E88: =E7+E8-E11-E75-E79 -> 92869.697 | F88: =F7+F8-F11-F75-F79 -> 101729.07 | G88: =G7+G8-G11-G75-G79 -> 4927.4404 | H88: =H7+H8-H11-H75-H79 -> 10137.279 | I88: =I7+I8-I11-I75-I79 -> 68249.974 | J88: =J7+J8-J11-J75-J79 -> 106223.39 | K88: =K7+K8-K11-K75-K79 -> 111946.49 | ... T88: =T7+T8-T11-T75-T79 -> 258768.92 | U88: =SUM(D88:T88) -> 2164575.7
B89: NJ loss carryforward, start of year | D89: =0 -> 0 | E89: =D92 -> 0 | F89: =E92 -> 0 | G89: =F92 -> 0 | H89: =G92 -> 0 | I89: =H92 -> 0 | J89: =I92 -> 0 | K89: =J92 -> 0 | L89: =K92 -> 0 | ... T89: =S92 -> 0
B90: NJ carryforward used | D90: =MIN(D89,MAX(0,D88)) -> 0 | E90: =MIN(E89,MAX(0,E88)) -> 0 | F90: =MIN(F89,MAX(0,F88)) -> 0 | G90: =MIN(G89,MAX(0,G88)) -> 0 | H90: =MIN(H89,MAX(0,H88)) -> 0 | I90: =MIN(I89,MAX(0,I88)) -> 0 | J90: =MIN(J89,MAX(0,J88)) -> 0 | K90: =MIN(K89,MAX(0,K88)) -> 0 | ... T90: =MIN(T89,MAX(0,T88)) -> 0 | U90: =SUM(D90:T90) -> 0
B91: NJ loss used against other income | D91: =IF(D88<0,MIN(-D88,0),0) -> 0 | E91: =IF(E88<0,MIN(-E88,0),0) -> 0 | F91: =IF(F88<0,MIN(-F88,0),0) -> 0 | G91: =IF(G88<0,MIN(-G88,0),0) -> 0 | H91: =IF(H88<0,MIN(-H88,0),0) -> 0 | I91: =IF(I88<0,MIN(-I88,0),0) -> 0 | J91: =IF(J88<0,MIN(-J88,0),0) -> 0 | K91: =IF(K88<0,MIN(-K88,0),0) -> 0 | ... T91: =IF(T88<0,MIN(-T88,0),0) -> 0 | U91: =SUM(D91:T91) -> 0
B92: NJ loss carryforward, end of year | D92: =D89-D90+MAX(0,-D88)-D91 -> 0 | E92: =E89-E90+MAX(0,-E88)-E91 -> 0 | F92: =F89-F90+MAX(0,-F88)-F91 -> 0 | G92: =G89-G90+MAX(0,-G88)-G91 -> 0 | H92: =H89-H90+MAX(0,-H88)-H91 -> 0 | I92: =I89-I90+MAX(0,-I88)-I91 -> 0 | J92: =J89-J90+MAX(0,-J88)-J91 -> 0 | K92: =K89-K90+MAX(0,-K88)-K91 -> 0 | ... T92: =T89-T90+MAX(0,-T88)-T91 -> 0
B93: NJ tax (negative = tax saved on other income) | D93: =(MAX(0,D88)-D90-D91)*RyanNJ -> 4372.4381 | E93: =(MAX(0,E88)-E90-E91)*RyanNJ -> 5915.7997 | F93: =(MAX(0,F88)-F90-F91)*RyanNJ -> 6480.1421 | G93: =(MAX(0,G88)-G90-G91)*RyanNJ -> 313.87795 | H93: =(MAX(0,H88)-H90-H91)*RyanNJ -> 645.74464 | I93: =(MAX(0,I88)-I90-I91)*RyanNJ -> 4347.5233 | J93: =(MAX(0,J88)-J90-J91)*RyanNJ -> 6766.4298 | K93: =(MAX(0,K88)-K90-K91)*RyanNJ -> 7130.9913 | ... T93: =(MAX(0,T88)-T90-T91)*RyanNJ -> 16483.58 | U93: =SUM(D93:T93) -> 137883.47
B94: Total tax (Ryan: federal + SE/payroll + NJ) | D94: =D87+D80+D93 -> 9394.8585 | E94: =E87+E80+E93 -> 38145.4 | F94: =F87+F80+F93 -> 39957.213 | G94: =G87+G80+G93 -> 1075.9285 | H94: =H87+H80+H93 -> 12819.467 | I94: =I87+I80+I93 -> 17827.298 | J94: =J87+J80+J93 -> 49924.906 | K94: =K87+K80+K93 -> 51862.903 | ... T94: =T87+T80+T93 -> 84845.161 | U94: =SUM(D94:T94) -> 784109.29
B95: Parents' after-tax interest received (stays in the family) | D95: =D75*(1-ParentFed-NIIT-ParentNJ) -> 11578.015 | E95: =E75*(1-ParentFed-NIIT-ParentNJ) -> 10698.086 | F95: =F75*(1-ParentFed-NIIT-ParentNJ) -> 9818.1567 | G95: =G75*(1-ParentFed-NIIT-ParentNJ) -> 8938.2276 | H95: =H75*(1-ParentFed-NIIT-ParentNJ) -> 8058.2984 | I95: =I75*(1-ParentFed-NIIT-ParentNJ) -> 7178.3693 | J95: =J75*(1-ParentFed-NIIT-ParentNJ) -> 6298.4402 | K95: =K75*(1-ParentFed-NIIT-ParentNJ) -> 5418.511 | ... T95: =T75*(1-ParentFed-NIIT-ParentNJ) -> 0 | U95: =SUM(D95:T95) -> 82018.658
B96: Family after-tax cash flow | C96: =C13 -> -480000 | D96: =D13+D8-D94-D75+D95-D14*ExitTax -> 129324.26 | E96: =E13+E8-E94-E75+E95-E14*ExitTax -> 110345.72 | F96: =F13+F8-F94-F75+F95-F14*ExitTax -> 112257 | G96: =G13+G8-G94-G75+G95-G14*ExitTax -> -264401.42 | H96: =H13+H8-H94-H75+H95-H14*ExitTax -> 169986.8 | I96: =I13+I8-I94-I75+I95-I14*ExitTax -> 169979.44 | J96: =J13+J8-J94-J75+J95-J14*ExitTax -> 142937.41 | K96: =K13+K8-K94-K75+K95-K14*ExitTax -> 146108.21 | ... T96: =T13+T8-T94-T75+T95-T14*ExitTax -> 400700.73 | U96: =SUM(D96:T96) -> 2282561.4
B97: Ryan's own after-tax cash flow (after interest to parents) | C97: =C13+LoanAmt -> 20000 | D97: =D13+D8-D94-D75-D14*ExitTax -> 117746.24 | E97: =E13+E8-E94-E75-E14*ExitTax -> 99647.63 | F97: =F13+F8-F94-F75-F14*ExitTax -> 102438.85 | G97: =G13+G8-G94-G75-G14*ExitTax -> -273339.65 | H97: =H13+H8-H94-H75-H14*ExitTax -> 161928.5 | I97: =I13+I8-I94-I75-I14*ExitTax -> 162801.07 | J97: =J13+J8-J94-J75-J14*ExitTax -> 136638.97 | K97: =K13+K8-K94-K75-K14*ExitTax -> 140689.69 | ... T97: =T13+T8-T94-T75-T14*ExitTax -> 400700.73 | U97: =SUM(D97:T97) -> 2200542.7
B99: Comparison
B100: Structure | C100: NPV @ discount rate | D100: After-tax IRR | E100: Total tax yrs 1-17 | F100: Year-1 tax (neg = saving)
B101: A Ryan owns (gift), single-member LLC | C101: =C33+NPV(DiscRate,D33:T33) -> 388418.1 | D101: =IRR(C33:T33) -> 0.19149462 | E101: =U32 -> 935027.66 | F101: =D32 -> 17890.201
B102: B Parents own, passive, no passive income | C102: =C52+NPV(DiscRate,D52:T52) -> 353962.62 | D102: =IRR(C52:T52) -> 0.18300719 | E102: =U50 -> 589953.97 | F102: =D50 -> 4437.1989
B103: C Parents own, passive, with passive income | C103: =C71+NPV(DiscRate,D71:T71) -> 371078.76 | D103: =IRR(C71:T71) -> 0.19066626 | E103: =U69 -> 589953.97 | F103: =D69 -> 3335.7757
B104: D Ryan owns, AFR loan from parents, S-corp later | C104: =C96+NPV(DiscRate,D96:T96) -> 402532.12 | D104: =IRR(C96:T96) -> 0.19196049 | E104: =U94 -> 784109.29 | F104: =D94 -> 9394.8585
B106: Simplifications: marginal-rate method; NOLs used without the 80% limit; Ryan's QBI assumed below the threshold; SE tax ignores Ryan's other wages; exit taxed at one blended rate. Have a CPA run the final structure.

Sheet Depreciation
B2: Capex plan and depreciation (federal vs. state)
B3: Columns are years 0 (closing) to 17. Year-0 spend is placed in service in tax Year 1.
B5: Year | C5: 0 | D5: 1 | E5: 2 | F5: 3 | G5: 4 | H5: 5 | I5: 6 | J5: 7 | K5: 8 | L5: 9 | M5: 10 | N5: 11 | O5: 12 | P5: 13 | Q5: 14 | R5: 15 | S5: 16 | T5: 17
B7: Capex schedule by scenario (today's $; source: equipment thread capex_schedule.csv)
B8: 1 Keep & repair; replace as machines wear out (yr 4, yr 11) | C8: 0 | D8: 0 | E8: 0 | F8: 0 | G8: 372500 | H8: 0 | I8: 0 | J8: 0 | K8: 0 | L8: 0 | M8: 0 | N8: 171000 | O8: 0 | P8: 0 | Q8: 0 | R8: 0 | S8: 0 | T8: 0 | U8: Source: capex_scenarios.json (2026-10-16)
B9: 2 Washers at close; dryers as they wear out (yr 0, yr 11) | C9: 363188 | D9: 0 | E9: 0 | F9: 0 | G9: 0 | H9: 0 | I9: 0 | J9: 0 | K9: 0 | L9: 0 | M9: 0 | N9: 171000 | O9: 0 | P9: 0 | Q9: 0 | R9: 0 | S9: 0 | T9: 0
B10: 3 Full retool at close (yr 0) | C10: 529912 | D10: 0 | E10: 0 | F10: 0 | G10: 0 | H10: 0 | I10: 0 | J10: 0 | K10: 0 | L10: 0 | M10: 0 | N10: 0 | O10: 0 | P10: 0 | Q10: 0 | R10: 0 | S10: 0 | T10: 0
B11: 4 Bear: fleet 3 yrs older than stated (yr 1, yr 8) | C11: 0 | D11: 372500 | E11: 0 | F11: 0 | G11: 0 | H11: 0 | I11: 0 | J11: 0 | K11: 171000 | L11: 0 | M11: 0 | N11: 0 | O11: 0 | P11: 0 | Q11: 0 | R11: 0 | S11: 0 | T11: 0
B12: Selected scenario capex (inflated) | C12: =INDEX(C8:C11,CapexScenario)*(1+CapexInfl)^C$5 -> 0 | D12: =INDEX(D8:D11,CapexScenario)*(1+CapexInfl)^D$5 -> 0 | E12: =INDEX(E8:E11,CapexScenario)*(1+CapexInfl)^E$5 -> 0 | F12: =INDEX(F8:F11,CapexScenario)*(1+CapexInfl)^F$5 -> 0 | G12: =INDEX(G8:G11,CapexScenario)*(1+CapexInfl)^G$5 -> 419252.03 | H12: =INDEX(H8:H11,CapexScenario)*(1+CapexInfl)^H$5 -> 0 | I12: =INDEX(I8:I11,CapexScenario)*(1+CapexInfl)^I$5 -> 0 | J12: =INDEX(J8:J11,CapexScenario)*(1+CapexInfl)^J$5 -> 0 | ... T12: =INDEX(T8:T11,CapexScenario)*(1+CapexInfl)^T$5 -> 0
B13: Share of fleet that is new (drives revenue lift, utilities, repairs) | C13: =0 -> 0 | D13: =IF(SUM($C$12:$T$12)=0,0,SUM($C$12:C$12)/SUM($C$12:$T$12)) -> 0 | E13: =IF(SUM($C$12:$T$12)=0,0,SUM($C$12:D$12)/SUM($C$12:$T$12)) -> 0 | F13: =IF(SUM($C$12:$T$12)=0,0,SUM($C$12:E$12)/SUM($C$12:$T$12)) -> 0 | G13: =IF(SUM($C$12:$T$12)=0,0,SUM($C$12:F$12)/SUM($C$12:$T$12)) -> 0 | H13: =IF(SUM($C$12:$T$12)=0,0,SUM($C$12:G$12)/SUM($C$12:$T$12)) -> 0.63914655 | I13: =IF(SUM($C$12:$T$12)=0,0,SUM($C$12:H$12)/SUM($C$12:$T$12)) -> 0.63914655 | J13: =IF(SUM($C$12:$T$12)=0,0,SUM($C$12:I$12)/SUM($C$12:$T$12)) -> 0.63914655 | K13: =IF(SUM($C$12:$T$12)=0,0,SUM($C$12:J$12)/SUM($C$12:$T$12)) -> 0.63914655 | ... T13: =IF(SUM($C$12:$T$12)=0,0,SUM($C$12:S$12)/SUM($C$12:$T$12)) -> 1
B15: MACRS rate tables (half-year convention), by recovery year 1-20
B16: 5-yr MACRS 200DB | C16: 0.2 | D16: 0.32 | E16: 0.192 | F16: 0.1152 | G16: 0.1152 | H16: 0.0576 | I16: 0 | J16: 0 | K16: 0 | L16: 0 | M16: 0 | N16: 0 | O16: 0 | P16: 0 | Q16: 0 | R16: 0 | S16: 0 | T16: 0 | U16: 0 | V16: 0 | X16: IRS Pub 946 Table A-1
B17: 7-yr MACRS 200DB | C17: 0.1429 | D17: 0.2449 | E17: 0.1749 | F17: 0.1249 | G17: 0.0893 | H17: 0.0892 | I17: 0.0893 | J17: 0.0446 | K17: 0 | L17: 0 | M17: 0 | N17: 0 | O17: 0 | P17: 0 | Q17: 0 | R17: 0 | S17: 0 | T17: 0 | U17: 0 | V17: 0
B18: 15-yr straight line (QIP) | C18: 0.033333333 | D18: 0.066666667 | E18: 0.066666667 | F18: 0.066666667 | G18: 0.066666667 | H18: 0.066666667 | I18: 0.066666667 | J18: 0.066666667 | K18: 0.066666667 | L18: 0.066666667 | M18: 0.066666667 | N18: 0.066666667 | O18: 0.066666667 | P18: 0.066666667 | Q18: 0.066666667 | R18: 0.033333333 | S18: 0 | T18: 0 | U18: 0 | V18: 0
B19: Machines: selected table | C19: =IF(EquipLife=7,C17,C16) -> 0.2 | D19: =IF(EquipLife=7,D17,D16) -> 0.32 | E19: =IF(EquipLife=7,E17,E16) -> 0.192 | F19: =IF(EquipLife=7,F17,F16) -> 0.1152 | G19: =IF(EquipLife=7,G17,G16) -> 0.1152 | H19: =IF(EquipLife=7,H17,H16) -> 0.0576 | I19: =IF(EquipLife=7,I17,I16) -> 0 | J19: =IF(EquipLife=7,J17,J16) -> 0 | ... V19: =IF(EquipLife=7,V17,V16) -> 0
B21: Machines placed in service by tax year
B22: Machines placed in service (acquired fleet + capex) | D22: =AllocEquip+C12+D12 -> 60000 | E22: =E12 -> 0 | F22: =F12 -> 0 | G22: =G12 -> 419252.03 | H22: =H12 -> 0 | I22: =I12 -> 0 | J22: =J12 -> 0 | K22: =K12 -> 0 | L22: =L12 -> 0 | ... T22: =T12 -> 0
B24: Federal: machines (bonus + MACRS)
B25: Vintage year 1 | D25: =$D$22*(IF(1=1,Bonus,0)+(1-Bonus)*INDEX($C$19:$V$19,1)) -> 60000 | E25: =$D$22*(IF(2=1,Bonus,0)+(1-Bonus)*INDEX($C$19:$V$19,2)) -> 0 | F25: =$D$22*(IF(3=1,Bonus,0)+(1-Bonus)*INDEX($C$19:$V$19,3)) -> 0 | G25: =$D$22*(IF(4=1,Bonus,0)+(1-Bonus)*INDEX($C$19:$V$19,4)) -> 0 | H25: =$D$22*(IF(5=1,Bonus,0)+(1-Bonus)*INDEX($C$19:$V$19,5)) -> 0 | I25: =$D$22*(IF(6=1,Bonus,0)+(1-Bonus)*INDEX($C$19:$V$19,6)) -> 0 | J25: =$D$22*(IF(7=1,Bonus,0)+(1-Bonus)*INDEX($C$19:$V$19,7)) -> 0 | K25: =$D$22*(IF(8=1,Bonus,0)+(1-Bonus)*INDEX($C$19:$V$19,8)) -> 0 | L25: =$D$22*(IF(9=1,Bonus,0)+(1-Bonus)*INDEX($C$19:$V$19,9)) -> 0 | M25: =$D$22*(IF(10=1,Bonus,0)+(1-Bonus)*INDEX($C$19:$V$19,10)) -> 0 | N25: =$D$22*(IF(11=1,Bonus,0)+(1-Bonus)*INDEX($C$19:$V$19,11)) -> 0 | O25: =$D$22*(IF(12=1,Bonus,0)+(1-Bonus)*INDEX($C$19:$V$19,12)) -> 0 | P25: =$D$22*(IF(13=1,Bonus,0)+(1-Bonus)*INDEX($C$19:$V$19,13)) -> 0 | Q25: =$D$22*(IF(14=1,Bonus,0)+(1-Bonus)*INDEX($C$19:$V$19,14)) -> 0 | R25: =$D$22*(IF(15=1,Bonus,0)+(1-Bonus)*INDEX($C$19:$V$19,15)) -> 0 | S25: =$D$22*(IF(16=1,Bonus,0)+(1-Bonus)*INDEX($C$19:$V$19,16)) -> 0 | T25: =$D$22*(IF(17=1,Bonus,0)+(1-Bonus)*INDEX($C$19:$V$19,17)) -> 0
B26: Vintage year 2 | D26: =0 -> 0 | E26: =$E$22*(IF(2=2,Bonus,0)+(1-Bonus)*INDEX($C$19:$V$19,1)) -> 0 | F26: =$E$22*(IF(3=2,Bonus,0)+(1-Bonus)*INDEX($C$19:$V$19,2)) -> 0 | G26: =$E$22*(IF(4=2,Bonus,0)+(1-Bonus)*INDEX($C$19:$V$19,3)) -> 0 | H26: =$E$22*(IF(5=2,Bonus,0)+(1-Bonus)*INDEX($C$19:$V$19,4)) -> 0 | I26: =$E$22*(IF(6=2,Bonus,0)+(1-Bonus)*INDEX($C$19:$V$19,5)) -> 0 | J26: =$E$22*(IF(7=2,Bonus,0)+(1-Bonus)*INDEX($C$19:$V$19,6)) -> 0 | K26: =$E$22*(IF(8=2,Bonus,0)+(1-Bonus)*INDEX($C$19:$V$19,7)) -> 0 | L26: =$E$22*(IF(9=2,Bonus,0)+(1-Bonus)*INDEX($C$19:$V$19,8)) -> 0 | M26: =$E$22*(IF(10=2,Bonus,0)+(1-Bonus)*INDEX($C$19:$V$19,9)) -> 0 | N26: =$E$22*(IF(11=2,Bonus,0)+(1-Bonus)*INDEX($C$19:$V$19,10)) -> 0 | O26: =$E$22*(IF(12=2,Bonus,0)+(1-Bonus)*INDEX($C$19:$V$19,11)) -> 0 | P26: =$E$22*(IF(13=2,Bonus,0)+(1-Bonus)*INDEX($C$19:$V$19,12)) -> 0 | Q26: =$E$22*(IF(14=2,Bonus,0)+(1-Bonus)*INDEX($C$19:$V$19,13)) -> 0 | R26: =$E$22*(IF(15=2,Bonus,0)+(1-Bonus)*INDEX($C$19:$V$19,14)) -> 0 | S26: =$E$22*(IF(16=2,Bonus,0)+(1-Bonus)*INDEX($C$19:$V$19,15)) -> 0 | T26: =$E$22*(IF(17=2,Bonus,0)+(1-Bonus)*INDEX($C$19:$V$19,16)) -> 0
B27: Vintage year 3 | D27: =0 -> 0 | E27: =0 -> 0 | F27: =$F$22*(IF(3=3,Bonus,0)+(1-Bonus)*INDEX($C$19:$V$19,1)) -> 0 | G27: =$F$22*(IF(4=3,Bonus,0)+(1-Bonus)*INDEX($C$19:$V$19,2)) -> 0 | H27: =$F$22*(IF(5=3,Bonus,0)+(1-Bonus)*INDEX($C$19:$V$19,3)) -> 0 | I27: =$F$22*(IF(6=3,Bonus,0)+(1-Bonus)*INDEX($C$19:$V$19,4)) -> 0 | J27: =$F$22*(IF(7=3,Bonus,0)+(1-Bonus)*INDEX($C$19:$V$19,5)) -> 0 | K27: =$F$22*(IF(8=3,Bonus,0)+(1-Bonus)*INDEX($C$19:$V$19,6)) -> 0 | L27: =$F$22*(IF(9=3,Bonus,0)+(1-Bonus)*INDEX($C$19:$V$19,7)) -> 0 | M27: =$F$22*(IF(10=3,Bonus,0)+(1-Bonus)*INDEX($C$19:$V$19,8)) -> 0 | N27: =$F$22*(IF(11=3,Bonus,0)+(1-Bonus)*INDEX($C$19:$V$19,9)) -> 0 | O27: =$F$22*(IF(12=3,Bonus,0)+(1-Bonus)*INDEX($C$19:$V$19,10)) -> 0 | P27: =$F$22*(IF(13=3,Bonus,0)+(1-Bonus)*INDEX($C$19:$V$19,11)) -> 0 | Q27: =$F$22*(IF(14=3,Bonus,0)+(1-Bonus)*INDEX($C$19:$V$19,12)) -> 0 | R27: =$F$22*(IF(15=3,Bonus,0)+(1-Bonus)*INDEX($C$19:$V$19,13)) -> 0 | S27: =$F$22*(IF(16=3,Bonus,0)+(1-Bonus)*INDEX($C$19:$V$19,14)) -> 0 | T27: =$F$22*(IF(17=3,Bonus,0)+(1-Bonus)*INDEX($C$19:$V$19,15)) -> 0
B28: Vintage year 4 | D28: =0 -> 0 | E28: =0 -> 0 | F28: =0 -> 0 | G28: =$G$22*(IF(4=4,Bonus,0)+(1-Bonus)*INDEX($C$19:$V$19,1)) -> 419252.03 | H28: =$G$22*(IF(5=4,Bonus,0)+(1-Bonus)*INDEX($C$19:$V$19,2)) -> 0 | I28: =$G$22*(IF(6=4,Bonus,0)+(1-Bonus)*INDEX($C$19:$V$19,3)) -> 0 | J28: =$G$22*(IF(7=4,Bonus,0)+(1-Bonus)*INDEX($C$19:$V$19,4)) -> 0 | K28: =$G$22*(IF(8=4,Bonus,0)+(1-Bonus)*INDEX($C$19:$V$19,5)) -> 0 | L28: =$G$22*(IF(9=4,Bonus,0)+(1-Bonus)*INDEX($C$19:$V$19,6)) -> 0 | M28: =$G$22*(IF(10=4,Bonus,0)+(1-Bonus)*INDEX($C$19:$V$19,7)) -> 0 | N28: =$G$22*(IF(11=4,Bonus,0)+(1-Bonus)*INDEX($C$19:$V$19,8)) -> 0 | O28: =$G$22*(IF(12=4,Bonus,0)+(1-Bonus)*INDEX($C$19:$V$19,9)) -> 0 | P28: =$G$22*(IF(13=4,Bonus,0)+(1-Bonus)*INDEX($C$19:$V$19,10)) -> 0 | Q28: =$G$22*(IF(14=4,Bonus,0)+(1-Bonus)*INDEX($C$19:$V$19,11)) -> 0 | R28: =$G$22*(IF(15=4,Bonus,0)+(1-Bonus)*INDEX($C$19:$V$19,12)) -> 0 | S28: =$G$22*(IF(16=4,Bonus,0)+(1-Bonus)*INDEX($C$19:$V$19,13)) -> 0 | T28: =$G$22*(IF(17=4,Bonus,0)+(1-Bonus)*INDEX($C$19:$V$19,14)) -> 0
B29: Vintage year 5 | D29: =0 -> 0 | E29: =0 -> 0 | F29: =0 -> 0 | G29: =0 -> 0 | H29: =$H$22*(IF(5=5,Bonus,0)+(1-Bonus)*INDEX($C$19:$V$19,1)) -> 0 | I29: =$H$22*(IF(6=5,Bonus,0)+(1-Bonus)*INDEX($C$19:$V$19,2)) -> 0 | J29: =$H$22*(IF(7=5,Bonus,0)+(1-Bonus)*INDEX($C$19:$V$19,3)) -> 0 | K29: =$H$22*(IF(8=5,Bonus,0)+(1-Bonus)*INDEX($C$19:$V$19,4)) -> 0 | L29: =$H$22*(IF(9=5,Bonus,0)+(1-Bonus)*INDEX($C$19:$V$19,5)) -> 0 | M29: =$H$22*(IF(10=5,Bonus,0)+(1-Bonus)*INDEX($C$19:$V$19,6)) -> 0 | N29: =$H$22*(IF(11=5,Bonus,0)+(1-Bonus)*INDEX($C$19:$V$19,7)) -> 0 | O29: =$H$22*(IF(12=5,Bonus,0)+(1-Bonus)*INDEX($C$19:$V$19,8)) -> 0 | P29: =$H$22*(IF(13=5,Bonus,0)+(1-Bonus)*INDEX($C$19:$V$19,9)) -> 0 | Q29: =$H$22*(IF(14=5,Bonus,0)+(1-Bonus)*INDEX($C$19:$V$19,10)) -> 0 | R29: =$H$22*(IF(15=5,Bonus,0)+(1-Bonus)*INDEX($C$19:$V$19,11)) -> 0 | S29: =$H$22*(IF(16=5,Bonus,0)+(1-Bonus)*INDEX($C$19:$V$19,12)) -> 0 | T29: =$H$22*(IF(17=5,Bonus,0)+(1-Bonus)*INDEX($C$19:$V$19,13)) -> 0
B30: Vintage year 6 | D30: =0 -> 0 | E30: =0 -> 0 | F30: =0 -> 0 | G30: =0 -> 0 | H30: =0 -> 0 | I30: =$I$22*(IF(6=6,Bonus,0)+(1-Bonus)*INDEX($C$19:$V$19,1)) -> 0 | J30: =$I$22*(IF(7=6,Bonus,0)+(1-Bonus)*INDEX($C$19:$V$19,2)) -> 0 | K30: =$I$22*(IF(8=6,Bonus,0)+(1-Bonus)*INDEX($C$19:$V$19,3)) -> 0 | L30: =$I$22*(IF(9=6,Bonus,0)+(1-Bonus)*INDEX($C$19:$V$19,4)) -> 0 | M30: =$I$22*(IF(10=6,Bonus,0)+(1-Bonus)*INDEX($C$19:$V$19,5)) -> 0 | N30: =$I$22*(IF(11=6,Bonus,0)+(1-Bonus)*INDEX($C$19:$V$19,6)) -> 0 | O30: =$I$22*(IF(12=6,Bonus,0)+(1-Bonus)*INDEX($C$19:$V$19,7)) -> 0 | P30: =$I$22*(IF(13=6,Bonus,0)+(1-Bonus)*INDEX($C$19:$V$19,8)) -> 0 | Q30: =$I$22*(IF(14=6,Bonus,0)+(1-Bonus)*INDEX($C$19:$V$19,9)) -> 0 | R30: =$I$22*(IF(15=6,Bonus,0)+(1-Bonus)*INDEX($C$19:$V$19,10)) -> 0 | S30: =$I$22*(IF(16=6,Bonus,0)+(1-Bonus)*INDEX($C$19:$V$19,11)) -> 0 | T30: =$I$22*(IF(17=6,Bonus,0)+(1-Bonus)*INDEX($C$19:$V$19,12)) -> 0
B31: Vintage year 7 | D31: =0 -> 0 | E31: =0 -> 0 | F31: =0 -> 0 | G31: =0 -> 0 | H31: =0 -> 0 | I31: =0 -> 0 | J31: =$J$22*(IF(7=7,Bonus,0)+(1-Bonus)*INDEX($C$19:$V$19,1)) -> 0 | K31: =$J$22*(IF(8=7,Bonus,0)+(1-Bonus)*INDEX($C$19:$V$19,2)) -> 0 | L31: =$J$22*(IF(9=7,Bonus,0)+(1-Bonus)*INDEX($C$19:$V$19,3)) -> 0 | M31: =$J$22*(IF(10=7,Bonus,0)+(1-Bonus)*INDEX($C$19:$V$19,4)) -> 0 | N31: =$J$22*(IF(11=7,Bonus,0)+(1-Bonus)*INDEX($C$19:$V$19,5)) -> 0 | O31: =$J$22*(IF(12=7,Bonus,0)+(1-Bonus)*INDEX($C$19:$V$19,6)) -> 0 | P31: =$J$22*(IF(13=7,Bonus,0)+(1-Bonus)*INDEX($C$19:$V$19,7)) -> 0 | Q31: =$J$22*(IF(14=7,Bonus,0)+(1-Bonus)*INDEX($C$19:$V$19,8)) -> 0 | R31: =$J$22*(IF(15=7,Bonus,0)+(1-Bonus)*INDEX($C$19:$V$19,9)) -> 0 | S31: =$J$22*(IF(16=7,Bonus,0)+(1-Bonus)*INDEX($C$19:$V$19,10)) -> 0 | T31: =$J$22*(IF(17=7,Bonus,0)+(1-Bonus)*INDEX($C$19:$V$19,11)) -> 0
B32: Vintage year 8 | D32: =0 -> 0 | E32: =0 -> 0 | F32: =0 -> 0 | G32: =0 -> 0 | H32: =0 -> 0 | I32: =0 -> 0 | J32: =0 -> 0 | K32: =$K$22*(IF(8=8,Bonus,0)+(1-Bonus)*INDEX($C$19:$V$19,1)) -> 0 | L32: =$K$22*(IF(9=8,Bonus,0)+(1-Bonus)*INDEX($C$19:$V$19,2)) -> 0 | M32: =$K$22*(IF(10=8,Bonus,0)+(1-Bonus)*INDEX($C$19:$V$19,3)) -> 0 | N32: =$K$22*(IF(11=8,Bonus,0)+(1-Bonus)*INDEX($C$19:$V$19,4)) -> 0 | O32: =$K$22*(IF(12=8,Bonus,0)+(1-Bonus)*INDEX($C$19:$V$19,5)) -> 0 | P32: =$K$22*(IF(13=8,Bonus,0)+(1-Bonus)*INDEX($C$19:$V$19,6)) -> 0 | Q32: =$K$22*(IF(14=8,Bonus,0)+(1-Bonus)*INDEX($C$19:$V$19,7)) -> 0 | R32: =$K$22*(IF(15=8,Bonus,0)+(1-Bonus)*INDEX($C$19:$V$19,8)) -> 0 | S32: =$K$22*(IF(16=8,Bonus,0)+(1-Bonus)*INDEX($C$19:$V$19,9)) -> 0 | T32: =$K$22*(IF(17=8,Bonus,0)+(1-Bonus)*INDEX($C$19:$V$19,10)) -> 0
B33: Vintage year 9 | D33: =0 -> 0 | E33: =0 -> 0 | F33: =0 -> 0 | G33: =0 -> 0 | H33: =0 -> 0 | I33: =0 -> 0 | J33: =0 -> 0 | K33: =0 -> 0 | L33: =$L$22*(IF(9=9,Bonus,0)+(1-Bonus)*INDEX($C$19:$V$19,1)) -> 0 | M33: =$L$22*(IF(10=9,Bonus,0)+(1-Bonus)*INDEX($C$19:$V$19,2)) -> 0 | N33: =$L$22*(IF(11=9,Bonus,0)+(1-Bonus)*INDEX($C$19:$V$19,3)) -> 0 | O33: =$L$22*(IF(12=9,Bonus,0)+(1-Bonus)*INDEX($C$19:$V$19,4)) -> 0 | P33: =$L$22*(IF(13=9,Bonus,0)+(1-Bonus)*INDEX($C$19:$V$19,5)) -> 0 | Q33: =$L$22*(IF(14=9,Bonus,0)+(1-Bonus)*INDEX($C$19:$V$19,6)) -> 0 | R33: =$L$22*(IF(15=9,Bonus,0)+(1-Bonus)*INDEX($C$19:$V$19,7)) -> 0 | S33: =$L$22*(IF(16=9,Bonus,0)+(1-Bonus)*INDEX($C$19:$V$19,8)) -> 0 | T33: =$L$22*(IF(17=9,Bonus,0)+(1-Bonus)*INDEX($C$19:$V$19,9)) -> 0
B34: Vintage year 10 | D34: =0 -> 0 | E34: =0 -> 0 | F34: =0 -> 0 | G34: =0 -> 0 | H34: =0 -> 0 | I34: =0 -> 0 | J34: =0 -> 0 | K34: =0 -> 0 | L34: =0 -> 0 | M34: =$M$22*(IF(10=10,Bonus,0)+(1-Bonus)*INDEX($C$19:$V$19,1)) -> 0 | N34: =$M$22*(IF(11=10,Bonus,0)+(1-Bonus)*INDEX($C$19:$V$19,2)) -> 0 | O34: =$M$22*(IF(12=10,Bonus,0)+(1-Bonus)*INDEX($C$19:$V$19,3)) -> 0 | P34: =$M$22*(IF(13=10,Bonus,0)+(1-Bonus)*INDEX($C$19:$V$19,4)) -> 0 | Q34: =$M$22*(IF(14=10,Bonus,0)+(1-Bonus)*INDEX($C$19:$V$19,5)) -> 0 | R34: =$M$22*(IF(15=10,Bonus,0)+(1-Bonus)*INDEX($C$19:$V$19,6)) -> 0 | S34: =$M$22*(IF(16=10,Bonus,0)+(1-Bonus)*INDEX($C$19:$V$19,7)) -> 0 | T34: =$M$22*(IF(17=10,Bonus,0)+(1-Bonus)*INDEX($C$19:$V$19,8)) -> 0
B35: Vintage year 11 | D35: =0 -> 0 | E35: =0 -> 0 | F35: =0 -> 0 | G35: =0 -> 0 | H35: =0 -> 0 | I35: =0 -> 0 | J35: =0 -> 0 | K35: =0 -> 0 | ... M35: =0 -> 0 | N35: =$N$22*(IF(11=11,Bonus,0)+(1-Bonus)*INDEX($C$19:$V$19,1)) -> 236703.99 | O35: =$N$22*(IF(12=11,Bonus,0)+(1-Bonus)*INDEX($C$19:$V$19,2)) -> 0 | P35: =$N$22*(IF(13=11,Bonus,0)+(1-Bonus)*INDEX($C$19:$V$19,3)) -> 0 | Q35: =$N$22*(IF(14=11,Bonus,0)+(1-Bonus)*INDEX($C$19:$V$19,4)) -> 0 | R35: =$N$22*(IF(15=11,Bonus,0)+(1-Bonus)*INDEX($C$19:$V$19,5)) -> 0 | S35: =$N$22*(IF(16=11,Bonus,0)+(1-Bonus)*INDEX($C$19:$V$19,6)) -> 0 | T35: =$N$22*(IF(17=11,Bonus,0)+(1-Bonus)*INDEX($C$19:$V$19,7)) -> 0
B36: Vintage year 12 | D36: =0 -> 0 | E36: =0 -> 0 | F36: =0 -> 0 | G36: =0 -> 0 | H36: =0 -> 0 | I36: =0 -> 0 | J36: =0 -> 0 | K36: =0 -> 0 | ... N36: =0 -> 0 | O36: =$O$22*(IF(12=12,Bonus,0)+(1-Bonus)*INDEX($C$19:$V$19,1)) -> 0 | P36: =$O$22*(IF(13=12,Bonus,0)+(1-Bonus)*INDEX($C$19:$V$19,2)) -> 0 | Q36: =$O$22*(IF(14=12,Bonus,0)+(1-Bonus)*INDEX($C$19:$V$19,3)) -> 0 | R36: =$O$22*(IF(15=12,Bonus,0)+(1-Bonus)*INDEX($C$19:$V$19,4)) -> 0 | S36: =$O$22*(IF(16=12,Bonus,0)+(1-Bonus)*INDEX($C$19:$V$19,5)) -> 0 | T36: =$O$22*(IF(17=12,Bonus,0)+(1-Bonus)*INDEX($C$19:$V$19,6)) -> 0
B37: Vintage year 13 | D37: =0 -> 0 | E37: =0 -> 0 | F37: =0 -> 0 | G37: =0 -> 0 | H37: =0 -> 0 | I37: =0 -> 0 | J37: =0 -> 0 | K37: =0 -> 0 | ... O37: =0 -> 0 | P37: =$P$22*(IF(13=13,Bonus,0)+(1-Bonus)*INDEX($C$19:$V$19,1)) -> 0 | Q37: =$P$22*(IF(14=13,Bonus,0)+(1-Bonus)*INDEX($C$19:$V$19,2)) -> 0 | R37: =$P$22*(IF(15=13,Bonus,0)+(1-Bonus)*INDEX($C$19:$V$19,3)) -> 0 | S37: =$P$22*(IF(16=13,Bonus,0)+(1-Bonus)*INDEX($C$19:$V$19,4)) -> 0 | T37: =$P$22*(IF(17=13,Bonus,0)+(1-Bonus)*INDEX($C$19:$V$19,5)) -> 0
B38: Vintage year 14 | D38: =0 -> 0 | E38: =0 -> 0 | F38: =0 -> 0 | G38: =0 -> 0 | H38: =0 -> 0 | I38: =0 -> 0 | J38: =0 -> 0 | K38: =0 -> 0 | ... P38: =0 -> 0 | Q38: =$Q$22*(IF(14=14,Bonus,0)+(1-Bonus)*INDEX($C$19:$V$19,1)) -> 0 | R38: =$Q$22*(IF(15=14,Bonus,0)+(1-Bonus)*INDEX($C$19:$V$19,2)) -> 0 | S38: =$Q$22*(IF(16=14,Bonus,0)+(1-Bonus)*INDEX($C$19:$V$19,3)) -> 0 | T38: =$Q$22*(IF(17=14,Bonus,0)+(1-Bonus)*INDEX($C$19:$V$19,4)) -> 0
B39: Vintage year 15 | D39: =0 -> 0 | E39: =0 -> 0 | F39: =0 -> 0 | G39: =0 -> 0 | H39: =0 -> 0 | I39: =0 -> 0 | J39: =0 -> 0 | K39: =0 -> 0 | ... Q39: =0 -> 0 | R39: =$R$22*(IF(15=15,Bonus,0)+(1-Bonus)*INDEX($C$19:$V$19,1)) -> 0 | S39: =$R$22*(IF(16=15,Bonus,0)+(1-Bonus)*INDEX($C$19:$V$19,2)) -> 0 | T39: =$R$22*(IF(17=15,Bonus,0)+(1-Bonus)*INDEX($C$19:$V$19,3)) -> 0
B40: Vintage year 16 | D40: =0 -> 0 | E40: =0 -> 0 | F40: =0 -> 0 | G40: =0 -> 0 | H40: =0 -> 0 | I40: =0 -> 0 | J40: =0 -> 0 | K40: =0 -> 0 | ... R40: =0 -> 0 | S40: =$S$22*(IF(16=16,Bonus,0)+(1-Bonus)*INDEX($C$19:$V$19,1)) -> 0 | T40: =$S$22*(IF(17=16,Bonus,0)+(1-Bonus)*INDEX($C$19:$V$19,2)) -> 0
B41: Vintage year 17 | D41: =0 -> 0 | E41: =0 -> 0 | F41: =0 -> 0 | G41: =0 -> 0 | H41: =0 -> 0 | I41: =0 -> 0 | J41: =0 -> 0 | K41: =0 -> 0 | ... S41: =0 -> 0 | T41: =$T$22*(IF(17=17,Bonus,0)+(1-Bonus)*INDEX($C$19:$V$19,1)) -> 0
B42: Total machine depreciation (FED) | D42: =SUM(D25:D41) -> 60000 | E42: =SUM(E25:E41) -> 0 | F42: =SUM(F25:F41) -> 0 | G42: =SUM(G25:G41) -> 419252.03 | H42: =SUM(H25:H41) -> 0 | I42: =SUM(I25:I41) -> 0 | J42: =SUM(J25:J41) -> 0 | K42: =SUM(K25:K41) -> 0 | ... T42: =SUM(T25:T41) -> 0
B44: State (NJ rules): machines (Sec. 179 cap + MACRS, no bonus)
B45: Vintage year 1 | D45: =IF(1=1,MIN(NJ179,$D$22),0)+($D$22-MIN(NJ179,$D$22))*INDEX($C$19:$V$19,1) -> 32000 | E45: =IF(2=1,MIN(NJ179,$D$22),0)+($D$22-MIN(NJ179,$D$22))*INDEX($C$19:$V$19,2) -> 11200 | F45: =IF(3=1,MIN(NJ179,$D$22),0)+($D$22-MIN(NJ179,$D$22))*INDEX($C$19:$V$19,3) -> 6720 | G45: =IF(4=1,MIN(NJ179,$D$22),0)+($D$22-MIN(NJ179,$D$22))*INDEX($C$19:$V$19,4) -> 4032 | H45: =IF(5=1,MIN(NJ179,$D$22),0)+($D$22-MIN(NJ179,$D$22))*INDEX($C$19:$V$19,5) -> 4032 | I45: =IF(6=1,MIN(NJ179,$D$22),0)+($D$22-MIN(NJ179,$D$22))*INDEX($C$19:$V$19,6) -> 2016 | J45: =IF(7=1,MIN(NJ179,$D$22),0)+($D$22-MIN(NJ179,$D$22))*INDEX($C$19:$V$19,7) -> 0 | K45: =IF(8=1,MIN(NJ179,$D$22),0)+($D$22-MIN(NJ179,$D$22))*INDEX($C$19:$V$19,8) -> 0 | L45: =IF(9=1,MIN(NJ179,$D$22),0)+($D$22-MIN(NJ179,$D$22))*INDEX($C$19:$V$19,9) -> 0 | M45: =IF(10=1,MIN(NJ179,$D$22),0)+($D$22-MIN(NJ179,$D$22))*INDEX($C$19:$V$19,10) -> 0 | N45: =IF(11=1,MIN(NJ179,$D$22),0)+($D$22-MIN(NJ179,$D$22))*INDEX($C$19:$V$19,11) -> 0 | O45: =IF(12=1,MIN(NJ179,$D$22),0)+($D$22-MIN(NJ179,$D$22))*INDEX($C$19:$V$19,12) -> 0 | P45: =IF(13=1,MIN(NJ179,$D$22),0)+($D$22-MIN(NJ179,$D$22))*INDEX($C$19:$V$19,13) -> 0 | Q45: =IF(14=1,MIN(NJ179,$D$22),0)+($D$22-MIN(NJ179,$D$22))*INDEX($C$19:$V$19,14) -> 0 | R45: =IF(15=1,MIN(NJ179,$D$22),0)+($D$22-MIN(NJ179,$D$22))*INDEX($C$19:$V$19,15) -> 0 | S45: =IF(16=1,MIN(NJ179,$D$22),0)+($D$22-MIN(NJ179,$D$22))*INDEX($C$19:$V$19,16) -> 0 | T45: =IF(17=1,MIN(NJ179,$D$22),0)+($D$22-MIN(NJ179,$D$22))*INDEX($C$19:$V$19,17) -> 0
B46: Vintage year 2 | D46: =0 -> 0 | E46: =IF(2=2,MIN(NJ179,$E$22),0)+($E$22-MIN(NJ179,$E$22))*INDEX($C$19:$V$19,1) -> 0 | F46: =IF(3=2,MIN(NJ179,$E$22),0)+($E$22-MIN(NJ179,$E$22))*INDEX($C$19:$V$19,2) -> 0 | G46: =IF(4=2,MIN(NJ179,$E$22),0)+($E$22-MIN(NJ179,$E$22))*INDEX($C$19:$V$19,3) -> 0 | H46: =IF(5=2,MIN(NJ179,$E$22),0)+($E$22-MIN(NJ179,$E$22))*INDEX($C$19:$V$19,4) -> 0 | I46: =IF(6=2,MIN(NJ179,$E$22),0)+($E$22-MIN(NJ179,$E$22))*INDEX($C$19:$V$19,5) -> 0 | J46: =IF(7=2,MIN(NJ179,$E$22),0)+($E$22-MIN(NJ179,$E$22))*INDEX($C$19:$V$19,6) -> 0 | K46: =IF(8=2,MIN(NJ179,$E$22),0)+($E$22-MIN(NJ179,$E$22))*INDEX($C$19:$V$19,7) -> 0 | L46: =IF(9=2,MIN(NJ179,$E$22),0)+($E$22-MIN(NJ179,$E$22))*INDEX($C$19:$V$19,8) -> 0 | M46: =IF(10=2,MIN(NJ179,$E$22),0)+($E$22-MIN(NJ179,$E$22))*INDEX($C$19:$V$19,9) -> 0 | N46: =IF(11=2,MIN(NJ179,$E$22),0)+($E$22-MIN(NJ179,$E$22))*INDEX($C$19:$V$19,10) -> 0 | O46: =IF(12=2,MIN(NJ179,$E$22),0)+($E$22-MIN(NJ179,$E$22))*INDEX($C$19:$V$19,11) -> 0 | P46: =IF(13=2,MIN(NJ179,$E$22),0)+($E$22-MIN(NJ179,$E$22))*INDEX($C$19:$V$19,12) -> 0 | Q46: =IF(14=2,MIN(NJ179,$E$22),0)+($E$22-MIN(NJ179,$E$22))*INDEX($C$19:$V$19,13) -> 0 | R46: =IF(15=2,MIN(NJ179,$E$22),0)+($E$22-MIN(NJ179,$E$22))*INDEX($C$19:$V$19,14) -> 0 | S46: =IF(16=2,MIN(NJ179,$E$22),0)+($E$22-MIN(NJ179,$E$22))*INDEX($C$19:$V$19,15) -> 0 | T46: =IF(17=2,MIN(NJ179,$E$22),0)+($E$22-MIN(NJ179,$E$22))*INDEX($C$19:$V$19,16) -> 0
B47: Vintage year 3 | D47: =0 -> 0 | E47: =0 -> 0 | F47: =IF(3=3,MIN(NJ179,$F$22),0)+($F$22-MIN(NJ179,$F$22))*INDEX($C$19:$V$19,1) -> 0 | G47: =IF(4=3,MIN(NJ179,$F$22),0)+($F$22-MIN(NJ179,$F$22))*INDEX($C$19:$V$19,2) -> 0 | H47: =IF(5=3,MIN(NJ179,$F$22),0)+($F$22-MIN(NJ179,$F$22))*INDEX($C$19:$V$19,3) -> 0 | I47: =IF(6=3,MIN(NJ179,$F$22),0)+($F$22-MIN(NJ179,$F$22))*INDEX($C$19:$V$19,4) -> 0 | J47: =IF(7=3,MIN(NJ179,$F$22),0)+($F$22-MIN(NJ179,$F$22))*INDEX($C$19:$V$19,5) -> 0 | K47: =IF(8=3,MIN(NJ179,$F$22),0)+($F$22-MIN(NJ179,$F$22))*INDEX($C$19:$V$19,6) -> 0 | L47: =IF(9=3,MIN(NJ179,$F$22),0)+($F$22-MIN(NJ179,$F$22))*INDEX($C$19:$V$19,7) -> 0 | M47: =IF(10=3,MIN(NJ179,$F$22),0)+($F$22-MIN(NJ179,$F$22))*INDEX($C$19:$V$19,8) -> 0 | N47: =IF(11=3,MIN(NJ179,$F$22),0)+($F$22-MIN(NJ179,$F$22))*INDEX($C$19:$V$19,9) -> 0 | O47: =IF(12=3,MIN(NJ179,$F$22),0)+($F$22-MIN(NJ179,$F$22))*INDEX($C$19:$V$19,10) -> 0 | P47: =IF(13=3,MIN(NJ179,$F$22),0)+($F$22-MIN(NJ179,$F$22))*INDEX($C$19:$V$19,11) -> 0 | Q47: =IF(14=3,MIN(NJ179,$F$22),0)+($F$22-MIN(NJ179,$F$22))*INDEX($C$19:$V$19,12) -> 0 | R47: =IF(15=3,MIN(NJ179,$F$22),0)+($F$22-MIN(NJ179,$F$22))*INDEX($C$19:$V$19,13) -> 0 | S47: =IF(16=3,MIN(NJ179,$F$22),0)+($F$22-MIN(NJ179,$F$22))*INDEX($C$19:$V$19,14) -> 0 | T47: =IF(17=3,MIN(NJ179,$F$22),0)+($F$22-MIN(NJ179,$F$22))*INDEX($C$19:$V$19,15) -> 0
B48: Vintage year 4 | D48: =0 -> 0 | E48: =0 -> 0 | F48: =0 -> 0 | G48: =IF(4=4,MIN(NJ179,$G$22),0)+($G$22-MIN(NJ179,$G$22))*INDEX($C$19:$V$19,1) -> 103850.41 | H48: =IF(5=4,MIN(NJ179,$G$22),0)+($G$22-MIN(NJ179,$G$22))*INDEX($C$19:$V$19,2) -> 126160.65 | I48: =IF(6=4,MIN(NJ179,$G$22),0)+($G$22-MIN(NJ179,$G$22))*INDEX($C$19:$V$19,3) -> 75696.39 | J48: =IF(7=4,MIN(NJ179,$G$22),0)+($G$22-MIN(NJ179,$G$22))*INDEX($C$19:$V$19,4) -> 45417.834 | K48: =IF(8=4,MIN(NJ179,$G$22),0)+($G$22-MIN(NJ179,$G$22))*INDEX($C$19:$V$19,5) -> 45417.834 | L48: =IF(9=4,MIN(NJ179,$G$22),0)+($G$22-MIN(NJ179,$G$22))*INDEX($C$19:$V$19,6) -> 22708.917 | M48: =IF(10=4,MIN(NJ179,$G$22),0)+($G$22-MIN(NJ179,$G$22))*INDEX($C$19:$V$19,7) -> 0 | N48: =IF(11=4,MIN(NJ179,$G$22),0)+($G$22-MIN(NJ179,$G$22))*INDEX($C$19:$V$19,8) -> 0 | O48: =IF(12=4,MIN(NJ179,$G$22),0)+($G$22-MIN(NJ179,$G$22))*INDEX($C$19:$V$19,9) -> 0 | P48: =IF(13=4,MIN(NJ179,$G$22),0)+($G$22-MIN(NJ179,$G$22))*INDEX($C$19:$V$19,10) -> 0 | Q48: =IF(14=4,MIN(NJ179,$G$22),0)+($G$22-MIN(NJ179,$G$22))*INDEX($C$19:$V$19,11) -> 0 | R48: =IF(15=4,MIN(NJ179,$G$22),0)+($G$22-MIN(NJ179,$G$22))*INDEX($C$19:$V$19,12) -> 0 | S48: =IF(16=4,MIN(NJ179,$G$22),0)+($G$22-MIN(NJ179,$G$22))*INDEX($C$19:$V$19,13) -> 0 | T48: =IF(17=4,MIN(NJ179,$G$22),0)+($G$22-MIN(NJ179,$G$22))*INDEX($C$19:$V$19,14) -> 0
B49: Vintage year 5 | D49: =0 -> 0 | E49: =0 -> 0 | F49: =0 -> 0 | G49: =0 -> 0 | H49: =IF(5=5,MIN(NJ179,$H$22),0)+($H$22-MIN(NJ179,$H$22))*INDEX($C$19:$V$19,1) -> 0 | I49: =IF(6=5,MIN(NJ179,$H$22),0)+($H$22-MIN(NJ179,$H$22))*INDEX($C$19:$V$19,2) -> 0 | J49: =IF(7=5,MIN(NJ179,$H$22),0)+($H$22-MIN(NJ179,$H$22))*INDEX($C$19:$V$19,3) -> 0 | K49: =IF(8=5,MIN(NJ179,$H$22),0)+($H$22-MIN(NJ179,$H$22))*INDEX($C$19:$V$19,4) -> 0 | L49: =IF(9=5,MIN(NJ179,$H$22),0)+($H$22-MIN(NJ179,$H$22))*INDEX($C$19:$V$19,5) -> 0 | M49: =IF(10=5,MIN(NJ179,$H$22),0)+($H$22-MIN(NJ179,$H$22))*INDEX($C$19:$V$19,6) -> 0 | N49: =IF(11=5,MIN(NJ179,$H$22),0)+($H$22-MIN(NJ179,$H$22))*INDEX($C$19:$V$19,7) -> 0 | O49: =IF(12=5,MIN(NJ179,$H$22),0)+($H$22-MIN(NJ179,$H$22))*INDEX($C$19:$V$19,8) -> 0 | P49: =IF(13=5,MIN(NJ179,$H$22),0)+($H$22-MIN(NJ179,$H$22))*INDEX($C$19:$V$19,9) -> 0 | Q49: =IF(14=5,MIN(NJ179,$H$22),0)+($H$22-MIN(NJ179,$H$22))*INDEX($C$19:$V$19,10) -> 0 | R49: =IF(15=5,MIN(NJ179,$H$22),0)+($H$22-MIN(NJ179,$H$22))*INDEX($C$19:$V$19,11) -> 0 | S49: =IF(16=5,MIN(NJ179,$H$22),0)+($H$22-MIN(NJ179,$H$22))*INDEX($C$19:$V$19,12) -> 0 | T49: =IF(17=5,MIN(NJ179,$H$22),0)+($H$22-MIN(NJ179,$H$22))*INDEX($C$19:$V$19,13) -> 0
B50: Vintage year 6 | D50: =0 -> 0 | E50: =0 -> 0 | F50: =0 -> 0 | G50: =0 -> 0 | H50: =0 -> 0 | I50: =IF(6=6,MIN(NJ179,$I$22),0)+($I$22-MIN(NJ179,$I$22))*INDEX($C$19:$V$19,1) -> 0 | J50: =IF(7=6,MIN(NJ179,$I$22),0)+($I$22-MIN(NJ179,$I$22))*INDEX($C$19:$V$19,2) -> 0 | K50: =IF(8=6,MIN(NJ179,$I$22),0)+($I$22-MIN(NJ179,$I$22))*INDEX($C$19:$V$19,3) -> 0 | L50: =IF(9=6,MIN(NJ179,$I$22),0)+($I$22-MIN(NJ179,$I$22))*INDEX($C$19:$V$19,4) -> 0 | M50: =IF(10=6,MIN(NJ179,$I$22),0)+($I$22-MIN(NJ179,$I$22))*INDEX($C$19:$V$19,5) -> 0 | N50: =IF(11=6,MIN(NJ179,$I$22),0)+($I$22-MIN(NJ179,$I$22))*INDEX($C$19:$V$19,6) -> 0 | O50: =IF(12=6,MIN(NJ179,$I$22),0)+($I$22-MIN(NJ179,$I$22))*INDEX($C$19:$V$19,7) -> 0 | P50: =IF(13=6,MIN(NJ179,$I$22),0)+($I$22-MIN(NJ179,$I$22))*INDEX($C$19:$V$19,8) -> 0 | Q50: =IF(14=6,MIN(NJ179,$I$22),0)+($I$22-MIN(NJ179,$I$22))*INDEX($C$19:$V$19,9) -> 0 | R50: =IF(15=6,MIN(NJ179,$I$22),0)+($I$22-MIN(NJ179,$I$22))*INDEX($C$19:$V$19,10) -> 0 | S50: =IF(16=6,MIN(NJ179,$I$22),0)+($I$22-MIN(NJ179,$I$22))*INDEX($C$19:$V$19,11) -> 0 | T50: =IF(17=6,MIN(NJ179,$I$22),0)+($I$22-MIN(NJ179,$I$22))*INDEX($C$19:$V$19,12) -> 0
B51: Vintage year 7 | D51: =0 -> 0 | E51: =0 -> 0 | F51: =0 -> 0 | G51: =0 -> 0 | H51: =0 -> 0 | I51: =0 -> 0 | J51: =IF(7=7,MIN(NJ179,$J$22),0)+($J$22-MIN(NJ179,$J$22))*INDEX($C$19:$V$19,1) -> 0 | K51: =IF(8=7,MIN(NJ179,$J$22),0)+($J$22-MIN(NJ179,$J$22))*INDEX($C$19:$V$19,2) -> 0 | L51: =IF(9=7,MIN(NJ179,$J$22),0)+($J$22-MIN(NJ179,$J$22))*INDEX($C$19:$V$19,3) -> 0 | M51: =IF(10=7,MIN(NJ179,$J$22),0)+($J$22-MIN(NJ179,$J$22))*INDEX($C$19:$V$19,4) -> 0 | N51: =IF(11=7,MIN(NJ179,$J$22),0)+($J$22-MIN(NJ179,$J$22))*INDEX($C$19:$V$19,5) -> 0 | O51: =IF(12=7,MIN(NJ179,$J$22),0)+($J$22-MIN(NJ179,$J$22))*INDEX($C$19:$V$19,6) -> 0 | P51: =IF(13=7,MIN(NJ179,$J$22),0)+($J$22-MIN(NJ179,$J$22))*INDEX($C$19:$V$19,7) -> 0 | Q51: =IF(14=7,MIN(NJ179,$J$22),0)+($J$22-MIN(NJ179,$J$22))*INDEX($C$19:$V$19,8) -> 0 | R51: =IF(15=7,MIN(NJ179,$J$22),0)+($J$22-MIN(NJ179,$J$22))*INDEX($C$19:$V$19,9) -> 0 | S51: =IF(16=7,MIN(NJ179,$J$22),0)+($J$22-MIN(NJ179,$J$22))*INDEX($C$19:$V$19,10) -> 0 | T51: =IF(17=7,MIN(NJ179,$J$22),0)+($J$22-MIN(NJ179,$J$22))*INDEX($C$19:$V$19,11) -> 0
B52: Vintage year 8 | D52: =0 -> 0 | E52: =0 -> 0 | F52: =0 -> 0 | G52: =0 -> 0 | H52: =0 -> 0 | I52: =0 -> 0 | J52: =0 -> 0 | K52: =IF(8=8,MIN(NJ179,$K$22),0)+($K$22-MIN(NJ179,$K$22))*INDEX($C$19:$V$19,1) -> 0 | L52: =IF(9=8,MIN(NJ179,$K$22),0)+($K$22-MIN(NJ179,$K$22))*INDEX($C$19:$V$19,2) -> 0 | M52: =IF(10=8,MIN(NJ179,$K$22),0)+($K$22-MIN(NJ179,$K$22))*INDEX($C$19:$V$19,3) -> 0 | N52: =IF(11=8,MIN(NJ179,$K$22),0)+($K$22-MIN(NJ179,$K$22))*INDEX($C$19:$V$19,4) -> 0 | O52: =IF(12=8,MIN(NJ179,$K$22),0)+($K$22-MIN(NJ179,$K$22))*INDEX($C$19:$V$19,5) -> 0 | P52: =IF(13=8,MIN(NJ179,$K$22),0)+($K$22-MIN(NJ179,$K$22))*INDEX($C$19:$V$19,6) -> 0 | Q52: =IF(14=8,MIN(NJ179,$K$22),0)+($K$22-MIN(NJ179,$K$22))*INDEX($C$19:$V$19,7) -> 0 | R52: =IF(15=8,MIN(NJ179,$K$22),0)+($K$22-MIN(NJ179,$K$22))*INDEX($C$19:$V$19,8) -> 0 | S52: =IF(16=8,MIN(NJ179,$K$22),0)+($K$22-MIN(NJ179,$K$22))*INDEX($C$19:$V$19,9) -> 0 | T52: =IF(17=8,MIN(NJ179,$K$22),0)+($K$22-MIN(NJ179,$K$22))*INDEX($C$19:$V$19,10) -> 0
B53: Vintage year 9 | D53: =0 -> 0 | E53: =0 -> 0 | F53: =0 -> 0 | G53: =0 -> 0 | H53: =0 -> 0 | I53: =0 -> 0 | J53: =0 -> 0 | K53: =0 -> 0 | L53: =IF(9=9,MIN(NJ179,$L$22),0)+($L$22-MIN(NJ179,$L$22))*INDEX($C$19:$V$19,1) -> 0 | M53: =IF(10=9,MIN(NJ179,$L$22),0)+($L$22-MIN(NJ179,$L$22))*INDEX($C$19:$V$19,2) -> 0 | N53: =IF(11=9,MIN(NJ179,$L$22),0)+($L$22-MIN(NJ179,$L$22))*INDEX($C$19:$V$19,3) -> 0 | O53: =IF(12=9,MIN(NJ179,$L$22),0)+($L$22-MIN(NJ179,$L$22))*INDEX($C$19:$V$19,4) -> 0 | P53: =IF(13=9,MIN(NJ179,$L$22),0)+($L$22-MIN(NJ179,$L$22))*INDEX($C$19:$V$19,5) -> 0 | Q53: =IF(14=9,MIN(NJ179,$L$22),0)+($L$22-MIN(NJ179,$L$22))*INDEX($C$19:$V$19,6) -> 0 | R53: =IF(15=9,MIN(NJ179,$L$22),0)+($L$22-MIN(NJ179,$L$22))*INDEX($C$19:$V$19,7) -> 0 | S53: =IF(16=9,MIN(NJ179,$L$22),0)+($L$22-MIN(NJ179,$L$22))*INDEX($C$19:$V$19,8) -> 0 | T53: =IF(17=9,MIN(NJ179,$L$22),0)+($L$22-MIN(NJ179,$L$22))*INDEX($C$19:$V$19,9) -> 0
B54: Vintage year 10 | D54: =0 -> 0 | E54: =0 -> 0 | F54: =0 -> 0 | G54: =0 -> 0 | H54: =0 -> 0 | I54: =0 -> 0 | J54: =0 -> 0 | K54: =0 -> 0 | L54: =0 -> 0 | M54: =IF(10=10,MIN(NJ179,$M$22),0)+($M$22-MIN(NJ179,$M$22))*INDEX($C$19:$V$19,1) -> 0 | N54: =IF(11=10,MIN(NJ179,$M$22),0)+($M$22-MIN(NJ179,$M$22))*INDEX($C$19:$V$19,2) -> 0 | O54: =IF(12=10,MIN(NJ179,$M$22),0)+($M$22-MIN(NJ179,$M$22))*INDEX($C$19:$V$19,3) -> 0 | P54: =IF(13=10,MIN(NJ179,$M$22),0)+($M$22-MIN(NJ179,$M$22))*INDEX($C$19:$V$19,4) -> 0 | Q54: =IF(14=10,MIN(NJ179,$M$22),0)+($M$22-MIN(NJ179,$M$22))*INDEX($C$19:$V$19,5) -> 0 | R54: =IF(15=10,MIN(NJ179,$M$22),0)+($M$22-MIN(NJ179,$M$22))*INDEX($C$19:$V$19,6) -> 0 | S54: =IF(16=10,MIN(NJ179,$M$22),0)+($M$22-MIN(NJ179,$M$22))*INDEX($C$19:$V$19,7) -> 0 | T54: =IF(17=10,MIN(NJ179,$M$22),0)+($M$22-MIN(NJ179,$M$22))*INDEX($C$19:$V$19,8) -> 0
B55: Vintage year 11 | D55: =0 -> 0 | E55: =0 -> 0 | F55: =0 -> 0 | G55: =0 -> 0 | H55: =0 -> 0 | I55: =0 -> 0 | J55: =0 -> 0 | K55: =0 -> 0 | ... M55: =0 -> 0 | N55: =IF(11=11,MIN(NJ179,$N$22),0)+($N$22-MIN(NJ179,$N$22))*INDEX($C$19:$V$19,1) -> 67340.798 | O55: =IF(12=11,MIN(NJ179,$N$22),0)+($N$22-MIN(NJ179,$N$22))*INDEX($C$19:$V$19,2) -> 67745.277 | P55: =IF(13=11,MIN(NJ179,$N$22),0)+($N$22-MIN(NJ179,$N$22))*INDEX($C$19:$V$19,3) -> 40647.166 | Q55: =IF(14=11,MIN(NJ179,$N$22),0)+($N$22-MIN(NJ179,$N$22))*INDEX($C$19:$V$19,4) -> 24388.3 | R55: =IF(15=11,MIN(NJ179,$N$22),0)+($N$22-MIN(NJ179,$N$22))*INDEX($C$19:$V$19,5) -> 24388.3 | S55: =IF(16=11,MIN(NJ179,$N$22),0)+($N$22-MIN(NJ179,$N$22))*INDEX($C$19:$V$19,6) -> 12194.15 | T55: =IF(17=11,MIN(NJ179,$N$22),0)+($N$22-MIN(NJ179,$N$22))*INDEX($C$19:$V$19,7) -> 0
B56: Vintage year 12 | D56: =0 -> 0 | E56: =0 -> 0 | F56: =0 -> 0 | G56: =0 -> 0 | H56: =0 -> 0 | I56: =0 -> 0 | J56: =0 -> 0 | K56: =0 -> 0 | ... N56: =0 -> 0 | O56: =IF(12=12,MIN(NJ179,$O$22),0)+($O$22-MIN(NJ179,$O$22))*INDEX($C$19:$V$19,1) -> 0 | P56: =IF(13=12,MIN(NJ179,$O$22),0)+($O$22-MIN(NJ179,$O$22))*INDEX($C$19:$V$19,2) -> 0 | Q56: =IF(14=12,MIN(NJ179,$O$22),0)+($O$22-MIN(NJ179,$O$22))*INDEX($C$19:$V$19,3) -> 0 | R56: =IF(15=12,MIN(NJ179,$O$22),0)+($O$22-MIN(NJ179,$O$22))*INDEX($C$19:$V$19,4) -> 0 | S56: =IF(16=12,MIN(NJ179,$O$22),0)+($O$22-MIN(NJ179,$O$22))*INDEX($C$19:$V$19,5) -> 0 | T56: =IF(17=12,MIN(NJ179,$O$22),0)+($O$22-MIN(NJ179,$O$22))*INDEX($C$19:$V$19,6) -> 0
B57: Vintage year 13 | D57: =0 -> 0 | E57: =0 -> 0 | F57: =0 -> 0 | G57: =0 -> 0 | H57: =0 -> 0 | I57: =0 -> 0 | J57: =0 -> 0 | K57: =0 -> 0 | ... O57: =0 -> 0 | P57: =IF(13=13,MIN(NJ179,$P$22),0)+($P$22-MIN(NJ179,$P$22))*INDEX($C$19:$V$19,1) -> 0 | Q57: =IF(14=13,MIN(NJ179,$P$22),0)+($P$22-MIN(NJ179,$P$22))*INDEX($C$19:$V$19,2) -> 0 | R57: =IF(15=13,MIN(NJ179,$P$22),0)+($P$22-MIN(NJ179,$P$22))*INDEX($C$19:$V$19,3) -> 0 | S57: =IF(16=13,MIN(NJ179,$P$22),0)+($P$22-MIN(NJ179,$P$22))*INDEX($C$19:$V$19,4) -> 0 | T57: =IF(17=13,MIN(NJ179,$P$22),0)+($P$22-MIN(NJ179,$P$22))*INDEX($C$19:$V$19,5) -> 0
B58: Vintage year 14 | D58: =0 -> 0 | E58: =0 -> 0 | F58: =0 -> 0 | G58: =0 -> 0 | H58: =0 -> 0 | I58: =0 -> 0 | J58: =0 -> 0 | K58: =0 -> 0 | ... P58: =0 -> 0 | Q58: =IF(14=14,MIN(NJ179,$Q$22),0)+($Q$22-MIN(NJ179,$Q$22))*INDEX($C$19:$V$19,1) -> 0 | R58: =IF(15=14,MIN(NJ179,$Q$22),0)+($Q$22-MIN(NJ179,$Q$22))*INDEX($C$19:$V$19,2) -> 0 | S58: =IF(16=14,MIN(NJ179,$Q$22),0)+($Q$22-MIN(NJ179,$Q$22))*INDEX($C$19:$V$19,3) -> 0 | T58: =IF(17=14,MIN(NJ179,$Q$22),0)+($Q$22-MIN(NJ179,$Q$22))*INDEX($C$19:$V$19,4) -> 0
B59: Vintage year 15 | D59: =0 -> 0 | E59: =0 -> 0 | F59: =0 -> 0 | G59: =0 -> 0 | H59: =0 -> 0 | I59: =0 -> 0 | J59: =0 -> 0 | K59: =0 -> 0 | ... Q59: =0 -> 0 | R59: =IF(15=15,MIN(NJ179,$R$22),0)+($R$22-MIN(NJ179,$R$22))*INDEX($C$19:$V$19,1) -> 0 | S59: =IF(16=15,MIN(NJ179,$R$22),0)+($R$22-MIN(NJ179,$R$22))*INDEX($C$19:$V$19,2) -> 0 | T59: =IF(17=15,MIN(NJ179,$R$22),0)+($R$22-MIN(NJ179,$R$22))*INDEX($C$19:$V$19,3) -> 0
B60: Vintage year 16 | D60: =0 -> 0 | E60: =0 -> 0 | F60: =0 -> 0 | G60: =0 -> 0 | H60: =0 -> 0 | I60: =0 -> 0 | J60: =0 -> 0 | K60: =0 -> 0 | ... R60: =0 -> 0 | S60: =IF(16=16,MIN(NJ179,$S$22),0)+($S$22-MIN(NJ179,$S$22))*INDEX($C$19:$V$19,1) -> 0 | T60: =IF(17=16,MIN(NJ179,$S$22),0)+($S$22-MIN(NJ179,$S$22))*INDEX($C$19:$V$19,2) -> 0
B61: Vintage year 17 | D61: =0 -> 0 | E61: =0 -> 0 | F61: =0 -> 0 | G61: =0 -> 0 | H61: =0 -> 0 | I61: =0 -> 0 | J61: =0 -> 0 | K61: =0 -> 0 | ... S61: =0 -> 0 | T61: =IF(17=17,MIN(NJ179,$T$22),0)+($T$22-MIN(NJ179,$T$22))*INDEX($C$19:$V$19,1) -> 0
B62: Total machine depreciation (NJ) | D62: =SUM(D45:D61) -> 32000 | E62: =SUM(E45:E61) -> 11200 | F62: =SUM(F45:F61) -> 6720 | G62: =SUM(G45:G61) -> 107882.41 | H62: =SUM(H45:H61) -> 130192.65 | I62: =SUM(I45:I61) -> 77712.39 | J62: =SUM(J45:J61) -> 45417.834 | K62: =SUM(K45:K61) -> 45417.834 | ... T62: =SUM(T45:T61) -> 0
B64: Leasehold improvements and Sec. 197 intangibles
B65: Federal: leasehold improvements (QIP, bonus) | D65: =AllocLHI*(IF(1=1,Bonus,0)+(1-Bonus)*INDEX($C$18:$V$18,1)) -> 25000 | E65: =AllocLHI*(IF(2=1,Bonus,0)+(1-Bonus)*INDEX($C$18:$V$18,2)) -> 0 | F65: =AllocLHI*(IF(3=1,Bonus,0)+(1-Bonus)*INDEX($C$18:$V$18,3)) -> 0 | G65: =AllocLHI*(IF(4=1,Bonus,0)+(1-Bonus)*INDEX($C$18:$V$18,4)) -> 0 | H65: =AllocLHI*(IF(5=1,Bonus,0)+(1-Bonus)*INDEX($C$18:$V$18,5)) -> 0 | I65: =AllocLHI*(IF(6=1,Bonus,0)+(1-Bonus)*INDEX($C$18:$V$18,6)) -> 0 | J65: =AllocLHI*(IF(7=1,Bonus,0)+(1-Bonus)*INDEX($C$18:$V$18,7)) -> 0 | K65: =AllocLHI*(IF(8=1,Bonus,0)+(1-Bonus)*INDEX($C$18:$V$18,8)) -> 0 | L65: =AllocLHI*(IF(9=1,Bonus,0)+(1-Bonus)*INDEX($C$18:$V$18,9)) -> 0 | M65: =AllocLHI*(IF(10=1,Bonus,0)+(1-Bonus)*INDEX($C$18:$V$18,10)) -> 0 | N65: =AllocLHI*(IF(11=1,Bonus,0)+(1-Bonus)*INDEX($C$18:$V$18,11)) -> 0 | O65: =AllocLHI*(IF(12=1,Bonus,0)+(1-Bonus)*INDEX($C$18:$V$18,12)) -> 0 | P65: =AllocLHI*(IF(13=1,Bonus,0)+(1-Bonus)*INDEX($C$18:$V$18,13)) -> 0 | Q65: =AllocLHI*(IF(14=1,Bonus,0)+(1-Bonus)*INDEX($C$18:$V$18,14)) -> 0 | R65: =AllocLHI*(IF(15=1,Bonus,0)+(1-Bonus)*INDEX($C$18:$V$18,15)) -> 0 | S65: =AllocLHI*(IF(16=1,Bonus,0)+(1-Bonus)*INDEX($C$18:$V$18,16)) -> 0 | T65: =AllocLHI*(IF(17=1,Bonus,0)+(1-Bonus)*INDEX($C$18:$V$18,17)) -> 0
B66: NJ: leasehold improvements (15-yr SL) | D66: =AllocLHI*INDEX($C$18:$V$18,1) -> 833.33333 | E66: =AllocLHI*INDEX($C$18:$V$18,2) -> 1666.6667 | F66: =AllocLHI*INDEX($C$18:$V$18,3) -> 1666.6667 | G66: =AllocLHI*INDEX($C$18:$V$18,4) -> 1666.6667 | H66: =AllocLHI*INDEX($C$18:$V$18,5) -> 1666.6667 | I66: =AllocLHI*INDEX($C$18:$V$18,6) -> 1666.6667 | J66: =AllocLHI*INDEX($C$18:$V$18,7) -> 1666.6667 | K66: =AllocLHI*INDEX($C$18:$V$18,8) -> 1666.6667 | L66: =AllocLHI*INDEX($C$18:$V$18,9) -> 1666.6667 | M66: =AllocLHI*INDEX($C$18:$V$18,10) -> 1666.6667 | N66: =AllocLHI*INDEX($C$18:$V$18,11) -> 1666.6667 | O66: =AllocLHI*INDEX($C$18:$V$18,12) -> 1666.6667 | P66: =AllocLHI*INDEX($C$18:$V$18,13) -> 1666.6667 | Q66: =AllocLHI*INDEX($C$18:$V$18,14) -> 1666.6667 | R66: =AllocLHI*INDEX($C$18:$V$18,15) -> 1666.6667 | S66: =AllocLHI*INDEX($C$18:$V$18,16) -> 833.33333 | T66: =AllocLHI*INDEX($C$18:$V$18,17) -> 0
B67: Goodwill + non-compete + closing costs (15-yr, both) | D67: =IF(1<=15,(Goodwill+AllocNoncompete)/15,0) -> 25666.667 | E67: =IF(2<=15,(Goodwill+AllocNoncompete)/15,0) -> 25666.667 | F67: =IF(3<=15,(Goodwill+AllocNoncompete)/15,0) -> 25666.667 | G67: =IF(4<=15,(Goodwill+AllocNoncompete)/15,0) -> 25666.667 | H67: =IF(5<=15,(Goodwill+AllocNoncompete)/15,0) -> 25666.667 | I67: =IF(6<=15,(Goodwill+AllocNoncompete)/15,0) -> 25666.667 | J67: =IF(7<=15,(Goodwill+AllocNoncompete)/15,0) -> 25666.667 | K67: =IF(8<=15,(Goodwill+AllocNoncompete)/15,0) -> 25666.667 | L67: =IF(9<=15,(Goodwill+AllocNoncompete)/15,0) -> 25666.667 | M67: =IF(10<=15,(Goodwill+AllocNoncompete)/15,0) -> 25666.667 | N67: =IF(11<=15,(Goodwill+AllocNoncompete)/15,0) -> 25666.667 | O67: =IF(12<=15,(Goodwill+AllocNoncompete)/15,0) -> 25666.667 | P67: =IF(13<=15,(Goodwill+AllocNoncompete)/15,0) -> 25666.667 | Q67: =IF(14<=15,(Goodwill+AllocNoncompete)/15,0) -> 25666.667 | R67: =IF(15<=15,(Goodwill+AllocNoncompete)/15,0) -> 25666.667 | S67: =IF(16<=15,(Goodwill+AllocNoncompete)/15,0) -> 0 | T67: =IF(17<=15,(Goodwill+AllocNoncompete)/15,0) -> 0
B69: TOTAL FEDERAL depreciation & amortization | D69: =D42+D65+D67 -> 110666.67 | E69: =E42+E65+E67 -> 25666.667 | F69: =F42+F65+F67 -> 25666.667 | G69: =G42+G65+G67 -> 444918.7 | H69: =H42+H65+H67 -> 25666.667 | I69: =I42+I65+I67 -> 25666.667 | J69: =J42+J65+J67 -> 25666.667 | K69: =K42+K65+K67 -> 25666.667 | ... T69: =T42+T65+T67 -> 0
B70: TOTAL NJ depreciation & amortization | D70: =D62+D66+D67 -> 58500 | E70: =E62+E66+E67 -> 38533.333 | F70: =F62+F66+F67 -> 34053.333 | G70: =G62+G66+G67 -> 135215.74 | H70: =H62+H66+H67 -> 157525.98 | I70: =I62+I66+I67 -> 105045.72 | J70: =J62+J66+J67 -> 72751.167 | K70: =K62+K66+K67 -> 72751.167 | ... T70: =T62+T66+T67 -> 0
B71: Cumulative depreciable property (UBIA proxy for QBI wage/property test) | D71: =SUM($D$22:D$22)+AllocLHI -> 85000 | E71: =SUM($D$22:E$22)+AllocLHI -> 85000 | F71: =SUM($D$22:F$22)+AllocLHI -> 85000 | G71: =SUM($D$22:G$22)+AllocLHI -> 504252.03 | H71: =SUM($D$22:H$22)+AllocLHI -> 504252.03 | I71: =SUM($D$22:I$22)+AllocLHI -> 504252.03 | J71: =SUM($D$22:J$22)+AllocLHI -> 504252.03 | K71: =SUM($D$22:K$22)+AllocLHI -> 504252.03 | ... T71: =SUM($D$22:T$22)+AllocLHI -> 740956.02
B73: Check: federal total over 17 yrs vs. state total (should match once fully recovered) | C73: =SUM(D69:T69)-SUM(D70:T70) -> 0

Sheet Comps
B2: Comparable laundromat listings and sales
B3: Asking prices unless noted. 'Sold*' = broker marked sold; closing price not disclosed. Full table: /mnt/project-files/underwriting/research/comps.md
B5: Location | C5: Price | D5: Gross | E5: Cash flow | F5: P/CF | G5: P/Gross | H5: Notes | I5: Status | J5: Source
B6: Jersey City (SUBJECT, broker figures) | C6: 450000 | D6: 372000 | E6: 177000 | F6: =IF(ISNUMBER(E6),C6/E6,"n/a") -> 2.5423729 | G6: =IF(ISNUMBER(D6),C6/D6,"n/a") -> 1.2096774 | H6: ~2,000 sf; 33W/36D ~15 yr; 17 yr lease, $2,758/mo | I6: Asking | J6: https://www.bizbuysell.com/business-opportunity/profitable-laundromat-run-absentee-high-revenue-jersey-city-nj-450k/2564518/
B7: Hudson County, NJ | C7: 550000 | D7: 294000 | E7: 102000 | F7: =IF(ISNUMBER(E7),C7/E7,"n/a") -> 5.3921569 | G7: =IF(ISNUMBER(D7),C7/D7,"n/a") -> 1.8707483 | H7: 48 machines, energy-efficient | I7: Sold* | J7: https://www.hedgestone.com/business-opportunity/63086/profitable-absentee-run-laundromat-for-sale-in-new-jersey/
B8: Hudson County, NJ (downtown) | C8: 50000 | D8: 104000 | E8: 43000 | F8: =IF(ISNUMBER(E8),C8/E8,"n/a") -> 1.1627907 | G8: =IF(ISNUMBER(D8),C8/D8,"n/a") -> 0.48076923 | H8: 15W/16D; ~5.5 yr lease left | I8: Sold* | J8: https://www.vestedbb.com/very-successful-laundromat-for-sale-in-hudson-county-new-jersey-listing-id-7091
B9: Bayonne, NJ | C9: 179000 | D9: 175000 | E9: 16000 | F9: =IF(ISNUMBER(E9),C9/E9,"n/a") -> 11.1875 | G9: =IF(ISNUMBER(D9),C9/D9,"n/a") -> 1.0228571 | H9: Search-page figures only | I9: Asking | J9: https://www.bizbuysell.com/business-opportunity/laundromat-in-great-location-excellent-potential-bayonne-nj-179-000/2556056/
B10: Bergen County, NJ (plaza) | C10: 950000 | D10: 498922 | E10: 173422 | F10: =IF(ISNUMBER(E10),C10/E10,"n/a") -> 5.477967 | G10: =IF(ISNUMBER(D10),C10/D10,"n/a") -> 1.9041053 | H10: 4,000 sf; 50W/52D 3-7 yr; lease to 2041; rent 24% | I10: Asking | J10: https://www.bizbuysell.com/business-opportunity/4-000-sf-laundromat-for-sale-busy-shopping-plaza-with-parking/2521410/
B11: Union County, NJ | C11: 650000 | D11: 416000 | E11: 150000 | F11: =IF(ISNUMBER(E11),C11/E11,"n/a") -> 4.3333333 | G11: =IF(ISNUMBER(D11),C11/D11,"n/a") -> 1.5625 | H11: 2,800 sf; 41W/46D | I11: Sold* | J11: https://www.hedgestone.com/business-opportunity/62794/coin-operated-new-jersey-laundromat-for-sale/
B12: Bergen County, NJ | C12: 110000 | D12: 153000 | E12: 58045 | F12: =IF(ISNUMBER(E12),C12/E12,"n/a") -> 1.8950814 | G12: =IF(ISNUMBER(D12),C12/D12,"n/a") -> 0.71895425 | I12: Sold* | J12: https://www.vestedbb.com/great-laundromat-for-sale-in-bergen-county-new-jersey-listing-id-7167
B13: Ridgefield Park, NJ (24-hr) | C13: 275000 | D13: n/a | E13: 52000 | F13: =IF(ISNUMBER(E13),C13/E13,"n/a") -> 5.2884615 | G13: =IF(ISNUMBER(D13),C13/D13,"n/a") -> n/a | H13: Unattended | I13: Asking | J13: https://www.bizbuysell.com/business-opportunity/stress-free-absentee-laundromat-open-24-hours/2560849/
B14: Paterson, NJ | C14: 295000 | D14: 300000 | E14: n/a | F14: =IF(ISNUMBER(E14),C14/E14,"n/a") -> n/a | G14: =IF(ISNUMBER(D14),C14/D14,"n/a") -> 0.98333333 | H14: 20-25 yr equipment; '2x net' | I14: Sold* | J14: https://www.laundromat-broker.com/listings.html
B15: South NJ (near Waterford) | C15: 297500 | D15: 190000 | E15: 90000 | F15: =IF(ISNUMBER(E15),C15/E15,"n/a") -> 3.3055556 | G15: =IF(ISNUMBER(D15),C15/D15,"n/a") -> 1.5657895 | H15: 19 mo lease left | I15: Sold* 2025 | J15: https://www.laundromat-broker.com/listings.html
B16: Bronx, NY (same broker template) | C16: 450000 | D16: 400000 | E16: 177000 | F16: =IF(ISNUMBER(E16),C16/E16,"n/a") -> 2.5423729 | G16: =IF(ISNUMBER(D16),C16/D16,"n/a") -> 1.125 | H16: 32W/34D 11-12 yr; 3 yr lease | I16: Asking | J16: https://www.bizbuysell.com/business-opportunity/absentee-and-high-volume-laundromat-excellent-profit-bronx-ny-450k/2564395/
B17: Park Slope, Brooklyn | C17: 799000 | D17: 467000 | E17: 156000 | F17: =IF(ISNUMBER(E17),C17/E17,"n/a") -> 5.1217949 | G17: =IF(ISNUMBER(D17),C17/D17,"n/a") -> 1.7109208 | H17: Newer equipment, long lease | I17: Asking | J17: https://www.bizbuysell.com/new-york/new-york-city-metro-area/laundromats-and-coin-laundry-businesses-for-sale/
B18: Queens (prime) | C18: 589999 | D18: 420000 | E18: 130000 | F18: =IF(ISNUMBER(E18),C18/E18,"n/a") -> 4.5384538 | G18: =IF(ISNUMBER(D18),C18/D18,"n/a") -> 1.4047595 | H18: 64 machines; new 10-yr lease | I18: Asking | J18: https://www.bizbuysell.com/new-york/new-york-city-metro-area/laundromats-and-coin-laundry-businesses-for-sale/
B19: Prospect Park 11226 | C19: 449300 | D19: n/a | E19: 160840 | F19: =IF(ISNUMBER(E19),C19/E19,"n/a") -> 2.7934593 | G19: =IF(ISNUMBER(D19),C19/D19,"n/a") -> n/a | H19: 75 machines; 12 yr lease | I19: Asking | J19: https://www.bizbuysell.com/new-york/new-york-city-metro-area/laundromats-and-coin-laundry-businesses-for-sale/
B20: Brooklyn 11219 | C20: 349500 | D20: n/a | E20: 112950 | F20: =IF(ISNUMBER(E20),C20/E20,"n/a") -> 3.0942895 | G20: =IF(ISNUMBER(D20),C20/D20,"n/a") -> n/a | H20: 41 machines; 15-yr lease option | I20: Asking | J20: https://www.bizbuysell.com/new-york/new-york-city-metro-area/laundromats-and-coin-laundry-businesses-for-sale/
B21: Median of comps (excl. subject) | F21: =MEDIAN(F7:F20) -> 4.3333333 | G21: =MEDIAN(G7:G20) -> 1.4047595
B23: Benchmarks
B24: BizBuySell national closed deals 2021-25 (n=855): median price/SDE | H24: 3.50x (IQR 2.72-4.50x); 2025 avg 4.12x
B25: BizBuySell national: median price/revenue | H25: 1.21x; sale price ~92% of ask
B26: NYC-metro asking, Oct 2026 (n=28): median price/cash flow | H26: 3.5x (range 1.45-7.0x)
B27: Laundromat Resource rule of thumb: 13-16 yr equipment | H27: 3.5-4.0x NOI
B28: Laundromat Resource rule of thumb: 15+ yr lease; rent <=25% of gross | H28: 4.5-5.0x NOI
B29: Utilities, % of gross (2023 operator survey) | H29: 21.6% avg; ~15% with new machines
B30: BizBuySell EDGE, NJ laundromat listings: revenue (25th / median / 75th pct) | H30: $172K / $312K / $495K (listing PDF, 10/14/2026)
B31: BizBuySell EDGE, NJ laundromat listings: SDE (25th / median / 75th pct) | H31: $62.5K / $107K / $246K
B32: BizBuySell EDGE, operating NJ laundromats 2024 averages | H32: Revenue $570K; SDE $127K; EBITDA $81K (14% of revenue)
